Compiled from "Gepo.java"
public class org.reassembler.gepo.Gepo extends java.lang.Object
  SourceFile: "Gepo.java"
  InnerClass: 
   #105= #46 of #103; //Default=class org/reassembler/gepo/Gepo$Default of class org/reassembler/gepo/Gepo
   #72; //class org/reassembler/gepo/Gepo$1
  minor version: 3
  major version: 45
  Constant pool:
const #1 = String	#198;	//  org.reassembler.gepo.files
const #2 = String	#199;	//  .
const #3 = Method	#200.#201;	//  java/lang/System.getProperty:(Ljava/lang/String;Ljava/lang/String;)Ljava/lang/String;
const #4 = Method	#103.#202;	//  org/reassembler/gepo/Gepo."<init>":(Ljava/lang/String;)V
const #5 = Method	#104.#203;	//  java/lang/Object."<init>":()V
const #6 = class	#204;	//  java/util/TreeMap
const #7 = Method	#6.#203;	//  java/util/TreeMap."<init>":()V
const #8 = Field	#103.#205;	//  org/reassembler/gepo/Gepo.props:Ljava/util/Map;
const #9 = class	#206;	//  java/util/ArrayList
const #10 = Method	#9.#203;	//  java/util/ArrayList."<init>":()V
const #11 = Field	#103.#207;	//  org/reassembler/gepo/Gepo.loaded:Ljava/util/ArrayList;
const #12 = Field	#103.#208;	//  org/reassembler/gepo/Gepo.skipped:Ljava/util/ArrayList;
const #13 = Field	#103.#209;	//  org/reassembler/gepo/Gepo.filesPath:Ljava/lang/String;
const #14 = Method	#103.#210;	//  org/reassembler/gepo/Gepo.loadProperties:()V
const #15 = class	#211;	//  java/lang/StringBuffer
const #16 = Method	#15.#203;	//  java/lang/StringBuffer."<init>":()V
const #17 = String	#212;	//  loaded:
const #18 = Method	#15.#213;	//  java/lang/StringBuffer.append:(Ljava/lang/String;)Ljava/lang/StringBuffer;
const #19 = Method	#15.#214;	//  java/lang/StringBuffer.append:(Ljava/lang/Object;)Ljava/lang/StringBuffer;
const #20 = String	#215;	//  ,skipped:
const #21 = String	#216;	//  ,filesPath:
const #22 = String	#217;	//  ,properties: 
const #23 = Method	#103.#218;	//  org/reassembler/gepo/Gepo.toProperties:()Ljava/util/Properties;
const #24 = Method	#219.#220;	//  java/util/Hashtable.toString:()Ljava/lang/String;
const #25 = Method	#15.#220;	//  java/lang/StringBuffer.toString:()Ljava/lang/String;
const #26 = Method	#9.#221;	//  java/util/ArrayList.size:()I
const #27 = class	#222;	//  java/lang/String
const #28 = Method	#9.#223;	//  java/util/ArrayList.toArray:([Ljava/lang/Object;)[Ljava/lang/Object;
const #29 = class	#146;	//  "[Ljava/lang/String;"
const #30 = String	#224;	//  ,
const #31 = Method	#27.#225;	//  java/lang/String.split:(Ljava/lang/String;)[Ljava/lang/String;
const #32 = class	#226;	//  java/net/URL
const #33 = Method	#32.#202;	//  java/net/URL."<init>":(Ljava/lang/String;)V
const #34 = Method	#103.#227;	//  org/reassembler/gepo/Gepo.loadPropertiesFromUrl:(Ljava/net/URL;)V
const #35 = class	#228;	//  java/net/MalformedURLException
const #36 = Method	#103.#229;	//  org/reassembler/gepo/Gepo.loadPropertyFiles:(Ljava/lang/String;)V
const #37 = class	#230;	//  java/lang/Exception
const #38 = Field	#103.#231;	//  org/reassembler/gepo/Gepo.log:Ljava/util/logging/Logger;
const #39 = Field	#232.#233;	//  java/util/logging/Level.SEVERE:Ljava/util/logging/Level;
const #40 = String	#234;	//  problem loading url: 
const #41 = Method	#235.#236;	//  java/util/logging/Logger.log:(Ljava/util/logging/Level;Ljava/lang/String;Ljava/lang/Throwable;)V
const #42 = Method	#32.#220;	//  java/net/URL.toString:()Ljava/lang/String;
const #43 = Method	#32.#237;	//  java/net/URL.openStream:()Ljava/io/InputStream;
const #44 = Method	#103.#238;	//  org/reassembler/gepo/Gepo.loadFromStream:(Ljava/lang/String;Ljava/io/InputStream;)V
const #45 = Method	#103.#239;	//  org/reassembler/gepo/Gepo.getImpl:(Ljava/lang/String;Ljava/lang/String;Lorg/reassembler/gepo/Gepo$Default;)Ljava/lang/String;
const #46 = class	#240;	//  org/reassembler/gepo/Gepo$Default
const #47 = Method	#46.#241;	//  org/reassembler/gepo/Gepo$Default."<init>":(Lorg/reassembler/gepo/Gepo;Ljava/lang/String;)V
const #48 = Method	#103.#242;	//  org/reassembler/gepo/Gepo.getKeysForPrefix:(Ljava/lang/String;)Ljava/util/Collection;
const #49 = InterfaceMethod	#243.#244;	//  java/util/Map.keySet:()Ljava/util/Set;
const #50 = class	#245;	//  java/util/HashSet
const #51 = Method	#50.#203;	//  java/util/HashSet."<init>":()V
const #52 = InterfaceMethod	#246.#247;	//  java/util/Set.iterator:()Ljava/util/Iterator;
const #53 = InterfaceMethod	#248.#249;	//  java/util/Iterator.hasNext:()Z
const #54 = InterfaceMethod	#248.#250;	//  java/util/Iterator.next:()Ljava/lang/Object;
const #55 = Method	#27.#251;	//  java/lang/String.startsWith:(Ljava/lang/String;)Z
const #56 = InterfaceMethod	#246.#252;	//  java/util/Set.add:(Ljava/lang/Object;)Z
const #57 = class	#253;	//  java/util/Properties
const #58 = Method	#57.#203;	//  java/util/Properties."<init>":()V
const #59 = InterfaceMethod	#243.#254;	//  java/util/Map.get:(Ljava/lang/Object;)Ljava/lang/Object;
const #60 = Method	#219.#255;	//  java/util/Hashtable.put:(Ljava/lang/Object;Ljava/lang/Object;)Ljava/lang/Object;
const #61 = class	#256;	//  java/io/File
const #62 = Method	#61.#202;	//  java/io/File."<init>":(Ljava/lang/String;)V
const #63 = Method	#61.#257;	//  java/io/File.exists:()Z
const #64 = Method	#61.#258;	//  java/io/File.isDirectory:()Z
const #65 = class	#259;	//  java/lang/IllegalStateException
const #66 = String	#260;	//  path is not a directory: '
const #67 = String	#261;	//  '
const #68 = Method	#65.#202;	//  java/lang/IllegalStateException."<init>":(Ljava/lang/String;)V
const #69 = String	#262;	//  searching 
const #70 = Method	#61.#263;	//  java/io/File.getAbsolutePath:()Ljava/lang/String;
const #71 = Method	#235.#264;	//  java/util/logging/Logger.finest:(Ljava/lang/String;)V
const #72 = class	#265;	//  org/reassembler/gepo/Gepo$1
const #73 = Method	#72.#267;	//  org/reassembler/gepo/Gepo$1."<init>":(Lorg/reassembler/gepo/Gepo;)V
const #74 = Method	#61.#268;	//  java/io/File.list:(Ljava/io/FilenameFilter;)[Ljava/lang/String;
const #75 = Field	#61.#269;	//  java/io/File.separator:Ljava/lang/String;
const #76 = String	#270;	//  loading 
const #77 = class	#271;	//  java/io/FileInputStream
const #78 = Method	#77.#202;	//  java/io/FileInputStream."<init>":(Ljava/lang/String;)V
const #79 = Method	#77.#272;	//  java/io/FileInputStream.close:()V
const #80 = class	#273;	//  java/io/IOException
const #81 = String	#274;	//  error loading property file: 
const #82 = Method	#65.#275;	//  java/lang/IllegalStateException."<init>":(Ljava/lang/String;Ljava/lang/Throwable;)V
const #83 = Method	#57.#276;	//  java/util/Properties.load:(Ljava/io/InputStream;)V
const #84 = String	#277;	//  org.reassembler.gepo.skip.file
const #85 = Method	#57.#278;	//  java/util/Properties.getProperty:(Ljava/lang/String;)Ljava/lang/String;
const #86 = Method	#9.#252;	//  java/util/ArrayList.add:(Ljava/lang/Object;)Z
const #87 = String	#279;	//  GEPO_SKIP was found, skipping file: 
const #88 = Method	#235.#280;	//  java/util/logging/Logger.info:(Ljava/lang/String;)V
const #89 = Method	#219.#244;	//  java/util/Hashtable.keySet:()Ljava/util/Set;
const #90 = String	#281;	//  name collision for '
const #91 = String	#282;	//  ' in file '
const #92 = String	#283;	//  ', value will be overwritten
const #93 = Method	#235.#284;	//  java/util/logging/Logger.warning:(Ljava/lang/String;)V
const #94 = Method	#219.#254;	//  java/util/Hashtable.get:(Ljava/lang/Object;)Ljava/lang/Object;
const #95 = InterfaceMethod	#243.#255;	//  java/util/Map.put:(Ljava/lang/Object;Ljava/lang/Object;)Ljava/lang/Object;
const #96 = String	#285;	//  value for name: '
const #97 = String	#286;	//  ' found
const #98 = Method	#235.#287;	//  java/util/logging/Logger.fine:(Ljava/lang/String;)V
const #99 = String	#288;	//  ' not found
const #100 = Field	#46.#289;	//  org/reassembler/gepo/Gepo$Default.value:Ljava/lang/String;
const #101 = String	#290;	//  gepo
const #102 = Method	#235.#291;	//  java/util/logging/Logger.getLogger:(Ljava/lang/String;)Ljava/util/logging/Logger;
const #103 = class	#292;	//  org/reassembler/gepo/Gepo
const #104 = class	#293;	//  java/lang/Object
const #105 = Asciz	Default;
const #106 = Asciz	InnerClasses;
const #107 = Asciz	log;
const #108 = Asciz	Ljava/util/logging/Logger;;
const #109 = Asciz	ENV_PATH_IDENTIFIER;
const #110 = Asciz	Ljava/lang/String;;
const #111 = Asciz	ConstantValue;
const #112 = Asciz	VERSION_STRING;
const #113 = String	#294;	//  1.2
const #114 = Asciz	GEPO_SKIP;
const #115 = Asciz	GEPO_CONF;
const #116 = String	#295;	//  org.reassembler.gepo.conf.file
const #117 = Asciz	props;
const #118 = Asciz	Ljava/util/Map;;
const #119 = Asciz	filesPath;
const #120 = Asciz	loaded;
const #121 = Asciz	Ljava/util/ArrayList;;
const #122 = Asciz	skipped;
const #123 = Asciz	<init>;
const #124 = Asciz	()V;
const #125 = Asciz	Code;
const #126 = Asciz	LineNumberTable;
const #127 = Asciz	LocalVariableTable;
const #128 = Asciz	this;
const #129 = Asciz	Lorg/reassembler/gepo/Gepo;;
const #130 = Asciz	(Ljava/lang/String;)V;
const #131 = Asciz	getPath;
const #132 = Asciz	()Ljava/lang/String;;
const #133 = Asciz	toString;
const #134 = Asciz	getLoadedFiles;
const #135 = Asciz	()[Ljava/lang/String;;
const #136 = Asciz	getSkippedFiles;
const #137 = Asciz	loadProperties;
const #138 = Asciz	url;
const #139 = Asciz	Ljava/net/URL;;
const #140 = Asciz	e;
const #141 = Asciz	Ljava/net/MalformedURLException;;
const #142 = Asciz	Ljava/lang/Exception;;
const #143 = Asciz	i;
const #144 = Asciz	I;
const #145 = Asciz	paths;
const #146 = Asciz	[Ljava/lang/String;;
const #147 = Asciz	loadPropertiesFromUrl;
const #148 = Asciz	(Ljava/net/URL;)V;
const #149 = Asciz	Exceptions;
const #150 = Asciz	get;
const #151 = Asciz	(Ljava/lang/String;)Ljava/lang/String;;
const #152 = Asciz	name;
const #153 = Asciz	(Ljava/lang/String;Ljava/lang/String;)Ljava/lang/String;;
const #154 = Asciz	defaultValue;
const #155 = Asciz	getWithPrefix;
const #156 = Asciz	prefix;
const #157 = Asciz	(Ljava/lang/String;Ljava/lang/String;Ljava/lang/String;)Ljava/lang/String;;
const #158 = Asciz	defaultvalue;
const #159 = Asciz	getKeys;
const #160 = Asciz	()Ljava/util/Collection;;
const #161 = Asciz	getKeysForPrefix;
const #162 = Asciz	(Ljava/lang/String;)Ljava/util/Collection;;
const #163 = Asciz	propName;
const #164 = Asciz	keys;
const #165 = Asciz	Ljava/util/Set;;
const #166 = Asciz	_prefix;
const #167 = Asciz	it;
const #168 = Asciz	Ljava/util/Iterator;;
const #169 = Asciz	toProperties;
const #170 = Asciz	()Ljava/util/Properties;;
const #171 = Asciz	key;
const #172 = Asciz	Ljava/util/Properties;;
const #173 = Asciz	loadPropertyFiles;
const #174 = Asciz	Ljava/io/IOException;;
const #175 = Asciz	shortName;
const #176 = Asciz	fileName;
const #177 = Asciz	in;
const #178 = Asciz	Ljava/io/FileInputStream;;
const #179 = Asciz	filePath;
const #180 = Asciz	path;
const #181 = Asciz	Ljava/io/File;;
const #182 = Asciz	names;
const #183 = Asciz	loadFromStream;
const #184 = Asciz	(Ljava/lang/String;Ljava/io/InputStream;)V;
const #185 = Asciz	Ljava/lang/Object;;
const #186 = Asciz	resourceId;
const #187 = Asciz	Ljava/io/InputStream;;
const #188 = Asciz	prop;
const #189 = Asciz	getImpl;
const #190 = Asciz	(Ljava/lang/String;Ljava/lang/String;Lorg/reassembler/gepo/Gepo$Default;)Ljava/lang/String;;
const #191 = Asciz	valueName;
const #192 = Asciz	defaultVal;
const #193 = Asciz	Lorg/reassembler/gepo/Gepo$Default;;
const #194 = Asciz	val;
const #195 = Asciz	<clinit>;
const #196 = Asciz	SourceFile;
const #197 = Asciz	Gepo.java;
const #198 = Asciz	org.reassembler.gepo.files;
const #199 = Asciz	.;
const #200 = class	#296;	//  java/lang/System
const #201 = NameAndType	#297:#153;//  getProperty:(Ljava/lang/String;Ljava/lang/String;)Ljava/lang/String;
const #202 = NameAndType	#123:#130;//  "<init>":(Ljava/lang/String;)V
const #203 = NameAndType	#123:#124;//  "<init>":()V
const #204 = Asciz	java/util/TreeMap;
const #205 = NameAndType	#117:#118;//  props:Ljava/util/Map;
const #206 = Asciz	java/util/ArrayList;
const #207 = NameAndType	#120:#121;//  loaded:Ljava/util/ArrayList;
const #208 = NameAndType	#122:#121;//  skipped:Ljava/util/ArrayList;
const #209 = NameAndType	#119:#110;//  filesPath:Ljava/lang/String;
const #210 = NameAndType	#137:#124;//  loadProperties:()V
const #211 = Asciz	java/lang/StringBuffer;
const #212 = Asciz	loaded:;
const #213 = NameAndType	#298:#299;//  append:(Ljava/lang/String;)Ljava/lang/StringBuffer;
const #214 = NameAndType	#298:#300;//  append:(Ljava/lang/Object;)Ljava/lang/StringBuffer;
const #215 = Asciz	,skipped:;
const #216 = Asciz	,filesPath:;
const #217 = Asciz	,properties: ;
const #218 = NameAndType	#169:#170;//  toProperties:()Ljava/util/Properties;
const #219 = class	#301;	//  java/util/Hashtable
const #220 = NameAndType	#133:#132;//  toString:()Ljava/lang/String;
const #221 = NameAndType	#302:#303;//  size:()I
const #222 = Asciz	java/lang/String;
const #223 = NameAndType	#304:#305;//  toArray:([Ljava/lang/Object;)[Ljava/lang/Object;
const #224 = Asciz	,;
const #225 = NameAndType	#306:#307;//  split:(Ljava/lang/String;)[Ljava/lang/String;
const #226 = Asciz	java/net/URL;
const #227 = NameAndType	#147:#148;//  loadPropertiesFromUrl:(Ljava/net/URL;)V
const #228 = Asciz	java/net/MalformedURLException;
const #229 = NameAndType	#173:#130;//  loadPropertyFiles:(Ljava/lang/String;)V
const #230 = Asciz	java/lang/Exception;
const #231 = NameAndType	#107:#108;//  log:Ljava/util/logging/Logger;
const #232 = class	#308;	//  java/util/logging/Level
const #233 = NameAndType	#309:#310;//  SEVERE:Ljava/util/logging/Level;
const #234 = Asciz	problem loading url: ;
const #235 = class	#311;	//  java/util/logging/Logger
const #236 = NameAndType	#107:#312;//  log:(Ljava/util/logging/Level;Ljava/lang/String;Ljava/lang/Throwable;)V
const #237 = NameAndType	#313:#314;//  openStream:()Ljava/io/InputStream;
const #238 = NameAndType	#183:#184;//  loadFromStream:(Ljava/lang/String;Ljava/io/InputStream;)V
const #239 = NameAndType	#189:#190;//  getImpl:(Ljava/lang/String;Ljava/lang/String;Lorg/reassembler/gepo/Gepo$Default;)Ljava/lang/String;
const #240 = Asciz	org/reassembler/gepo/Gepo$Default;
const #241 = NameAndType	#123:#315;//  "<init>":(Lorg/reassembler/gepo/Gepo;Ljava/lang/String;)V
const #242 = NameAndType	#161:#162;//  getKeysForPrefix:(Ljava/lang/String;)Ljava/util/Collection;
const #243 = class	#316;	//  java/util/Map
const #244 = NameAndType	#317:#318;//  keySet:()Ljava/util/Set;
const #245 = Asciz	java/util/HashSet;
const #246 = class	#319;	//  java/util/Set
const #247 = NameAndType	#320:#321;//  iterator:()Ljava/util/Iterator;
const #248 = class	#322;	//  java/util/Iterator
const #249 = NameAndType	#323:#324;//  hasNext:()Z
const #250 = NameAndType	#325:#326;//  next:()Ljava/lang/Object;
const #251 = NameAndType	#327:#328;//  startsWith:(Ljava/lang/String;)Z
const #252 = NameAndType	#329:#330;//  add:(Ljava/lang/Object;)Z
const #253 = Asciz	java/util/Properties;
const #254 = NameAndType	#150:#331;//  get:(Ljava/lang/Object;)Ljava/lang/Object;
const #255 = NameAndType	#332:#333;//  put:(Ljava/lang/Object;Ljava/lang/Object;)Ljava/lang/Object;
const #256 = Asciz	java/io/File;
const #257 = NameAndType	#334:#324;//  exists:()Z
const #258 = NameAndType	#335:#324;//  isDirectory:()Z
const #259 = Asciz	java/lang/IllegalStateException;
const #260 = Asciz	path is not a directory: ';
const #261 = Asciz	';
const #262 = Asciz	searching ;
const #263 = NameAndType	#336:#132;//  getAbsolutePath:()Ljava/lang/String;
const #264 = NameAndType	#337:#130;//  finest:(Ljava/lang/String;)V
const #265 = Asciz	org/reassembler/gepo/Gepo$1;
const #266 = Asciz	;
const #267 = NameAndType	#123:#338;//  "<init>":(Lorg/reassembler/gepo/Gepo;)V
const #268 = NameAndType	#339:#340;//  list:(Ljava/io/FilenameFilter;)[Ljava/lang/String;
const #269 = NameAndType	#341:#110;//  separator:Ljava/lang/String;
const #270 = Asciz	loading ;
const #271 = Asciz	java/io/FileInputStream;
const #272 = NameAndType	#342:#124;//  close:()V
const #273 = Asciz	java/io/IOException;
const #274 = Asciz	error loading property file: ;
const #275 = NameAndType	#123:#343;//  "<init>":(Ljava/lang/String;Ljava/lang/Throwable;)V
const #276 = NameAndType	#344:#345;//  load:(Ljava/io/InputStream;)V
const #277 = Asciz	org.reassembler.gepo.skip.file;
const #278 = NameAndType	#297:#151;//  getProperty:(Ljava/lang/String;)Ljava/lang/String;
const #279 = Asciz	GEPO_SKIP was found, skipping file: ;
const #280 = NameAndType	#346:#130;//  info:(Ljava/lang/String;)V
const #281 = Asciz	name collision for ';
const #282 = Asciz	' in file ';
const #283 = Asciz	', value will be overwritten;
const #284 = NameAndType	#347:#130;//  warning:(Ljava/lang/String;)V
const #285 = Asciz	value for name: ';
const #286 = Asciz	' found;
const #287 = NameAndType	#348:#130;//  fine:(Ljava/lang/String;)V
const #288 = Asciz	' not found;
const #289 = NameAndType	#349:#110;//  value:Ljava/lang/String;
const #290 = Asciz	gepo;
const #291 = NameAndType	#350:#351;//  getLogger:(Ljava/lang/String;)Ljava/util/logging/Logger;
const #292 = Asciz	org/reassembler/gepo/Gepo;
const #293 = Asciz	java/lang/Object;
const #294 = Asciz	1.2;
const #295 = Asciz	org.reassembler.gepo.conf.file;
const #296 = Asciz	java/lang/System;
const #297 = Asciz	getProperty;
const #298 = Asciz	append;
const #299 = Asciz	(Ljava/lang/String;)Ljava/lang/StringBuffer;;
const #300 = Asciz	(Ljava/lang/Object;)Ljava/lang/StringBuffer;;
const #301 = Asciz	java/util/Hashtable;
const #302 = Asciz	size;
const #303 = Asciz	()I;
const #304 = Asciz	toArray;
const #305 = Asciz	([Ljava/lang/Object;)[Ljava/lang/Object;;
const #306 = Asciz	split;
const #307 = Asciz	(Ljava/lang/String;)[Ljava/lang/String;;
const #308 = Asciz	java/util/logging/Level;
const #309 = Asciz	SEVERE;
const #310 = Asciz	Ljava/util/logging/Level;;
const #311 = Asciz	java/util/logging/Logger;
const #312 = Asciz	(Ljava/util/logging/Level;Ljava/lang/String;Ljava/lang/Throwable;)V;
const #313 = Asciz	openStream;
const #314 = Asciz	()Ljava/io/InputStream;;
const #315 = Asciz	(Lorg/reassembler/gepo/Gepo;Ljava/lang/String;)V;
const #316 = Asciz	java/util/Map;
const #317 = Asciz	keySet;
const #318 = Asciz	()Ljava/util/Set;;
const #319 = Asciz	java/util/Set;
const #320 = Asciz	iterator;
const #321 = Asciz	()Ljava/util/Iterator;;
const #322 = Asciz	java/util/Iterator;
const #323 = Asciz	hasNext;
const #324 = Asciz	()Z;
const #325 = Asciz	next;
const #326 = Asciz	()Ljava/lang/Object;;
const #327 = Asciz	startsWith;
const #328 = Asciz	(Ljava/lang/String;)Z;
const #329 = Asciz	add;
const #330 = Asciz	(Ljava/lang/Object;)Z;
const #331 = Asciz	(Ljava/lang/Object;)Ljava/lang/Object;;
const #332 = Asciz	put;
const #333 = Asciz	(Ljava/lang/Object;Ljava/lang/Object;)Ljava/lang/Object;;
const #334 = Asciz	exists;
const #335 = Asciz	isDirectory;
const #336 = Asciz	getAbsolutePath;
const #337 = Asciz	finest;
const #338 = Asciz	(Lorg/reassembler/gepo/Gepo;)V;
const #339 = Asciz	list;
const #340 = Asciz	(Ljava/io/FilenameFilter;)[Ljava/lang/String;;
const #341 = Asciz	separator;
const #342 = Asciz	close;
const #343 = Asciz	(Ljava/lang/String;Ljava/lang/Throwable;)V;
const #344 = Asciz	load;
const #345 = Asciz	(Ljava/io/InputStream;)V;
const #346 = Asciz	info;
const #347 = Asciz	warning;
const #348 = Asciz	fine;
const #349 = Asciz	value;
const #350 = Asciz	getLogger;
const #351 = Asciz	(Ljava/lang/String;)Ljava/util/logging/Logger;;

{
public static final java.lang.String ENV_PATH_IDENTIFIER;
  Constant value: String org.reassembler.gepo.files
public static final java.lang.String VERSION_STRING;
  Constant value: String 1.2
public static final java.lang.String GEPO_SKIP;
  Constant value: String org.reassembler.gepo.skip.file
public static final java.lang.String GEPO_CONF;
  Constant value: String org.reassembler.gepo.conf.file
public org.reassembler.gepo.Gepo();
  Code:
   Stack=3, Locals=1, Args_size=1
   0:	aload_0
   1:	ldc	#1; //String org.reassembler.gepo.files
   3:	ldc	#2; //String .
   5:	invokestatic	#3; //Method java/lang/System.getProperty:(Ljava/lang/String;Ljava/lang/String;)Ljava/lang/String;
   8:	invokespecial	#4; //Method "<init>":(Ljava/lang/String;)V
   11:	return
  LineNumberTable: 
   line 75: 0
   line 76: 11

  LocalVariableTable: 
   Start  Length  Slot  Name   Signature
   0      12      0    this       Lorg/reassembler/gepo/Gepo;


public org.reassembler.gepo.Gepo(java.lang.String);
  Code:
   Stack=3, Locals=2, Args_size=2
   0:	aload_0
   1:	invokespecial	#5; //Method java/lang/Object."<init>":()V
   4:	aload_0
   5:	new	#6; //class java/util/TreeMap
   8:	dup
   9:	invokespecial	#7; //Method java/util/TreeMap."<init>":()V
   12:	putfield	#8; //Field props:Ljava/util/Map;
   15:	aload_0
   16:	new	#9; //class java/util/ArrayList
   19:	dup
   20:	invokespecial	#10; //Method java/util/ArrayList."<init>":()V
   23:	putfield	#11; //Field loaded:Ljava/util/ArrayList;
   26:	aload_0
   27:	new	#9; //class java/util/ArrayList
   30:	dup
   31:	invokespecial	#10; //Method java/util/ArrayList."<init>":()V
   34:	putfield	#12; //Field skipped:Ljava/util/ArrayList;
   37:	aload_0
   38:	aload_1
   39:	putfield	#13; //Field filesPath:Ljava/lang/String;
   42:	aload_0
   43:	invokespecial	#14; //Method loadProperties:()V
   46:	return
  LineNumberTable: 
   line 78: 0
   line 61: 4
   line 63: 15
   line 64: 26
   line 79: 37
   line 80: 42
   line 81: 46

  LocalVariableTable: 
   Start  Length  Slot  Name   Signature
   0      47      0    this       Lorg/reassembler/gepo/Gepo;
   0      47      1    filesPath       Ljava/lang/String;


public java.lang.String getPath();
  Code:
   Stack=1, Locals=1, Args_size=1
   0:	aload_0
   1:	getfield	#13; //Field filesPath:Ljava/lang/String;
   4:	areturn
  LineNumberTable: 
   line 84: 0

  LocalVariableTable: 
   Start  Length  Slot  Name   Signature
   0      5      0    this       Lorg/reassembler/gepo/Gepo;


public java.lang.String toString();
  Code:
   Stack=2, Locals=1, Args_size=1
   0:	new	#15; //class java/lang/StringBuffer
   3:	dup
   4:	invokespecial	#16; //Method java/lang/StringBuffer."<init>":()V
   7:	ldc	#17; //String loaded:
   9:	invokevirtual	#18; //Method java/lang/StringBuffer.append:(Ljava/lang/String;)Ljava/lang/StringBuffer;
   12:	aload_0
   13:	getfield	#11; //Field loaded:Ljava/util/ArrayList;
   16:	invokevirtual	#19; //Method java/lang/StringBuffer.append:(Ljava/lang/Object;)Ljava/lang/StringBuffer;
   19:	ldc	#20; //String ,skipped:
   21:	invokevirtual	#18; //Method java/lang/StringBuffer.append:(Ljava/lang/String;)Ljava/lang/StringBuffer;
   24:	aload_0
   25:	getfield	#12; //Field skipped:Ljava/util/ArrayList;
   28:	invokevirtual	#19; //Method java/lang/StringBuffer.append:(Ljava/lang/Object;)Ljava/lang/StringBuffer;
   31:	ldc	#21; //String ,filesPath:
   33:	invokevirtual	#18; //Method java/lang/StringBuffer.append:(Ljava/lang/String;)Ljava/lang/StringBuffer;
   36:	aload_0
   37:	getfield	#13; //Field filesPath:Ljava/lang/String;
   40:	invokevirtual	#18; //Method java/lang/StringBuffer.append:(Ljava/lang/String;)Ljava/lang/StringBuffer;
   43:	ldc	#22; //String ,properties: 
   45:	invokevirtual	#18; //Method java/lang/StringBuffer.append:(Ljava/lang/String;)Ljava/lang/StringBuffer;
   48:	aload_0
   49:	invokevirtual	#23; //Method toProperties:()Ljava/util/Properties;
   52:	invokevirtual	#24; //Method java/util/Hashtable.toString:()Ljava/lang/String;
   55:	invokevirtual	#18; //Method java/lang/StringBuffer.append:(Ljava/lang/String;)Ljava/lang/StringBuffer;
   58:	invokevirtual	#25; //Method java/lang/StringBuffer.toString:()Ljava/lang/String;
   61:	areturn
  LineNumberTable: 
   line 88: 0

  LocalVariableTable: 
   Start  Length  Slot  Name   Signature
   0      62      0    this       Lorg/reassembler/gepo/Gepo;


public java.lang.String[] getLoadedFiles();
  Code:
   Stack=2, Locals=1, Args_size=1
   0:	aload_0
   1:	getfield	#11; //Field loaded:Ljava/util/ArrayList;
   4:	aload_0
   5:	getfield	#11; //Field loaded:Ljava/util/ArrayList;
   8:	invokevirtual	#26; //Method java/util/ArrayList.size:()I
   11:	anewarray	#27; //class java/lang/String
   14:	invokevirtual	#28; //Method java/util/ArrayList.toArray:([Ljava/lang/Object;)[Ljava/lang/Object;
   17:	checkcast	#29; //class "[Ljava/lang/String;"
   20:	checkcast	#29; //class "[Ljava/lang/String;"
   23:	areturn
  LineNumberTable: 
   line 100: 0

  LocalVariableTable: 
   Start  Length  Slot  Name   Signature
   0      24      0    this       Lorg/reassembler/gepo/Gepo;


public java.lang.String[] getSkippedFiles();
  Code:
   Stack=2, Locals=1, Args_size=1
   0:	aload_0
   1:	getfield	#12; //Field skipped:Ljava/util/ArrayList;
   4:	aload_0
   5:	getfield	#12; //Field skipped:Ljava/util/ArrayList;
   8:	invokevirtual	#26; //Method java/util/ArrayList.size:()I
   11:	anewarray	#27; //class java/lang/String
   14:	invokevirtual	#28; //Method java/util/ArrayList.toArray:([Ljava/lang/Object;)[Ljava/lang/Object;
   17:	checkcast	#29; //class "[Ljava/lang/String;"
   20:	checkcast	#29; //class "[Ljava/lang/String;"
   23:	areturn
  LineNumberTable: 
   line 109: 0

  LocalVariableTable: 
   Start  Length  Slot  Name   Signature
   0      24      0    this       Lorg/reassembler/gepo/Gepo;


public java.lang.String get(java.lang.String);
  Code:
   Stack=4, Locals=2, Args_size=2
   0:	aload_0
   1:	aconst_null
   2:	aload_1
   3:	aconst_null
   4:	invokespecial	#45; //Method getImpl:(Ljava/lang/String;Ljava/lang/String;Lorg/reassembler/gepo/Gepo$Default;)Ljava/lang/String;
   7:	areturn
  LineNumberTable: 
   line 134: 0

  LocalVariableTable: 
   Start  Length  Slot  Name   Signature
   0      8      0    this       Lorg/reassembler/gepo/Gepo;
   0      8      1    name       Ljava/lang/String;


public java.lang.String get(java.lang.String, java.lang.String);
  Code:
   Stack=7, Locals=3, Args_size=3
   0:	aload_0
   1:	aconst_null
   2:	aload_1
   3:	new	#46; //class org/reassembler/gepo/Gepo$Default
   6:	dup
   7:	aload_0
   8:	aload_2
   9:	invokespecial	#47; //Method org/reassembler/gepo/Gepo$Default."<init>":(Lorg/reassembler/gepo/Gepo;Ljava/lang/String;)V
   12:	invokespecial	#45; //Method getImpl:(Ljava/lang/String;Ljava/lang/String;Lorg/reassembler/gepo/Gepo$Default;)Ljava/lang/String;
   15:	areturn
  LineNumberTable: 
   line 138: 0

  LocalVariableTable: 
   Start  Length  Slot  Name   Signature
   0      16      0    this       Lorg/reassembler/gepo/Gepo;
   0      16      1    name       Ljava/lang/String;
   0      16      2    defaultValue       Ljava/lang/String;


public java.lang.String getWithPrefix(java.lang.String, java.lang.String);
  Code:
   Stack=4, Locals=3, Args_size=3
   0:	aload_0
   1:	aload_1
   2:	aload_2
   3:	aconst_null
   4:	invokespecial	#45; //Method getImpl:(Ljava/lang/String;Ljava/lang/String;Lorg/reassembler/gepo/Gepo$Default;)Ljava/lang/String;
   7:	areturn
  LineNumberTable: 
   line 142: 0

  LocalVariableTable: 
   Start  Length  Slot  Name   Signature
   0      8      0    this       Lorg/reassembler/gepo/Gepo;
   0      8      1    prefix       Ljava/lang/String;
   0      8      2    name       Ljava/lang/String;


public java.lang.String getWithPrefix(java.lang.String, java.lang.String, java.lang.String);
  Code:
   Stack=7, Locals=4, Args_size=4
   0:	aload_0
   1:	aload_1
   2:	aload_2
   3:	new	#46; //class org/reassembler/gepo/Gepo$Default
   6:	dup
   7:	aload_0
   8:	aload_3
   9:	invokespecial	#47; //Method org/reassembler/gepo/Gepo$Default."<init>":(Lorg/reassembler/gepo/Gepo;Ljava/lang/String;)V
   12:	invokespecial	#45; //Method getImpl:(Ljava/lang/String;Ljava/lang/String;Lorg/reassembler/gepo/Gepo$Default;)Ljava/lang/String;
   15:	areturn
  LineNumberTable: 
   line 146: 0

  LocalVariableTable: 
   Start  Length  Slot  Name   Signature
   0      16      0    this       Lorg/reassembler/gepo/Gepo;
   0      16      1    prefix       Ljava/lang/String;
   0      16      2    name       Ljava/lang/String;
   0      16      3    defaultvalue       Ljava/lang/String;


public java.util.Collection getKeys();
  Code:
   Stack=2, Locals=1, Args_size=1
   0:	aload_0
   1:	aconst_null
   2:	invokevirtual	#48; //Method getKeysForPrefix:(Ljava/lang/String;)Ljava/util/Collection;
   5:	areturn
  LineNumberTable: 
   line 150: 0

  LocalVariableTable: 
   Start  Length  Slot  Name   Signature
   0      6      0    this       Lorg/reassembler/gepo/Gepo;


public java.util.Collection getKeysForPrefix(java.lang.String);
  Code:
   Stack=2, Locals=6, Args_size=2
   0:	aload_1
   1:	ifnonnull	14
   4:	aload_0
   5:	getfield	#8; //Field props:Ljava/util/Map;
   8:	invokeinterface	#49,  1; //InterfaceMethod java/util/Map.keySet:()Ljava/util/Set;
   13:	areturn
   14:	new	#50; //class java/util/HashSet
   17:	dup
   18:	invokespecial	#51; //Method java/util/HashSet."<init>":()V
   21:	astore_2
   22:	new	#15; //class java/lang/StringBuffer
   25:	dup
   26:	invokespecial	#16; //Method java/lang/StringBuffer."<init>":()V
   29:	aload_1
   30:	invokevirtual	#18; //Method java/lang/StringBuffer.append:(Ljava/lang/String;)Ljava/lang/StringBuffer;
   33:	ldc	#2; //String .
   35:	invokevirtual	#18; //Method java/lang/StringBuffer.append:(Ljava/lang/String;)Ljava/lang/StringBuffer;
   38:	invokevirtual	#25; //Method java/lang/StringBuffer.toString:()Ljava/lang/String;
   41:	astore_3
   42:	aload_0
   43:	getfield	#8; //Field props:Ljava/util/Map;
   46:	invokeinterface	#49,  1; //InterfaceMethod java/util/Map.keySet:()Ljava/util/Set;
   51:	invokeinterface	#52,  1; //InterfaceMethod java/util/Set.iterator:()Ljava/util/Iterator;
   56:	astore	4
   58:	aload	4
   60:	invokeinterface	#53,  1; //InterfaceMethod java/util/Iterator.hasNext:()Z
   65:	ifeq	101
   68:	aload	4
   70:	invokeinterface	#54,  1; //InterfaceMethod java/util/Iterator.next:()Ljava/lang/Object;
   75:	checkcast	#27; //class java/lang/String
   78:	astore	5
   80:	aload	5
   82:	aload_3
   83:	invokevirtual	#55; //Method java/lang/String.startsWith:(Ljava/lang/String;)Z
   86:	ifeq	98
   89:	aload_2
   90:	aload	5
   92:	invokeinterface	#56,  2; //InterfaceMethod java/util/Set.add:(Ljava/lang/Object;)Z
   97:	pop
   98:	goto	58
   101:	aload_2
   102:	areturn
  LineNumberTable: 
   line 154: 0
   line 155: 4
   line 158: 14
   line 159: 22
   line 161: 42
   line 162: 58
   line 163: 68
   line 165: 80
   line 166: 89
   line 168: 98
   line 170: 101

  LocalVariableTable: 
   Start  Length  Slot  Name   Signature
   80      18      5    propName       Ljava/lang/String;
   0      103      0    this       Lorg/reassembler/gepo/Gepo;
   0      103      1    prefix       Ljava/lang/String;
   22      81      2    keys       Ljava/util/Set;
   42      61      3    _prefix       Ljava/lang/String;
   58      45      4    it       Ljava/util/Iterator;


public java.util.Properties toProperties();
  Code:
   Stack=4, Locals=4, Args_size=1
   0:	new	#57; //class java/util/Properties
   3:	dup
   4:	invokespecial	#58; //Method java/util/Properties."<init>":()V
   7:	astore_1
   8:	aload_0
   9:	getfield	#8; //Field props:Ljava/util/Map;
   12:	invokeinterface	#49,  1; //InterfaceMethod java/util/Map.keySet:()Ljava/util/Set;
   17:	invokeinterface	#52,  1; //InterfaceMethod java/util/Set.iterator:()Ljava/util/Iterator;
   22:	astore_2
   23:	aload_2
   24:	invokeinterface	#53,  1; //InterfaceMethod java/util/Iterator.hasNext:()Z
   29:	ifeq	61
   32:	aload_2
   33:	invokeinterface	#54,  1; //InterfaceMethod java/util/Iterator.next:()Ljava/lang/Object;
   38:	checkcast	#27; //class java/lang/String
   41:	astore_3
   42:	aload_1
   43:	aload_3
   44:	aload_0
   45:	getfield	#8; //Field props:Ljava/util/Map;
   48:	aload_3
   49:	invokeinterface	#59,  2; //InterfaceMethod java/util/Map.get:(Ljava/lang/Object;)Ljava/lang/Object;
   54:	invokevirtual	#60; //Method java/util/Hashtable.put:(Ljava/lang/Object;Ljava/lang/Object;)Ljava/lang/Object;
   57:	pop
   58:	goto	23
   61:	aload_1
   62:	areturn
  LineNumberTable: 
   line 174: 0
   line 176: 8
   line 177: 23
   line 178: 32
   line 179: 42
   line 180: 58
   line 182: 61

  LocalVariableTable: 
   Start  Length  Slot  Name   Signature
   42      16      3    key       Ljava/lang/String;
   0      63      0    this       Lorg/reassembler/gepo/Gepo;
   8      55      1    props       Ljava/util/Properties;
   23      40      2    it       Ljava/util/Iterator;


static {};
  Code:
   Stack=1, Locals=0, Args_size=0
   0:	ldc	#101; //String gepo
   2:	invokestatic	#102; //Method java/util/logging/Logger.getLogger:(Ljava/lang/String;)Ljava/util/logging/Logger;
   5:	putstatic	#38; //Field log:Ljava/util/logging/Logger;
   8:	return
  LineNumberTable: 
   line 38: 0


}

