Compiled from "ArrayUtils.java"
public class org.apache.commons.lang.ArrayUtils extends java.lang.Object
  SourceFile: "ArrayUtils.java"
  minor version: 3
  major version: 45
  Constant pool:
const #1 = int	2147483647;
const #2 = String	#306;	//  ', has a length less than 2
const #3 = String	#307;	//  ', is neither of type Map.Entry nor an Array
const #4 = String	#479;	//  , '
const #5 = String	#480;	//  , Length: 
const #6 = String	#481;	//  , Length: 0
const #7 = String	#484;	//  Array element 
const #8 = String	#512;	//  Index: 
const #9 = String	#537;	//  The Array must not be null
const #10 = String	#599;	//  java.lang.Object
const #11 = String	#662;	//  {}
const #12 = class	#539;	//  "[B"
const #13 = class	#540;	//  "[C"
const #14 = class	#541;	//  "[D"
const #15 = class	#542;	//  "[F"
const #16 = class	#543;	//  "[I"
const #17 = class	#544;	//  "[J"
const #18 = class	#553;	//  "[Ljava/lang/Object;"
const #19 = class	#556;	//  "[S"
const #20 = class	#557;	//  "[Z"
const #21 = class	#600;	//  java/lang/Boolean
const #22 = class	#601;	//  java/lang/Byte
const #23 = class	#602;	//  java/lang/Character
const #24 = class	#603;	//  java/lang/Class
const #25 = class	#604;	//  java/lang/ClassNotFoundException
const #26 = class	#605;	//  java/lang/Double
const #27 = class	#606;	//  java/lang/Float
const #28 = class	#607;	//  java/lang/IllegalArgumentException
const #29 = class	#608;	//  java/lang/IndexOutOfBoundsException
const #30 = class	#609;	//  java/lang/Integer
const #31 = class	#610;	//  java/lang/Long
const #32 = class	#611;	//  java/lang/NoClassDefFoundError
const #33 = class	#612;	//  java/lang/Object
const #34 = class	#613;	//  java/lang/Short
const #35 = class	#614;	//  java/lang/String
const #36 = class	#615;	//  java/lang/StringBuffer
const #37 = class	#616;	//  java/lang/System
const #38 = class	#617;	//  java/lang/Throwable
const #39 = class	#618;	//  java/lang/reflect/Array
const #40 = class	#619;	//  java/util/HashMap
const #41 = class	#620;	//  java/util/Map
const #42 = class	#621;	//  java/util/Map$Entry
const #43 = class	#635;	//  org/apache/commons/lang/ArrayUtils
const #44 = class	#636;	//  org/apache/commons/lang/builder/EqualsBuilder
const #45 = class	#637;	//  org/apache/commons/lang/builder/HashCodeBuilder
const #46 = class	#638;	//  org/apache/commons/lang/builder/ToStringBuilder
const #47 = class	#639;	//  org/apache/commons/lang/builder/ToStringStyle
const #48 = Method	#33.#186;	//  java/lang/Object."<init>":()V
const #49 = Method	#44.#186;	//  org/apache/commons/lang/builder/EqualsBuilder."<init>":()V
const #50 = Method	#45.#186;	//  org/apache/commons/lang/builder/HashCodeBuilder."<init>":()V
const #51 = Method	#22.#187;	//  java/lang/Byte."<init>":(B)V
const #52 = Method	#23.#188;	//  java/lang/Character."<init>":(C)V
const #53 = Method	#26.#189;	//  java/lang/Double."<init>":(D)V
const #54 = Method	#27.#190;	//  java/lang/Float."<init>":(F)V
const #55 = Method	#30.#191;	//  java/lang/Integer."<init>":(I)V
const #56 = Method	#40.#191;	//  java/util/HashMap."<init>":(I)V
const #57 = Method	#31.#192;	//  java/lang/Long."<init>":(J)V
const #58 = Method	#46.#193;	//  org/apache/commons/lang/builder/ToStringBuilder."<init>":(Ljava/lang/Object;Lorg/apache/commons/lang/builder/ToStringStyle;)V
const #59 = Method	#28.#194;	//  java/lang/IllegalArgumentException."<init>":(Ljava/lang/String;)V
const #60 = Method	#29.#194;	//  java/lang/IndexOutOfBoundsException."<init>":(Ljava/lang/String;)V
const #61 = Method	#32.#194;	//  java/lang/NoClassDefFoundError."<init>":(Ljava/lang/String;)V
const #62 = Method	#36.#194;	//  java/lang/StringBuffer."<init>":(Ljava/lang/String;)V
const #63 = Method	#34.#195;	//  java/lang/Short."<init>":(S)V
const #64 = Method	#21.#196;	//  java/lang/Boolean."<init>":(Z)V
const #65 = Field	#43.#197;	//  org/apache/commons/lang/ArrayUtils.EMPTY_BOOLEAN_ARRAY:[Z
const #66 = Field	#43.#198;	//  org/apache/commons/lang/ArrayUtils.EMPTY_BOOLEAN_OBJECT_ARRAY:[Ljava/lang/Boolean;
const #67 = Field	#43.#199;	//  org/apache/commons/lang/ArrayUtils.EMPTY_BYTE_ARRAY:[B
const #68 = Field	#43.#200;	//  org/apache/commons/lang/ArrayUtils.EMPTY_BYTE_OBJECT_ARRAY:[Ljava/lang/Byte;
const #69 = Field	#43.#201;	//  org/apache/commons/lang/ArrayUtils.EMPTY_CHARACTER_OBJECT_ARRAY:[Ljava/lang/Character;
const #70 = Field	#43.#202;	//  org/apache/commons/lang/ArrayUtils.EMPTY_CHAR_ARRAY:[C
const #71 = Field	#43.#203;	//  org/apache/commons/lang/ArrayUtils.EMPTY_CLASS_ARRAY:[Ljava/lang/Class;
const #72 = Field	#43.#204;	//  org/apache/commons/lang/ArrayUtils.EMPTY_DOUBLE_ARRAY:[D
const #73 = Field	#43.#205;	//  org/apache/commons/lang/ArrayUtils.EMPTY_DOUBLE_OBJECT_ARRAY:[Ljava/lang/Double;
const #74 = Field	#43.#206;	//  org/apache/commons/lang/ArrayUtils.EMPTY_FLOAT_ARRAY:[F
const #75 = Field	#43.#207;	//  org/apache/commons/lang/ArrayUtils.EMPTY_FLOAT_OBJECT_ARRAY:[Ljava/lang/Float;
const #76 = Field	#43.#208;	//  org/apache/commons/lang/ArrayUtils.EMPTY_INTEGER_OBJECT_ARRAY:[Ljava/lang/Integer;
const #77 = Field	#43.#209;	//  org/apache/commons/lang/ArrayUtils.EMPTY_INT_ARRAY:[I
const #78 = Field	#43.#210;	//  org/apache/commons/lang/ArrayUtils.EMPTY_LONG_ARRAY:[J
const #79 = Field	#43.#211;	//  org/apache/commons/lang/ArrayUtils.EMPTY_LONG_OBJECT_ARRAY:[Ljava/lang/Long;
const #80 = Field	#43.#212;	//  org/apache/commons/lang/ArrayUtils.EMPTY_OBJECT_ARRAY:[Ljava/lang/Object;
const #81 = Field	#43.#213;	//  org/apache/commons/lang/ArrayUtils.EMPTY_SHORT_ARRAY:[S
const #82 = Field	#43.#214;	//  org/apache/commons/lang/ArrayUtils.EMPTY_SHORT_OBJECT_ARRAY:[Ljava/lang/Short;
const #83 = Field	#43.#215;	//  org/apache/commons/lang/ArrayUtils.EMPTY_STRING_ARRAY:[Ljava/lang/String;
const #84 = Field	#21.#216;	//  java/lang/Boolean.FALSE:Ljava/lang/Boolean;
const #85 = Field	#47.#217;	//  org/apache/commons/lang/builder/ToStringStyle.SIMPLE_STYLE:Lorg/apache/commons/lang/builder/ToStringStyle;
const #86 = Field	#21.#218;	//  java/lang/Boolean.TRUE:Ljava/lang/Boolean;
const #87 = Field	#21.#219;	//  java/lang/Boolean.TYPE:Ljava/lang/Class;
const #88 = Field	#22.#219;	//  java/lang/Byte.TYPE:Ljava/lang/Class;
const #89 = Field	#23.#219;	//  java/lang/Character.TYPE:Ljava/lang/Class;
const #90 = Field	#26.#219;	//  java/lang/Double.TYPE:Ljava/lang/Class;
const #91 = Field	#27.#219;	//  java/lang/Float.TYPE:Ljava/lang/Class;
const #92 = Field	#30.#219;	//  java/lang/Integer.TYPE:Ljava/lang/Class;
const #93 = Field	#31.#219;	//  java/lang/Long.TYPE:Ljava/lang/Class;
const #94 = Field	#34.#219;	//  java/lang/Short.TYPE:Ljava/lang/Class;
const #95 = Method	#43.#220;	//  org/apache/commons/lang/ArrayUtils.add:(Ljava/lang/Object;ILjava/lang/Object;Ljava/lang/Class;)Ljava/lang/Object;
const #96 = Method	#36.#221;	//  java/lang/StringBuffer.append:(I)Ljava/lang/StringBuffer;
const #97 = Method	#36.#222;	//  java/lang/StringBuffer.append:(Ljava/lang/Object;)Ljava/lang/StringBuffer;
const #98 = Method	#45.#223;	//  org/apache/commons/lang/builder/HashCodeBuilder.append:(Ljava/lang/Object;)Lorg/apache/commons/lang/builder/HashCodeBuilder;
const #99 = Method	#46.#224;	//  org/apache/commons/lang/builder/ToStringBuilder.append:(Ljava/lang/Object;)Lorg/apache/commons/lang/builder/ToStringBuilder;
const #100 = Method	#44.#225;	//  org/apache/commons/lang/builder/EqualsBuilder.append:(Ljava/lang/Object;Ljava/lang/Object;)Lorg/apache/commons/lang/builder/EqualsBuilder;
const #101 = Method	#36.#226;	//  java/lang/StringBuffer.append:(Ljava/lang/String;)Ljava/lang/StringBuffer;
const #102 = Method	#37.#227;	//  java/lang/System.arraycopy:(Ljava/lang/Object;ILjava/lang/Object;II)V
const #103 = Method	#21.#228;	//  java/lang/Boolean.booleanValue:()Z
const #104 = Method	#22.#229;	//  java/lang/Byte.byteValue:()B
const #105 = Method	#43.#230;	//  org/apache/commons/lang/ArrayUtils.class$:(Ljava/lang/String;)Ljava/lang/Class;
const #106 = Field	#43.#231;	//  org/apache/commons/lang/ArrayUtils.class$java$lang$Object:Ljava/lang/Class;
const #107 = Method	#33.#232;	//  java/lang/Object.clone:()Ljava/lang/Object;
const #108 = Method	#43.#233;	//  org/apache/commons/lang/ArrayUtils.clone:([B)[B
const #109 = Method	#43.#234;	//  org/apache/commons/lang/ArrayUtils.clone:([C)[C
const #110 = Method	#43.#235;	//  org/apache/commons/lang/ArrayUtils.clone:([D)[D
const #111 = Method	#43.#236;	//  org/apache/commons/lang/ArrayUtils.clone:([F)[F
const #112 = Method	#43.#237;	//  org/apache/commons/lang/ArrayUtils.clone:([I)[I
const #113 = Method	#43.#238;	//  org/apache/commons/lang/ArrayUtils.clone:([J)[J
const #114 = Method	#43.#239;	//  org/apache/commons/lang/ArrayUtils.clone:([Ljava/lang/Object;)[Ljava/lang/Object;
const #115 = Method	#43.#240;	//  org/apache/commons/lang/ArrayUtils.clone:([S)[S
const #116 = Method	#43.#241;	//  org/apache/commons/lang/ArrayUtils.clone:([Z)[Z
const #117 = Method	#43.#242;	//  org/apache/commons/lang/ArrayUtils.copyArrayGrow1:(Ljava/lang/Object;Ljava/lang/Class;)Ljava/lang/Object;
const #118 = Method	#26.#243;	//  java/lang/Double.doubleValue:()D
const #119 = Method	#33.#244;	//  java/lang/Object.equals:(Ljava/lang/Object;)Z
const #120 = Method	#35.#244;	//  java/lang/String.equals:(Ljava/lang/Object;)Z
const #121 = Method	#27.#245;	//  java/lang/Float.floatValue:()F
const #122 = Method	#24.#246;	//  java/lang/Class.forName:(Ljava/lang/String;)Ljava/lang/Class;
const #123 = Method	#33.#247;	//  java/lang/Object.getClass:()Ljava/lang/Class;
const #124 = Method	#24.#248;	//  java/lang/Class.getComponentType:()Ljava/lang/Class;
const #125 = InterfaceMethod	#42.#249;	//  java/util/Map$Entry.getKey:()Ljava/lang/Object;
const #126 = Method	#39.#250;	//  java/lang/reflect/Array.getLength:(Ljava/lang/Object;)I
const #127 = Method	#43.#250;	//  org/apache/commons/lang/ArrayUtils.getLength:(Ljava/lang/Object;)I
const #128 = Method	#38.#251;	//  java/lang/Throwable.getMessage:()Ljava/lang/String;
const #129 = Method	#24.#252;	//  java/lang/Class.getName:()Ljava/lang/String;
const #130 = InterfaceMethod	#42.#253;	//  java/util/Map$Entry.getValue:()Ljava/lang/Object;
const #131 = Method	#43.#254;	//  org/apache/commons/lang/ArrayUtils.indexOf:([BB)I
const #132 = Method	#43.#255;	//  org/apache/commons/lang/ArrayUtils.indexOf:([BBI)I
const #133 = Method	#43.#256;	//  org/apache/commons/lang/ArrayUtils.indexOf:([CC)I
const #134 = Method	#43.#257;	//  org/apache/commons/lang/ArrayUtils.indexOf:([CCI)I
const #135 = Method	#43.#258;	//  org/apache/commons/lang/ArrayUtils.indexOf:([DD)I
const #136 = Method	#43.#259;	//  org/apache/commons/lang/ArrayUtils.indexOf:([DDI)I
const #137 = Method	#43.#260;	//  org/apache/commons/lang/ArrayUtils.indexOf:([DDID)I
const #138 = Method	#43.#261;	//  org/apache/commons/lang/ArrayUtils.indexOf:([FF)I
const #139 = Method	#43.#262;	//  org/apache/commons/lang/ArrayUtils.indexOf:([FFI)I
const #140 = Method	#43.#263;	//  org/apache/commons/lang/ArrayUtils.indexOf:([II)I
const #141 = Method	#43.#264;	//  org/apache/commons/lang/ArrayUtils.indexOf:([III)I
const #142 = Method	#43.#265;	//  org/apache/commons/lang/ArrayUtils.indexOf:([JJ)I
const #143 = Method	#43.#266;	//  org/apache/commons/lang/ArrayUtils.indexOf:([JJI)I
const #144 = Method	#43.#267;	//  org/apache/commons/lang/ArrayUtils.indexOf:([Ljava/lang/Object;Ljava/lang/Object;)I
const #145 = Method	#43.#268;	//  org/apache/commons/lang/ArrayUtils.indexOf:([Ljava/lang/Object;Ljava/lang/Object;I)I
const #146 = Method	#43.#269;	//  org/apache/commons/lang/ArrayUtils.indexOf:([SS)I
const #147 = Method	#43.#270;	//  org/apache/commons/lang/ArrayUtils.indexOf:([SSI)I
const #148 = Method	#43.#271;	//  org/apache/commons/lang/ArrayUtils.indexOf:([ZZ)I
const #149 = Method	#43.#272;	//  org/apache/commons/lang/ArrayUtils.indexOf:([ZZI)I
const #150 = Method	#30.#273;	//  java/lang/Integer.intValue:()I
const #151 = Method	#43.#274;	//  org/apache/commons/lang/ArrayUtils.isEmpty:([D)Z
const #152 = Method	#43.#275;	//  org/apache/commons/lang/ArrayUtils.isEmpty:([F)Z
const #153 = Method	#43.#276;	//  org/apache/commons/lang/ArrayUtils.isEmpty:([Z)Z
const #154 = Method	#44.#277;	//  org/apache/commons/lang/builder/EqualsBuilder.isEquals:()Z
const #155 = Method	#43.#278;	//  org/apache/commons/lang/ArrayUtils.lastIndexOf:([BBI)I
const #156 = Method	#43.#279;	//  org/apache/commons/lang/ArrayUtils.lastIndexOf:([CCI)I
const #157 = Method	#43.#280;	//  org/apache/commons/lang/ArrayUtils.lastIndexOf:([DDI)I
const #158 = Method	#43.#281;	//  org/apache/commons/lang/ArrayUtils.lastIndexOf:([DDID)I
const #159 = Method	#43.#282;	//  org/apache/commons/lang/ArrayUtils.lastIndexOf:([FFI)I
const #160 = Method	#43.#283;	//  org/apache/commons/lang/ArrayUtils.lastIndexOf:([III)I
const #161 = Method	#43.#284;	//  org/apache/commons/lang/ArrayUtils.lastIndexOf:([JJI)I
const #162 = Method	#43.#285;	//  org/apache/commons/lang/ArrayUtils.lastIndexOf:([Ljava/lang/Object;Ljava/lang/Object;I)I
const #163 = Method	#43.#286;	//  org/apache/commons/lang/ArrayUtils.lastIndexOf:([SSI)I
const #164 = Method	#43.#287;	//  org/apache/commons/lang/ArrayUtils.lastIndexOf:([ZZI)I
const #165 = Method	#31.#288;	//  java/lang/Long.longValue:()J
const #166 = Method	#39.#289;	//  java/lang/reflect/Array.newInstance:(Ljava/lang/Class;I)Ljava/lang/Object;
const #167 = InterfaceMethod	#41.#290;	//  java/util/Map.put:(Ljava/lang/Object;Ljava/lang/Object;)Ljava/lang/Object;
const #168 = Method	#43.#291;	//  org/apache/commons/lang/ArrayUtils.remove:(Ljava/lang/Object;I)Ljava/lang/Object;
const #169 = Method	#43.#292;	//  org/apache/commons/lang/ArrayUtils.remove:([BI)[B
const #170 = Method	#43.#293;	//  org/apache/commons/lang/ArrayUtils.remove:([CI)[C
const #171 = Method	#43.#294;	//  org/apache/commons/lang/ArrayUtils.remove:([DI)[D
const #172 = Method	#43.#295;	//  org/apache/commons/lang/ArrayUtils.remove:([FI)[F
const #173 = Method	#43.#296;	//  org/apache/commons/lang/ArrayUtils.remove:([II)[I
const #174 = Method	#43.#297;	//  org/apache/commons/lang/ArrayUtils.remove:([JI)[J
const #175 = Method	#43.#298;	//  org/apache/commons/lang/ArrayUtils.remove:([Ljava/lang/Object;I)[Ljava/lang/Object;
const #176 = Method	#43.#299;	//  org/apache/commons/lang/ArrayUtils.remove:([SI)[S
const #177 = Method	#43.#300;	//  org/apache/commons/lang/ArrayUtils.remove:([ZI)[Z
const #178 = Method	#39.#301;	//  java/lang/reflect/Array.set:(Ljava/lang/Object;ILjava/lang/Object;)V
const #179 = Method	#34.#302;	//  java/lang/Short.shortValue:()S
const #180 = Method	#45.#303;	//  org/apache/commons/lang/builder/HashCodeBuilder.toHashCode:()I
const #181 = Method	#36.#304;	//  java/lang/StringBuffer.toString:()Ljava/lang/String;
const #182 = Method	#46.#304;	//  org/apache/commons/lang/builder/ToStringBuilder.toString:()Ljava/lang/String;
const #183 = Method	#43.#305;	//  org/apache/commons/lang/ArrayUtils.toString:(Ljava/lang/Object;Ljava/lang/String;)Ljava/lang/String;
const #184 = double	1.5d;
const #186 = NameAndType	#483:#317;//  "<init>":()V
const #187 = NameAndType	#483:#319;//  "<init>":(B)V
const #188 = NameAndType	#483:#320;//  "<init>":(C)V
const #189 = NameAndType	#483:#321;//  "<init>":(D)V
const #190 = NameAndType	#483:#322;//  "<init>":(F)V
const #191 = NameAndType	#483:#324;//  "<init>":(I)V
const #192 = NameAndType	#483:#325;//  "<init>":(J)V
const #193 = NameAndType	#483:#342;//  "<init>":(Ljava/lang/Object;Lorg/apache/commons/lang/builder/ToStringStyle;)V
const #194 = NameAndType	#483:#345;//  "<init>":(Ljava/lang/String;)V
const #195 = NameAndType	#483:#346;//  "<init>":(S)V
const #196 = NameAndType	#483:#347;//  "<init>":(Z)V
const #197 = NameAndType	#490:#557;//  EMPTY_BOOLEAN_ARRAY:[Z
const #198 = NameAndType	#491:#545;//  EMPTY_BOOLEAN_OBJECT_ARRAY:[Ljava/lang/Boolean;
const #199 = NameAndType	#492:#539;//  EMPTY_BYTE_ARRAY:[B
const #200 = NameAndType	#493:#546;//  EMPTY_BYTE_OBJECT_ARRAY:[Ljava/lang/Byte;
const #201 = NameAndType	#494:#547;//  EMPTY_CHARACTER_OBJECT_ARRAY:[Ljava/lang/Character;
const #202 = NameAndType	#495:#540;//  EMPTY_CHAR_ARRAY:[C
const #203 = NameAndType	#496:#548;//  EMPTY_CLASS_ARRAY:[Ljava/lang/Class;
const #204 = NameAndType	#497:#541;//  EMPTY_DOUBLE_ARRAY:[D
const #205 = NameAndType	#498:#549;//  EMPTY_DOUBLE_OBJECT_ARRAY:[Ljava/lang/Double;
const #206 = NameAndType	#499:#542;//  EMPTY_FLOAT_ARRAY:[F
const #207 = NameAndType	#500:#550;//  EMPTY_FLOAT_OBJECT_ARRAY:[Ljava/lang/Float;
const #208 = NameAndType	#501:#551;//  EMPTY_INTEGER_OBJECT_ARRAY:[Ljava/lang/Integer;
const #209 = NameAndType	#502:#543;//  EMPTY_INT_ARRAY:[I
const #210 = NameAndType	#503:#544;//  EMPTY_LONG_ARRAY:[J
const #211 = NameAndType	#504:#552;//  EMPTY_LONG_OBJECT_ARRAY:[Ljava/lang/Long;
const #212 = NameAndType	#505:#553;//  EMPTY_OBJECT_ARRAY:[Ljava/lang/Object;
const #213 = NameAndType	#506:#556;//  EMPTY_SHORT_ARRAY:[S
const #214 = NameAndType	#507:#554;//  EMPTY_SHORT_OBJECT_ARRAY:[Ljava/lang/Short;
const #215 = NameAndType	#508:#555;//  EMPTY_STRING_ARRAY:[Ljava/lang/String;
const #216 = NameAndType	#510:#515;//  FALSE:Ljava/lang/Boolean;
const #217 = NameAndType	#532:#530;//  SIMPLE_STYLE:Lorg/apache/commons/lang/builder/ToStringStyle;
const #218 = NameAndType	#535:#515;//  TRUE:Ljava/lang/Boolean;
const #219 = NameAndType	#536:#517;//  TYPE:Ljava/lang/Class;
const #220 = NameAndType	#558:#336;//  add:(Ljava/lang/Object;ILjava/lang/Object;Ljava/lang/Class;)Ljava/lang/Object;
const #221 = NameAndType	#560:#323;//  append:(I)Ljava/lang/StringBuffer;
const #222 = NameAndType	#560:#329;//  append:(Ljava/lang/Object;)Ljava/lang/StringBuffer;
const #223 = NameAndType	#560:#330;//  append:(Ljava/lang/Object;)Lorg/apache/commons/lang/builder/HashCodeBuilder;
const #224 = NameAndType	#560:#331;//  append:(Ljava/lang/Object;)Lorg/apache/commons/lang/builder/ToStringBuilder;
const #225 = NameAndType	#560:#339;//  append:(Ljava/lang/Object;Ljava/lang/Object;)Lorg/apache/commons/lang/builder/EqualsBuilder;
const #226 = NameAndType	#560:#344;//  append:(Ljava/lang/String;)Ljava/lang/StringBuffer;
const #227 = NameAndType	#565:#335;//  arraycopy:(Ljava/lang/Object;ILjava/lang/Object;II)V
const #228 = NameAndType	#567:#318;//  booleanValue:()Z
const #229 = NameAndType	#568:#308;//  byteValue:()B
const #230 = NameAndType	#569:#343;//  class$:(Ljava/lang/String;)Ljava/lang/Class;
const #231 = NameAndType	#570:#517;//  class$java$lang$Object:Ljava/lang/Class;
const #232 = NameAndType	#571:#314;//  clone:()Ljava/lang/Object;
const #233 = NameAndType	#571:#350;//  clone:([B)[B
const #234 = NameAndType	#571:#363;//  clone:([C)[C
const #235 = NameAndType	#571:#375;//  clone:([D)[D
const #236 = NameAndType	#571:#391;//  clone:([F)[F
const #237 = NameAndType	#571:#404;//  clone:([I)[I
const #238 = NameAndType	#571:#415;//  clone:([J)[J
const #239 = NameAndType	#571:#441;//  clone:([Ljava/lang/Object;)[Ljava/lang/Object;
const #240 = NameAndType	#571:#456;//  clone:([S)[S
const #241 = NameAndType	#571:#469;//  clone:([Z)[Z
const #242 = NameAndType	#574:#337;//  copyArrayGrow1:(Ljava/lang/Object;Ljava/lang/Class;)Ljava/lang/Object;
const #243 = NameAndType	#575:#309;//  doubleValue:()D
const #244 = NameAndType	#579:#332;//  equals:(Ljava/lang/Object;)Z
const #245 = NameAndType	#580:#310;//  floatValue:()F
const #246 = NameAndType	#581:#343;//  forName:(Ljava/lang/String;)Ljava/lang/Class;
const #247 = NameAndType	#582:#313;//  getClass:()Ljava/lang/Class;
const #248 = NameAndType	#583:#313;//  getComponentType:()Ljava/lang/Class;
const #249 = NameAndType	#584:#314;//  getKey:()Ljava/lang/Object;
const #250 = NameAndType	#585:#327;//  getLength:(Ljava/lang/Object;)I
const #251 = NameAndType	#586:#315;//  getMessage:()Ljava/lang/String;
const #252 = NameAndType	#587:#315;//  getName:()Ljava/lang/String;
const #253 = NameAndType	#588:#314;//  getValue:()Ljava/lang/Object;
const #254 = NameAndType	#592:#352;//  indexOf:([BB)I
const #255 = NameAndType	#592:#355;//  indexOf:([BBI)I
const #256 = NameAndType	#592:#364;//  indexOf:([CC)I
const #257 = NameAndType	#592:#367;//  indexOf:([CCI)I
const #258 = NameAndType	#592:#377;//  indexOf:([DD)I
const #259 = NameAndType	#592:#382;//  indexOf:([DDI)I
const #260 = NameAndType	#592:#383;//  indexOf:([DDID)I
const #261 = NameAndType	#592:#393;//  indexOf:([FF)I
const #262 = NameAndType	#592:#396;//  indexOf:([FFI)I
const #263 = NameAndType	#592:#406;//  indexOf:([II)I
const #264 = NameAndType	#592:#409;//  indexOf:([III)I
const #265 = NameAndType	#592:#420;//  indexOf:([JJ)I
const #266 = NameAndType	#592:#423;//  indexOf:([JJI)I
const #267 = NameAndType	#592:#445;//  indexOf:([Ljava/lang/Object;Ljava/lang/Object;)I
const #268 = NameAndType	#592:#448;//  indexOf:([Ljava/lang/Object;Ljava/lang/Object;I)I
const #269 = NameAndType	#592:#460;//  indexOf:([SS)I
const #270 = NameAndType	#592:#463;//  indexOf:([SSI)I
const #271 = NameAndType	#592:#473;//  indexOf:([ZZ)I
const #272 = NameAndType	#592:#476;//  indexOf:([ZZI)I
const #273 = NameAndType	#593:#311;//  intValue:()I
const #274 = NameAndType	#594:#374;//  isEmpty:([D)Z
const #275 = NameAndType	#594:#390;//  isEmpty:([F)Z
const #276 = NameAndType	#594:#467;//  isEmpty:([Z)Z
const #277 = NameAndType	#595:#318;//  isEquals:()Z
const #278 = NameAndType	#623:#355;//  lastIndexOf:([BBI)I
const #279 = NameAndType	#623:#367;//  lastIndexOf:([CCI)I
const #280 = NameAndType	#623:#382;//  lastIndexOf:([DDI)I
const #281 = NameAndType	#623:#383;//  lastIndexOf:([DDID)I
const #282 = NameAndType	#623:#396;//  lastIndexOf:([FFI)I
const #283 = NameAndType	#623:#409;//  lastIndexOf:([III)I
const #284 = NameAndType	#623:#423;//  lastIndexOf:([JJI)I
const #285 = NameAndType	#623:#448;//  lastIndexOf:([Ljava/lang/Object;Ljava/lang/Object;I)I
const #286 = NameAndType	#623:#463;//  lastIndexOf:([SSI)I
const #287 = NameAndType	#623:#476;//  lastIndexOf:([ZZI)I
const #288 = NameAndType	#625:#312;//  longValue:()J
const #289 = NameAndType	#631:#326;//  newInstance:(Ljava/lang/Class;I)Ljava/lang/Object;
const #290 = NameAndType	#640:#338;//  put:(Ljava/lang/Object;Ljava/lang/Object;)Ljava/lang/Object;
const #291 = NameAndType	#641:#333;//  remove:(Ljava/lang/Object;I)Ljava/lang/Object;
const #292 = NameAndType	#641:#356;//  remove:([BI)[B
const #293 = NameAndType	#641:#368;//  remove:([CI)[C
const #294 = NameAndType	#641:#384;//  remove:([DI)[D
const #295 = NameAndType	#641:#397;//  remove:([FI)[F
const #296 = NameAndType	#641:#408;//  remove:([II)[I
const #297 = NameAndType	#641:#417;//  remove:([JI)[J
const #298 = NameAndType	#641:#442;//  remove:([Ljava/lang/Object;I)[Ljava/lang/Object;
const #299 = NameAndType	#641:#457;//  remove:([SI)[S
const #300 = NameAndType	#641:#470;//  remove:([ZI)[Z
const #301 = NameAndType	#645:#334;//  set:(Ljava/lang/Object;ILjava/lang/Object;)V
const #302 = NameAndType	#646:#316;//  shortValue:()S
const #303 = NameAndType	#653:#311;//  toHashCode:()I
const #304 = NameAndType	#657:#315;//  toString:()Ljava/lang/String;
const #305 = NameAndType	#657:#341;//  toString:(Ljava/lang/Object;Ljava/lang/String;)Ljava/lang/String;
const #306 = Asciz	', has a length less than 2;
const #307 = Asciz	', is neither of type Map.Entry nor an Array;
const #308 = Asciz	()B;
const #309 = Asciz	()D;
const #310 = Asciz	()F;
const #311 = Asciz	()I;
const #312 = Asciz	()J;
const #313 = Asciz	()Ljava/lang/Class;;
const #314 = Asciz	()Ljava/lang/Object;;
const #315 = Asciz	()Ljava/lang/String;;
const #316 = Asciz	()S;
const #317 = Asciz	()V;
const #318 = Asciz	()Z;
const #319 = Asciz	(B)V;
const #320 = Asciz	(C)V;
const #321 = Asciz	(D)V;
const #322 = Asciz	(F)V;
const #323 = Asciz	(I)Ljava/lang/StringBuffer;;
const #324 = Asciz	(I)V;
const #325 = Asciz	(J)V;
const #326 = Asciz	(Ljava/lang/Class;I)Ljava/lang/Object;;
const #327 = Asciz	(Ljava/lang/Object;)I;
const #328 = Asciz	(Ljava/lang/Object;)Ljava/lang/String;;
const #329 = Asciz	(Ljava/lang/Object;)Ljava/lang/StringBuffer;;
const #330 = Asciz	(Ljava/lang/Object;)Lorg/apache/commons/lang/builder/HashCodeBuilder;;
const #331 = Asciz	(Ljava/lang/Object;)Lorg/apache/commons/lang/builder/ToStringBuilder;;
const #332 = Asciz	(Ljava/lang/Object;)Z;
const #333 = Asciz	(Ljava/lang/Object;I)Ljava/lang/Object;;
const #334 = Asciz	(Ljava/lang/Object;ILjava/lang/Object;)V;
const #335 = Asciz	(Ljava/lang/Object;ILjava/lang/Object;II)V;
const #336 = Asciz	(Ljava/lang/Object;ILjava/lang/Object;Ljava/lang/Class;)Ljava/lang/Object;;
const #337 = Asciz	(Ljava/lang/Object;Ljava/lang/Class;)Ljava/lang/Object;;
const #338 = Asciz	(Ljava/lang/Object;Ljava/lang/Object;)Ljava/lang/Object;;
const #339 = Asciz	(Ljava/lang/Object;Ljava/lang/Object;)Lorg/apache/commons/lang/builder/EqualsBuilder;;
const #340 = Asciz	(Ljava/lang/Object;Ljava/lang/Object;)Z;
const #341 = Asciz	(Ljava/lang/Object;Ljava/lang/String;)Ljava/lang/String;;
const #342 = Asciz	(Ljava/lang/Object;Lorg/apache/commons/lang/builder/ToStringStyle;)V;
const #343 = Asciz	(Ljava/lang/String;)Ljava/lang/Class;;
const #344 = Asciz	(Ljava/lang/String;)Ljava/lang/StringBuffer;;
const #345 = Asciz	(Ljava/lang/String;)V;
const #346 = Asciz	(S)V;
const #347 = Asciz	(Z)V;
const #348 = Asciz	([B)V;
const #349 = Asciz	([B)Z;
const #350 = Asciz	([B)[B;
const #351 = Asciz	([B)[Ljava/lang/Byte;;
const #352 = Asciz	([BB)I;
const #353 = Asciz	([BB)Z;
const #354 = Asciz	([BB)[B;
const #355 = Asciz	([BBI)I;
const #356 = Asciz	([BI)[B;
const #357 = Asciz	([BIB)[B;
const #358 = Asciz	([BII)[B;
const #359 = Asciz	([B[B)Z;
const #360 = Asciz	([B[B)[B;
const #361 = Asciz	([C)V;
const #362 = Asciz	([C)Z;
const #363 = Asciz	([C)[C;
const #364 = Asciz	([CC)I;
const #365 = Asciz	([CC)Z;
const #366 = Asciz	([CC)[C;
const #367 = Asciz	([CCI)I;
const #368 = Asciz	([CI)[C;
const #369 = Asciz	([CIC)[C;
const #370 = Asciz	([CII)[C;
const #371 = Asciz	([C[C)Z;
const #372 = Asciz	([C[C)[C;
const #373 = Asciz	([D)V;
const #374 = Asciz	([D)Z;
const #375 = Asciz	([D)[D;
const #376 = Asciz	([D)[Ljava/lang/Double;;
const #377 = Asciz	([DD)I;
const #378 = Asciz	([DD)Z;
const #379 = Asciz	([DD)[D;
const #380 = Asciz	([DDD)I;
const #381 = Asciz	([DDD)Z;
const #382 = Asciz	([DDI)I;
const #383 = Asciz	([DDID)I;
const #384 = Asciz	([DI)[D;
const #385 = Asciz	([DID)[D;
const #386 = Asciz	([DII)[D;
const #387 = Asciz	([D[D)Z;
const #388 = Asciz	([D[D)[D;
const #389 = Asciz	([F)V;
const #390 = Asciz	([F)Z;
const #391 = Asciz	([F)[F;
const #392 = Asciz	([F)[Ljava/lang/Float;;
const #393 = Asciz	([FF)I;
const #394 = Asciz	([FF)Z;
const #395 = Asciz	([FF)[F;
const #396 = Asciz	([FFI)I;
const #397 = Asciz	([FI)[F;
const #398 = Asciz	([FIF)[F;
const #399 = Asciz	([FII)[F;
const #400 = Asciz	([F[F)Z;
const #401 = Asciz	([F[F)[F;
const #402 = Asciz	([I)V;
const #403 = Asciz	([I)Z;
const #404 = Asciz	([I)[I;
const #405 = Asciz	([I)[Ljava/lang/Integer;;
const #406 = Asciz	([II)I;
const #407 = Asciz	([II)Z;
const #408 = Asciz	([II)[I;
const #409 = Asciz	([III)I;
const #410 = Asciz	([III)[I;
const #411 = Asciz	([I[I)Z;
const #412 = Asciz	([I[I)[I;
const #413 = Asciz	([J)V;
const #414 = Asciz	([J)Z;
const #415 = Asciz	([J)[J;
const #416 = Asciz	([J)[Ljava/lang/Long;;
const #417 = Asciz	([JI)[J;
const #418 = Asciz	([JII)[J;
const #419 = Asciz	([JIJ)[J;
const #420 = Asciz	([JJ)I;
const #421 = Asciz	([JJ)Z;
const #422 = Asciz	([JJ)[J;
const #423 = Asciz	([JJI)I;
const #424 = Asciz	([J[J)Z;
const #425 = Asciz	([J[J)[J;
const #426 = Asciz	([Ljava/lang/Boolean;)[Z;
const #427 = Asciz	([Ljava/lang/Boolean;Z)[Z;
const #428 = Asciz	([Ljava/lang/Byte;)[B;
const #429 = Asciz	([Ljava/lang/Byte;B)[B;
const #430 = Asciz	([Ljava/lang/Double;)[D;
const #431 = Asciz	([Ljava/lang/Double;D)[D;
const #432 = Asciz	([Ljava/lang/Float;)[F;
const #433 = Asciz	([Ljava/lang/Float;F)[F;
const #434 = Asciz	([Ljava/lang/Integer;)[I;
const #435 = Asciz	([Ljava/lang/Integer;I)[I;
const #436 = Asciz	([Ljava/lang/Long;)[J;
const #437 = Asciz	([Ljava/lang/Long;J)[J;
const #438 = Asciz	([Ljava/lang/Object;)Ljava/util/Map;;
const #439 = Asciz	([Ljava/lang/Object;)V;
const #440 = Asciz	([Ljava/lang/Object;)Z;
const #441 = Asciz	([Ljava/lang/Object;)[Ljava/lang/Object;;
const #442 = Asciz	([Ljava/lang/Object;I)[Ljava/lang/Object;;
const #443 = Asciz	([Ljava/lang/Object;II)[Ljava/lang/Object;;
const #444 = Asciz	([Ljava/lang/Object;ILjava/lang/Object;)[Ljava/lang/Object;;
const #445 = Asciz	([Ljava/lang/Object;Ljava/lang/Object;)I;
const #446 = Asciz	([Ljava/lang/Object;Ljava/lang/Object;)Z;
const #447 = Asciz	([Ljava/lang/Object;Ljava/lang/Object;)[Ljava/lang/Object;;
const #448 = Asciz	([Ljava/lang/Object;Ljava/lang/Object;I)I;
const #449 = Asciz	([Ljava/lang/Object;[Ljava/lang/Object;)Z;
const #450 = Asciz	([Ljava/lang/Object;[Ljava/lang/Object;)[Ljava/lang/Object;;
const #451 = Asciz	([Ljava/lang/Short;)[S;
const #452 = Asciz	([Ljava/lang/Short;S)[S;
const #453 = Asciz	([S)V;
const #454 = Asciz	([S)Z;
const #455 = Asciz	([S)[Ljava/lang/Short;;
const #456 = Asciz	([S)[S;
const #457 = Asciz	([SI)[S;
const #458 = Asciz	([SII)[S;
const #459 = Asciz	([SIS)[S;
const #460 = Asciz	([SS)I;
const #461 = Asciz	([SS)Z;
const #462 = Asciz	([SS)[S;
const #463 = Asciz	([SSI)I;
const #464 = Asciz	([S[S)Z;
const #465 = Asciz	([S[S)[S;
const #466 = Asciz	([Z)V;
const #467 = Asciz	([Z)Z;
const #468 = Asciz	([Z)[Ljava/lang/Boolean;;
const #469 = Asciz	([Z)[Z;
const #470 = Asciz	([ZI)[Z;
const #471 = Asciz	([ZII)[Z;
const #472 = Asciz	([ZIZ)[Z;
const #473 = Asciz	([ZZ)I;
const #474 = Asciz	([ZZ)Z;
const #475 = Asciz	([ZZ)[Z;
const #476 = Asciz	([ZZI)I;
const #477 = Asciz	([Z[Z)Z;
const #478 = Asciz	([Z[Z)[Z;
const #479 = Asciz	, ';
const #480 = Asciz	, Length: ;
const #481 = Asciz	, Length: 0;
const #482 = Asciz	<clinit>;
const #483 = Asciz	<init>;
const #484 = Asciz	Array element ;
const #485 = Asciz	ArrayUtils.java;
const #486 = Asciz	B;
const #487 = Asciz	C;
const #488 = Asciz	Code;
const #489 = Asciz	D;
const #490 = Asciz	EMPTY_BOOLEAN_ARRAY;
const #491 = Asciz	EMPTY_BOOLEAN_OBJECT_ARRAY;
const #492 = Asciz	EMPTY_BYTE_ARRAY;
const #493 = Asciz	EMPTY_BYTE_OBJECT_ARRAY;
const #494 = Asciz	EMPTY_CHARACTER_OBJECT_ARRAY;
const #495 = Asciz	EMPTY_CHAR_ARRAY;
const #496 = Asciz	EMPTY_CLASS_ARRAY;
const #497 = Asciz	EMPTY_DOUBLE_ARRAY;
const #498 = Asciz	EMPTY_DOUBLE_OBJECT_ARRAY;
const #499 = Asciz	EMPTY_FLOAT_ARRAY;
const #500 = Asciz	EMPTY_FLOAT_OBJECT_ARRAY;
const #501 = Asciz	EMPTY_INTEGER_OBJECT_ARRAY;
const #502 = Asciz	EMPTY_INT_ARRAY;
const #503 = Asciz	EMPTY_LONG_ARRAY;
const #504 = Asciz	EMPTY_LONG_OBJECT_ARRAY;
const #505 = Asciz	EMPTY_OBJECT_ARRAY;
const #506 = Asciz	EMPTY_SHORT_ARRAY;
const #507 = Asciz	EMPTY_SHORT_OBJECT_ARRAY;
const #508 = Asciz	EMPTY_STRING_ARRAY;
const #509 = Asciz	F;
const #510 = Asciz	FALSE;
const #511 = Asciz	I;
const #512 = Asciz	Index: ;
const #513 = Asciz	J;
const #514 = Asciz	LineNumberTable;
const #515 = Asciz	Ljava/lang/Boolean;;
const #516 = Asciz	Ljava/lang/Byte;;
const #517 = Asciz	Ljava/lang/Class;;
const #518 = Asciz	Ljava/lang/ClassNotFoundException;;
const #519 = Asciz	Ljava/lang/Double;;
const #520 = Asciz	Ljava/lang/Float;;
const #521 = Asciz	Ljava/lang/Integer;;
const #522 = Asciz	Ljava/lang/Long;;
const #523 = Asciz	Ljava/lang/Object;;
const #524 = Asciz	Ljava/lang/Short;;
const #525 = Asciz	Ljava/lang/String;;
const #526 = Asciz	Ljava/util/Map$Entry;;
const #527 = Asciz	Ljava/util/Map;;
const #528 = Asciz	LocalVariableTable;
const #529 = Asciz	Lorg/apache/commons/lang/ArrayUtils;;
const #530 = Asciz	Lorg/apache/commons/lang/builder/ToStringStyle;;
const #531 = Asciz	S;
const #532 = Asciz	SIMPLE_STYLE;
const #533 = Asciz	SourceFile;
const #534 = Asciz	Synthetic;
const #535 = Asciz	TRUE;
const #536 = Asciz	TYPE;
const #537 = Asciz	The Array must not be null;
const #538 = Asciz	Z;
const #539 = Asciz	[B;
const #540 = Asciz	[C;
const #541 = Asciz	[D;
const #542 = Asciz	[F;
const #543 = Asciz	[I;
const #544 = Asciz	[J;
const #545 = Asciz	[Ljava/lang/Boolean;;
const #546 = Asciz	[Ljava/lang/Byte;;
const #547 = Asciz	[Ljava/lang/Character;;
const #548 = Asciz	[Ljava/lang/Class;;
const #549 = Asciz	[Ljava/lang/Double;;
const #550 = Asciz	[Ljava/lang/Float;;
const #551 = Asciz	[Ljava/lang/Integer;;
const #552 = Asciz	[Ljava/lang/Long;;
const #553 = Asciz	[Ljava/lang/Object;;
const #554 = Asciz	[Ljava/lang/Short;;
const #555 = Asciz	[Ljava/lang/String;;
const #556 = Asciz	[S;
const #557 = Asciz	[Z;
const #558 = Asciz	add;
const #559 = Asciz	addAll;
const #560 = Asciz	append;
const #561 = Asciz	array;
const #562 = Asciz	array1;
const #563 = Asciz	array2;
const #564 = Asciz	arrayLength;
const #565 = Asciz	arraycopy;
const #566 = Asciz	b;
const #567 = Asciz	booleanValue;
const #568 = Asciz	byteValue;
const #569 = Asciz	class$;
const #570 = Asciz	class$java$lang$Object;
const #571 = Asciz	clone;
const #572 = Asciz	clss;
const #573 = Asciz	contains;
const #574 = Asciz	copyArrayGrow1;
const #575 = Asciz	doubleValue;
const #576 = Asciz	element;
const #577 = Asciz	endIndexExclusive;
const #578 = Asciz	entry;
const #579 = Asciz	equals;
const #580 = Asciz	floatValue;
const #581 = Asciz	forName;
const #582 = Asciz	getClass;
const #583 = Asciz	getComponentType;
const #584 = Asciz	getKey;
const #585 = Asciz	getLength;
const #586 = Asciz	getMessage;
const #587 = Asciz	getName;
const #588 = Asciz	getValue;
const #589 = Asciz	hashCode;
const #590 = Asciz	i;
const #591 = Asciz	index;
const #592 = Asciz	indexOf;
const #593 = Asciz	intValue;
const #594 = Asciz	isEmpty;
const #595 = Asciz	isEquals;
const #596 = Asciz	isSameLength;
const #597 = Asciz	isSameType;
const #598 = Asciz	j;
const #599 = Asciz	java.lang.Object;
const #600 = Asciz	java/lang/Boolean;
const #601 = Asciz	java/lang/Byte;
const #602 = Asciz	java/lang/Character;
const #603 = Asciz	java/lang/Class;
const #604 = Asciz	java/lang/ClassNotFoundException;
const #605 = Asciz	java/lang/Double;
const #606 = Asciz	java/lang/Float;
const #607 = Asciz	java/lang/IllegalArgumentException;
const #608 = Asciz	java/lang/IndexOutOfBoundsException;
const #609 = Asciz	java/lang/Integer;
const #610 = Asciz	java/lang/Long;
const #611 = Asciz	java/lang/NoClassDefFoundError;
const #612 = Asciz	java/lang/Object;
const #613 = Asciz	java/lang/Short;
const #614 = Asciz	java/lang/String;
const #615 = Asciz	java/lang/StringBuffer;
const #616 = Asciz	java/lang/System;
const #617 = Asciz	java/lang/Throwable;
const #618 = Asciz	java/lang/reflect/Array;
const #619 = Asciz	java/util/HashMap;
const #620 = Asciz	java/util/Map;
const #621 = Asciz	java/util/Map$Entry;
const #622 = Asciz	joinedArray;
const #623 = Asciz	lastIndexOf;
const #624 = Asciz	length;
const #625 = Asciz	longValue;
const #626 = Asciz	map;
const #627 = Asciz	max;
const #628 = Asciz	min;
const #629 = Asciz	newArray;
const #630 = Asciz	newArrayComponentType;
const #631 = Asciz	newInstance;
const #632 = Asciz	newSize;
const #633 = Asciz	object;
const #634 = Asciz	objectToFind;
const #635 = Asciz	org/apache/commons/lang/ArrayUtils;
const #636 = Asciz	org/apache/commons/lang/builder/EqualsBuilder;
const #637 = Asciz	org/apache/commons/lang/builder/HashCodeBuilder;
const #638 = Asciz	org/apache/commons/lang/builder/ToStringBuilder;
const #639 = Asciz	org/apache/commons/lang/builder/ToStringStyle;
const #640 = Asciz	put;
const #641 = Asciz	remove;
const #642 = Asciz	removeElement;
const #643 = Asciz	result;
const #644 = Asciz	reverse;
const #645 = Asciz	set;
const #646 = Asciz	shortValue;
const #647 = Asciz	startIndex;
const #648 = Asciz	startIndexInclusive;
const #649 = Asciz	stringIfNull;
const #650 = Asciz	subarray;
const #651 = Asciz	this;
const #652 = Asciz	tmp;
const #653 = Asciz	toHashCode;
const #654 = Asciz	toMap;
const #655 = Asciz	toObject;
const #656 = Asciz	toPrimitive;
const #657 = Asciz	toString;
const #658 = Asciz	tolerance;
const #659 = Asciz	type;
const #660 = Asciz	valueForNull;
const #661 = Asciz	valueToFind;
const #662 = Asciz	{};

{
public static final java.lang.Object[] EMPTY_OBJECT_ARRAY;

public static final java.lang.Class[] EMPTY_CLASS_ARRAY;

public static final java.lang.String[] EMPTY_STRING_ARRAY;

public static final long[] EMPTY_LONG_ARRAY;

public static final java.lang.Long[] EMPTY_LONG_OBJECT_ARRAY;

public static final int[] EMPTY_INT_ARRAY;

public static final java.lang.Integer[] EMPTY_INTEGER_OBJECT_ARRAY;

public static final short[] EMPTY_SHORT_ARRAY;

public static final java.lang.Short[] EMPTY_SHORT_OBJECT_ARRAY;

public static final byte[] EMPTY_BYTE_ARRAY;

public static final java.lang.Byte[] EMPTY_BYTE_OBJECT_ARRAY;

public static final double[] EMPTY_DOUBLE_ARRAY;

public static final java.lang.Double[] EMPTY_DOUBLE_OBJECT_ARRAY;

public static final float[] EMPTY_FLOAT_ARRAY;

public static final java.lang.Float[] EMPTY_FLOAT_OBJECT_ARRAY;

public static final boolean[] EMPTY_BOOLEAN_ARRAY;

public static final java.lang.Boolean[] EMPTY_BOOLEAN_OBJECT_ARRAY;

public static final char[] EMPTY_CHAR_ARRAY;

public static final java.lang.Character[] EMPTY_CHARACTER_OBJECT_ARRAY;

static java.lang.Class class$java$lang$Object;
  Synthetic: true

static {};
  Code:
   Stack=1, Locals=0, Args_size=0
   0:	iconst_0
   1:	anewarray	#33; //class java/lang/Object
   4:	putstatic	#80; //Field EMPTY_OBJECT_ARRAY:[Ljava/lang/Object;
   7:	iconst_0
   8:	anewarray	#24; //class java/lang/Class
   11:	putstatic	#71; //Field EMPTY_CLASS_ARRAY:[Ljava/lang/Class;
   14:	iconst_0
   15:	anewarray	#35; //class java/lang/String
   18:	putstatic	#83; //Field EMPTY_STRING_ARRAY:[Ljava/lang/String;
   21:	iconst_0
   22:	newarray long
   24:	putstatic	#78; //Field EMPTY_LONG_ARRAY:[J
   27:	iconst_0
   28:	anewarray	#31; //class java/lang/Long
   31:	putstatic	#79; //Field EMPTY_LONG_OBJECT_ARRAY:[Ljava/lang/Long;
   34:	iconst_0
   35:	newarray int
   37:	putstatic	#77; //Field EMPTY_INT_ARRAY:[I
   40:	iconst_0
   41:	anewarray	#30; //class java/lang/Integer
   44:	putstatic	#76; //Field EMPTY_INTEGER_OBJECT_ARRAY:[Ljava/lang/Integer;
   47:	iconst_0
   48:	newarray short
   50:	putstatic	#81; //Field EMPTY_SHORT_ARRAY:[S
   53:	iconst_0
   54:	anewarray	#34; //class java/lang/Short
   57:	putstatic	#82; //Field EMPTY_SHORT_OBJECT_ARRAY:[Ljava/lang/Short;
   60:	iconst_0
   61:	newarray byte
   63:	putstatic	#67; //Field EMPTY_BYTE_ARRAY:[B
   66:	iconst_0
   67:	anewarray	#22; //class java/lang/Byte
   70:	putstatic	#68; //Field EMPTY_BYTE_OBJECT_ARRAY:[Ljava/lang/Byte;
   73:	iconst_0
   74:	newarray double
   76:	putstatic	#72; //Field EMPTY_DOUBLE_ARRAY:[D
   79:	iconst_0
   80:	anewarray	#26; //class java/lang/Double
   83:	putstatic	#73; //Field EMPTY_DOUBLE_OBJECT_ARRAY:[Ljava/lang/Double;
   86:	iconst_0
   87:	newarray float
   89:	putstatic	#74; //Field EMPTY_FLOAT_ARRAY:[F
   92:	iconst_0
   93:	anewarray	#27; //class java/lang/Float
   96:	putstatic	#75; //Field EMPTY_FLOAT_OBJECT_ARRAY:[Ljava/lang/Float;
   99:	iconst_0
   100:	newarray boolean
   102:	putstatic	#65; //Field EMPTY_BOOLEAN_ARRAY:[Z
   105:	iconst_0
   106:	anewarray	#21; //class java/lang/Boolean
   109:	putstatic	#66; //Field EMPTY_BOOLEAN_OBJECT_ARRAY:[Ljava/lang/Boolean;
   112:	iconst_0
   113:	newarray char
   115:	putstatic	#70; //Field EMPTY_CHAR_ARRAY:[C
   118:	iconst_0
   119:	anewarray	#23; //class java/lang/Character
   122:	putstatic	#69; //Field EMPTY_CHARACTER_OBJECT_ARRAY:[Ljava/lang/Character;
   125:	return
  LineNumberTable: 
   line 54: 0
   line 58: 7
   line 62: 14
   line 66: 21
   line 70: 27
   line 74: 34
   line 78: 40
   line 82: 47
   line 86: 53
   line 90: 60
   line 94: 66
   line 98: 73
   line 102: 79
   line 106: 86
   line 110: 92
   line 114: 99
   line 118: 105
   line 122: 112
   line 126: 118
   line 49: 125



public org.apache.commons.lang.ArrayUtils();
  Code:
   Stack=1, Locals=1, Args_size=1
   0:	aload_0
   1:	invokespecial	#48; //Method java/lang/Object."<init>":()V
   4:	return
  LineNumberTable: 
   line 135: 0

  LocalVariableTable: 
   Start  Length  Slot  Name   Signature
   0      5      0    this       Lorg/apache/commons/lang/ArrayUtils;


public static byte[] add(byte[], byte);
  Code:
   Stack=3, Locals=3, Args_size=2
   0:	aload_0
   1:	getstatic	#88; //Field java/lang/Byte.TYPE:Ljava/lang/Class;
   4:	invokestatic	#117; //Method copyArrayGrow1:(Ljava/lang/Object;Ljava/lang/Class;)Ljava/lang/Object;
   7:	checkcast	#12; //class "[B"
   10:	astore_2
   11:	aload_2
   12:	aload_2
   13:	arraylength
   14:	iconst_1
   15:	isub
   16:	iload_1
   17:	bastore
   18:	aload_2
   19:	areturn
  LineNumberTable: 
   line 3209: 0
   line 3210: 11
   line 3211: 18

  LocalVariableTable: 
   Start  Length  Slot  Name   Signature
   0      20      0    array       [B
   0      20      1    element       B
   11      9      2    newArray       [B


public static byte[] add(byte[], int, byte);
  Code:
   Stack=5, Locals=3, Args_size=3
   0:	aload_0
   1:	iload_1
   2:	new	#22; //class java/lang/Byte
   5:	dup
   6:	iload_2
   7:	invokespecial	#51; //Method java/lang/Byte."<init>":(B)V
   10:	getstatic	#88; //Field java/lang/Byte.TYPE:Ljava/lang/Class;
   13:	invokestatic	#95; //Method add:(Ljava/lang/Object;ILjava/lang/Object;Ljava/lang/Class;)Ljava/lang/Object;
   16:	checkcast	#12; //class "[B"
   19:	areturn
  LineNumberTable: 
   line 3528: 0

  LocalVariableTable: 
   Start  Length  Slot  Name   Signature
   0      20      0    array       [B
   0      20      1    index       I
   0      20      2    element       B


public static char[] add(char[], char);
  Code:
   Stack=3, Locals=3, Args_size=2
   0:	aload_0
   1:	getstatic	#89; //Field java/lang/Character.TYPE:Ljava/lang/Class;
   4:	invokestatic	#117; //Method copyArrayGrow1:(Ljava/lang/Object;Ljava/lang/Class;)Ljava/lang/Object;
   7:	checkcast	#13; //class "[C"
   10:	astore_2
   11:	aload_2
   12:	aload_2
   13:	arraylength
   14:	iconst_1
   15:	isub
   16:	iload_1
   17:	castore
   18:	aload_2
   19:	areturn
  LineNumberTable: 
   line 3236: 0
   line 3237: 11
   line 3238: 18

  LocalVariableTable: 
   Start  Length  Slot  Name   Signature
   0      20      0    array       [C
   0      20      1    element       C
   11      9      2    newArray       [C


public static char[] add(char[], int, char);
  Code:
   Stack=5, Locals=3, Args_size=3
   0:	aload_0
   1:	iload_1
   2:	new	#23; //class java/lang/Character
   5:	dup
   6:	iload_2
   7:	invokespecial	#52; //Method java/lang/Character."<init>":(C)V
   10:	getstatic	#89; //Field java/lang/Character.TYPE:Ljava/lang/Class;
   13:	invokestatic	#95; //Method add:(Ljava/lang/Object;ILjava/lang/Object;Ljava/lang/Class;)Ljava/lang/Object;
   16:	checkcast	#13; //class "[C"
   19:	areturn
  LineNumberTable: 
   line 3497: 0

  LocalVariableTable: 
   Start  Length  Slot  Name   Signature
   0      20      0    array       [C
   0      20      1    index       I
   0      20      2    element       C


public static double[] add(double[], double);
  Code:
   Stack=4, Locals=4, Args_size=2
   0:	aload_0
   1:	getstatic	#90; //Field java/lang/Double.TYPE:Ljava/lang/Class;
   4:	invokestatic	#117; //Method copyArrayGrow1:(Ljava/lang/Object;Ljava/lang/Class;)Ljava/lang/Object;
   7:	checkcast	#14; //class "[D"
   10:	astore_3
   11:	aload_3
   12:	aload_3
   13:	arraylength
   14:	iconst_1
   15:	isub
   16:	dload_1
   17:	dastore
   18:	aload_3
   19:	areturn
  LineNumberTable: 
   line 3263: 0
   line 3264: 11
   line 3265: 18

  LocalVariableTable: 
   Start  Length  Slot  Name   Signature
   0      20      0    array       [D
   0      20      1    element       D
   11      9      3    newArray       [D


public static double[] add(double[], int, double);
  Code:
   Stack=6, Locals=4, Args_size=3
   0:	aload_0
   1:	iload_1
   2:	new	#26; //class java/lang/Double
   5:	dup
   6:	dload_2
   7:	invokespecial	#53; //Method java/lang/Double."<init>":(D)V
   10:	getstatic	#90; //Field java/lang/Double.TYPE:Ljava/lang/Class;
   13:	invokestatic	#95; //Method add:(Ljava/lang/Object;ILjava/lang/Object;Ljava/lang/Class;)Ljava/lang/Object;
   16:	checkcast	#14; //class "[D"
   19:	areturn
  LineNumberTable: 
   line 3683: 0

  LocalVariableTable: 
   Start  Length  Slot  Name   Signature
   0      20      0    array       [D
   0      20      1    index       I
   0      20      2    element       D


public static float[] add(float[], float);
  Code:
   Stack=3, Locals=3, Args_size=2
   0:	aload_0
   1:	getstatic	#91; //Field java/lang/Float.TYPE:Ljava/lang/Class;
   4:	invokestatic	#117; //Method copyArrayGrow1:(Ljava/lang/Object;Ljava/lang/Class;)Ljava/lang/Object;
   7:	checkcast	#15; //class "[F"
   10:	astore_2
   11:	aload_2
   12:	aload_2
   13:	arraylength
   14:	iconst_1
   15:	isub
   16:	fload_1
   17:	fastore
   18:	aload_2
   19:	areturn
  LineNumberTable: 
   line 3290: 0
   line 3291: 11
   line 3292: 18

  LocalVariableTable: 
   Start  Length  Slot  Name   Signature
   0      20      0    array       [F
   0      20      1    element       F
   11      9      2    newArray       [F


public static float[] add(float[], int, float);
  Code:
   Stack=5, Locals=3, Args_size=3
   0:	aload_0
   1:	iload_1
   2:	new	#27; //class java/lang/Float
   5:	dup
   6:	fload_2
   7:	invokespecial	#54; //Method java/lang/Float."<init>":(F)V
   10:	getstatic	#91; //Field java/lang/Float.TYPE:Ljava/lang/Class;
   13:	invokestatic	#95; //Method add:(Ljava/lang/Object;ILjava/lang/Object;Ljava/lang/Class;)Ljava/lang/Object;
   16:	checkcast	#15; //class "[F"
   19:	areturn
  LineNumberTable: 
   line 3652: 0

  LocalVariableTable: 
   Start  Length  Slot  Name   Signature
   0      20      0    array       [F
   0      20      1    index       I
   0      20      2    element       F


public static int[] add(int[], int);
  Code:
   Stack=3, Locals=3, Args_size=2
   0:	aload_0
   1:	getstatic	#92; //Field java/lang/Integer.TYPE:Ljava/lang/Class;
   4:	invokestatic	#117; //Method copyArrayGrow1:(Ljava/lang/Object;Ljava/lang/Class;)Ljava/lang/Object;
   7:	checkcast	#16; //class "[I"
   10:	astore_2
   11:	aload_2
   12:	aload_2
   13:	arraylength
   14:	iconst_1
   15:	isub
   16:	iload_1
   17:	iastore
   18:	aload_2
   19:	areturn
  LineNumberTable: 
   line 3317: 0
   line 3318: 11
   line 3319: 18

  LocalVariableTable: 
   Start  Length  Slot  Name   Signature
   0      20      0    array       [I
   0      20      1    element       I
   11      9      2    newArray       [I


public static int[] add(int[], int, int);
  Code:
   Stack=5, Locals=3, Args_size=3
   0:	aload_0
   1:	iload_1
   2:	new	#30; //class java/lang/Integer
   5:	dup
   6:	iload_2
   7:	invokespecial	#55; //Method java/lang/Integer."<init>":(I)V
   10:	getstatic	#92; //Field java/lang/Integer.TYPE:Ljava/lang/Class;
   13:	invokestatic	#95; //Method add:(Ljava/lang/Object;ILjava/lang/Object;Ljava/lang/Class;)Ljava/lang/Object;
   16:	checkcast	#16; //class "[I"
   19:	areturn
  LineNumberTable: 
   line 3590: 0

  LocalVariableTable: 
   Start  Length  Slot  Name   Signature
   0      20      0    array       [I
   0      20      1    index       I
   0      20      2    element       I


public static long[] add(long[], int, long);
  Code:
   Stack=6, Locals=4, Args_size=3
   0:	aload_0
   1:	iload_1
   2:	new	#31; //class java/lang/Long
   5:	dup
   6:	lload_2
   7:	invokespecial	#57; //Method java/lang/Long."<init>":(J)V
   10:	getstatic	#93; //Field java/lang/Long.TYPE:Ljava/lang/Class;
   13:	invokestatic	#95; //Method add:(Ljava/lang/Object;ILjava/lang/Object;Ljava/lang/Class;)Ljava/lang/Object;
   16:	checkcast	#17; //class "[J"
   19:	areturn
  LineNumberTable: 
   line 3621: 0

  LocalVariableTable: 
   Start  Length  Slot  Name   Signature
   0      20      0    array       [J
   0      20      1    index       I
   0      20      2    element       J


public static long[] add(long[], long);
  Code:
   Stack=4, Locals=4, Args_size=2
   0:	aload_0
   1:	getstatic	#93; //Field java/lang/Long.TYPE:Ljava/lang/Class;
   4:	invokestatic	#117; //Method copyArrayGrow1:(Ljava/lang/Object;Ljava/lang/Class;)Ljava/lang/Object;
   7:	checkcast	#17; //class "[J"
   10:	astore_3
   11:	aload_3
   12:	aload_3
   13:	arraylength
   14:	iconst_1
   15:	isub
   16:	lload_1
   17:	lastore
   18:	aload_3
   19:	areturn
  LineNumberTable: 
   line 3344: 0
   line 3345: 11
   line 3346: 18

  LocalVariableTable: 
   Start  Length  Slot  Name   Signature
   0      20      0    array       [J
   0      20      1    element       J
   11      9      3    newArray       [J


public static java.lang.Object[] add(java.lang.Object[], int, java.lang.Object);
  Code:
   Stack=4, Locals=4, Args_size=3
   0:	aconst_null
   1:	astore_3
   2:	aload_0
   3:	ifnull	17
   6:	aload_0
   7:	invokevirtual	#123; //Method java/lang/Object.getClass:()Ljava/lang/Class;
   10:	invokevirtual	#124; //Method java/lang/Class.getComponentType:()Ljava/lang/Class;
   13:	astore_3
   14:	goto	38
   17:	aload_2
   18:	ifnull	29
   21:	aload_2
   22:	invokevirtual	#123; //Method java/lang/Object.getClass:()Ljava/lang/Class;
   25:	astore_3
   26:	goto	38
   29:	iconst_1
   30:	anewarray	#33; //class java/lang/Object
   33:	dup
   34:	iconst_0
   35:	aconst_null
   36:	aastore
   37:	areturn
   38:	aload_0
   39:	iload_1
   40:	aload_2
   41:	aload_3
   42:	invokestatic	#95; //Method add:(Ljava/lang/Object;ILjava/lang/Object;Ljava/lang/Class;)Ljava/lang/Object;
   45:	checkcast	#18; //class "[Ljava/lang/Object;"
   48:	areturn
  LineNumberTable: 
   line 3425: 0
   line 3426: 2
   line 3427: 6
   line 3426: 14
   line 3429: 17
   line 3430: 21
   line 3429: 26
   line 3432: 29
   line 3434: 38

  LocalVariableTable: 
   Start  Length  Slot  Name   Signature
   0      49      0    array       [Ljava/lang/Object;
   0      49      1    index       I
   0      49      2    element       Ljava/lang/Object;
   2      47      3    clss       Ljava/lang/Class;


public static java.lang.Object[] add(java.lang.Object[], java.lang.Object);
  Code:
   Stack=3, Locals=4, Args_size=2
   0:	aload_0
   1:	ifnull	11
   4:	aload_0
   5:	invokevirtual	#123; //Method java/lang/Object.getClass:()Ljava/lang/Class;
   8:	goto	43
   11:	aload_1
   12:	ifnull	22
   15:	aload_1
   16:	invokevirtual	#123; //Method java/lang/Object.getClass:()Ljava/lang/Class;
   19:	goto	43
   22:	getstatic	#106; //Field class$java$lang$Object:Ljava/lang/Class;
   25:	ifnull	34
   28:	getstatic	#106; //Field class$java$lang$Object:Ljava/lang/Class;
   31:	goto	43
   34:	ldc	#10; //String java.lang.Object
   36:	invokestatic	#105; //Method class$:(Ljava/lang/String;)Ljava/lang/Class;
   39:	dup
   40:	putstatic	#106; //Field class$java$lang$Object:Ljava/lang/Class;
   43:	astore_2
   44:	aload_0
   45:	aload_2
   46:	invokestatic	#117; //Method copyArrayGrow1:(Ljava/lang/Object;Ljava/lang/Class;)Ljava/lang/Object;
   49:	checkcast	#18; //class "[Ljava/lang/Object;"
   52:	astore_3
   53:	aload_3
   54:	aload_3
   55:	arraylength
   56:	iconst_1
   57:	isub
   58:	aload_1
   59:	aastore
   60:	aload_3
   61:	areturn
  LineNumberTable: 
   line 3154: 0
   line 3155: 44
   line 3156: 53
   line 3157: 60

  LocalVariableTable: 
   Start  Length  Slot  Name   Signature
   0      62      0    array       [Ljava/lang/Object;
   0      62      1    element       Ljava/lang/Object;
   44      18      2    type       Ljava/lang/Class;
   53      9      3    newArray       [Ljava/lang/Object;


public static short[] add(short[], int, short);
  Code:
   Stack=5, Locals=3, Args_size=3
   0:	aload_0
   1:	iload_1
   2:	new	#34; //class java/lang/Short
   5:	dup
   6:	iload_2
   7:	invokespecial	#63; //Method java/lang/Short."<init>":(S)V
   10:	getstatic	#94; //Field java/lang/Short.TYPE:Ljava/lang/Class;
   13:	invokestatic	#95; //Method add:(Ljava/lang/Object;ILjava/lang/Object;Ljava/lang/Class;)Ljava/lang/Object;
   16:	checkcast	#19; //class "[S"
   19:	areturn
  LineNumberTable: 
   line 3559: 0

  LocalVariableTable: 
   Start  Length  Slot  Name   Signature
   0      20      0    array       [S
   0      20      1    index       I
   0      20      2    element       S


public static short[] add(short[], short);
  Code:
   Stack=3, Locals=3, Args_size=2
   0:	aload_0
   1:	getstatic	#94; //Field java/lang/Short.TYPE:Ljava/lang/Class;
   4:	invokestatic	#117; //Method copyArrayGrow1:(Ljava/lang/Object;Ljava/lang/Class;)Ljava/lang/Object;
   7:	checkcast	#19; //class "[S"
   10:	astore_2
   11:	aload_2
   12:	aload_2
   13:	arraylength
   14:	iconst_1
   15:	isub
   16:	iload_1
   17:	sastore
   18:	aload_2
   19:	areturn
  LineNumberTable: 
   line 3371: 0
   line 3372: 11
   line 3373: 18

  LocalVariableTable: 
   Start  Length  Slot  Name   Signature
   0      20      0    array       [S
   0      20      1    element       S
   11      9      2    newArray       [S


public static boolean[] add(boolean[], int, boolean);
  Code:
   Stack=5, Locals=3, Args_size=3
   0:	aload_0
   1:	iload_1
   2:	new	#21; //class java/lang/Boolean
   5:	dup
   6:	iload_2
   7:	invokespecial	#64; //Method java/lang/Boolean."<init>":(Z)V
   10:	getstatic	#87; //Field java/lang/Boolean.TYPE:Ljava/lang/Class;
   13:	invokestatic	#95; //Method add:(Ljava/lang/Object;ILjava/lang/Object;Ljava/lang/Class;)Ljava/lang/Object;
   16:	checkcast	#20; //class "[Z"
   19:	areturn
  LineNumberTable: 
   line 3465: 0

  LocalVariableTable: 
   Start  Length  Slot  Name   Signature
   0      20      0    array       [Z
   0      20      1    index       I
   0      20      2    element       Z


public static boolean[] add(boolean[], boolean);
  Code:
   Stack=3, Locals=3, Args_size=2
   0:	aload_0
   1:	getstatic	#87; //Field java/lang/Boolean.TYPE:Ljava/lang/Class;
   4:	invokestatic	#117; //Method copyArrayGrow1:(Ljava/lang/Object;Ljava/lang/Class;)Ljava/lang/Object;
   7:	checkcast	#20; //class "[Z"
   10:	astore_2
   11:	aload_2
   12:	aload_2
   13:	arraylength
   14:	iconst_1
   15:	isub
   16:	iload_1
   17:	bastore
   18:	aload_2
   19:	areturn
  LineNumberTable: 
   line 3182: 0
   line 3183: 11
   line 3184: 18

  LocalVariableTable: 
   Start  Length  Slot  Name   Signature
   0      20      0    array       [Z
   0      20      1    element       Z
   11      9      2    newArray       [Z


public static byte[] addAll(byte[], byte[]);
  Code:
   Stack=5, Locals=3, Args_size=2
   0:	aload_0
   1:	ifnonnull	9
   4:	aload_1
   5:	invokestatic	#108; //Method clone:([B)[B
   8:	areturn
   9:	aload_1
   10:	ifnonnull	18
   13:	aload_0
   14:	invokestatic	#108; //Method clone:([B)[B
   17:	areturn
   18:	aload_0
   19:	arraylength
   20:	aload_1
   21:	arraylength
   22:	iadd
   23:	newarray byte
   25:	astore_2
   26:	aload_0
   27:	iconst_0
   28:	aload_2
   29:	iconst_0
   30:	aload_0
   31:	arraylength
   32:	invokestatic	#102; //Method java/lang/System.arraycopy:(Ljava/lang/Object;ILjava/lang/Object;II)V
   35:	aload_1
   36:	iconst_0
   37:	aload_2
   38:	aload_0
   39:	arraylength
   40:	aload_1
   41:	arraylength
   42:	invokestatic	#102; //Method java/lang/System.arraycopy:(Ljava/lang/Object;ILjava/lang/Object;II)V
   45:	aload_2
   46:	areturn
  LineNumberTable: 
   line 2974: 0
   line 2975: 4
   line 2976: 9
   line 2977: 13
   line 2979: 18
   line 2980: 26
   line 2981: 35
   line 2982: 45

  LocalVariableTable: 
   Start  Length  Slot  Name   Signature
   0      47      0    array1       [B
   0      47      1    array2       [B
   26      21      2    joinedArray       [B


public static char[] addAll(char[], char[]);
  Code:
   Stack=5, Locals=3, Args_size=2
   0:	aload_0
   1:	ifnonnull	9
   4:	aload_1
   5:	invokestatic	#109; //Method clone:([C)[C
   8:	areturn
   9:	aload_1
   10:	ifnonnull	18
   13:	aload_0
   14:	invokestatic	#109; //Method clone:([C)[C
   17:	areturn
   18:	aload_0
   19:	arraylength
   20:	aload_1
   21:	arraylength
   22:	iadd
   23:	newarray char
   25:	astore_2
   26:	aload_0
   27:	iconst_0
   28:	aload_2
   29:	iconst_0
   30:	aload_0
   31:	arraylength
   32:	invokestatic	#102; //Method java/lang/System.arraycopy:(Ljava/lang/Object;ILjava/lang/Object;II)V
   35:	aload_1
   36:	iconst_0
   37:	aload_2
   38:	aload_0
   39:	arraylength
   40:	aload_1
   41:	arraylength
   42:	invokestatic	#102; //Method java/lang/System.arraycopy:(Ljava/lang/Object;ILjava/lang/Object;II)V
   45:	aload_2
   46:	areturn
  LineNumberTable: 
   line 2945: 0
   line 2946: 4
   line 2947: 9
   line 2948: 13
   line 2950: 18
   line 2951: 26
   line 2952: 35
   line 2953: 45

  LocalVariableTable: 
   Start  Length  Slot  Name   Signature
   0      47      0    array1       [C
   0      47      1    array2       [C
   26      21      2    joinedArray       [C


public static double[] addAll(double[], double[]);
  Code:
   Stack=5, Locals=3, Args_size=2
   0:	aload_0
   1:	ifnonnull	9
   4:	aload_1
   5:	invokestatic	#110; //Method clone:([D)[D
   8:	areturn
   9:	aload_1
   10:	ifnonnull	18
   13:	aload_0
   14:	invokestatic	#110; //Method clone:([D)[D
   17:	areturn
   18:	aload_0
   19:	arraylength
   20:	aload_1
   21:	arraylength
   22:	iadd
   23:	newarray double
   25:	astore_2
   26:	aload_0
   27:	iconst_0
   28:	aload_2
   29:	iconst_0
   30:	aload_0
   31:	arraylength
   32:	invokestatic	#102; //Method java/lang/System.arraycopy:(Ljava/lang/Object;ILjava/lang/Object;II)V
   35:	aload_1
   36:	iconst_0
   37:	aload_2
   38:	aload_0
   39:	arraylength
   40:	aload_1
   41:	arraylength
   42:	invokestatic	#102; //Method java/lang/System.arraycopy:(Ljava/lang/Object;ILjava/lang/Object;II)V
   45:	aload_2
   46:	areturn
  LineNumberTable: 
   line 3119: 0
   line 3120: 4
   line 3121: 9
   line 3122: 13
   line 3124: 18
   line 3125: 26
   line 3126: 35
   line 3127: 45

  LocalVariableTable: 
   Start  Length  Slot  Name   Signature
   0      47      0    array1       [D
   0      47      1    array2       [D
   26      21      2    joinedArray       [D


public static float[] addAll(float[], float[]);
  Code:
   Stack=5, Locals=3, Args_size=2
   0:	aload_0
   1:	ifnonnull	9
   4:	aload_1
   5:	invokestatic	#111; //Method clone:([F)[F
   8:	areturn
   9:	aload_1
   10:	ifnonnull	18
   13:	aload_0
   14:	invokestatic	#111; //Method clone:([F)[F
   17:	areturn
   18:	aload_0
   19:	arraylength
   20:	aload_1
   21:	arraylength
   22:	iadd
   23:	newarray float
   25:	astore_2
   26:	aload_0
   27:	iconst_0
   28:	aload_2
   29:	iconst_0
   30:	aload_0
   31:	arraylength
   32:	invokestatic	#102; //Method java/lang/System.arraycopy:(Ljava/lang/Object;ILjava/lang/Object;II)V
   35:	aload_1
   36:	iconst_0
   37:	aload_2
   38:	aload_0
   39:	arraylength
   40:	aload_1
   41:	arraylength
   42:	invokestatic	#102; //Method java/lang/System.arraycopy:(Ljava/lang/Object;ILjava/lang/Object;II)V
   45:	aload_2
   46:	areturn
  LineNumberTable: 
   line 3090: 0
   line 3091: 4
   line 3092: 9
   line 3093: 13
   line 3095: 18
   line 3096: 26
   line 3097: 35
   line 3098: 45

  LocalVariableTable: 
   Start  Length  Slot  Name   Signature
   0      47      0    array1       [F
   0      47      1    array2       [F
   26      21      2    joinedArray       [F


public static int[] addAll(int[], int[]);
  Code:
   Stack=5, Locals=3, Args_size=2
   0:	aload_0
   1:	ifnonnull	9
   4:	aload_1
   5:	invokestatic	#112; //Method clone:([I)[I
   8:	areturn
   9:	aload_1
   10:	ifnonnull	18
   13:	aload_0
   14:	invokestatic	#112; //Method clone:([I)[I
   17:	areturn
   18:	aload_0
   19:	arraylength
   20:	aload_1
   21:	arraylength
   22:	iadd
   23:	newarray int
   25:	astore_2
   26:	aload_0
   27:	iconst_0
   28:	aload_2
   29:	iconst_0
   30:	aload_0
   31:	arraylength
   32:	invokestatic	#102; //Method java/lang/System.arraycopy:(Ljava/lang/Object;ILjava/lang/Object;II)V
   35:	aload_1
   36:	iconst_0
   37:	aload_2
   38:	aload_0
   39:	arraylength
   40:	aload_1
   41:	arraylength
   42:	invokestatic	#102; //Method java/lang/System.arraycopy:(Ljava/lang/Object;ILjava/lang/Object;II)V
   45:	aload_2
   46:	areturn
  LineNumberTable: 
   line 3032: 0
   line 3033: 4
   line 3034: 9
   line 3035: 13
   line 3037: 18
   line 3038: 26
   line 3039: 35
   line 3040: 45

  LocalVariableTable: 
   Start  Length  Slot  Name   Signature
   0      47      0    array1       [I
   0      47      1    array2       [I
   26      21      2    joinedArray       [I


public static long[] addAll(long[], long[]);
  Code:
   Stack=5, Locals=3, Args_size=2
   0:	aload_0
   1:	ifnonnull	9
   4:	aload_1
   5:	invokestatic	#113; //Method clone:([J)[J
   8:	areturn
   9:	aload_1
   10:	ifnonnull	18
   13:	aload_0
   14:	invokestatic	#113; //Method clone:([J)[J
   17:	areturn
   18:	aload_0
   19:	arraylength
   20:	aload_1
   21:	arraylength
   22:	iadd
   23:	newarray long
   25:	astore_2
   26:	aload_0
   27:	iconst_0
   28:	aload_2
   29:	iconst_0
   30:	aload_0
   31:	arraylength
   32:	invokestatic	#102; //Method java/lang/System.arraycopy:(Ljava/lang/Object;ILjava/lang/Object;II)V
   35:	aload_1
   36:	iconst_0
   37:	aload_2
   38:	aload_0
   39:	arraylength
   40:	aload_1
   41:	arraylength
   42:	invokestatic	#102; //Method java/lang/System.arraycopy:(Ljava/lang/Object;ILjava/lang/Object;II)V
   45:	aload_2
   46:	areturn
  LineNumberTable: 
   line 3061: 0
   line 3062: 4
   line 3063: 9
   line 3064: 13
   line 3066: 18
   line 3067: 26
   line 3068: 35
   line 3069: 45

  LocalVariableTable: 
   Start  Length  Slot  Name   Signature
   0      47      0    array1       [J
   0      47      1    array2       [J
   26      21      2    joinedArray       [J


public static java.lang.Object[] addAll(java.lang.Object[], java.lang.Object[]);
  Code:
   Stack=5, Locals=3, Args_size=2
   0:	aload_0
   1:	ifnonnull	9
   4:	aload_1
   5:	invokestatic	#114; //Method clone:([Ljava/lang/Object;)[Ljava/lang/Object;
   8:	areturn
   9:	aload_1
   10:	ifnonnull	18
   13:	aload_0
   14:	invokestatic	#114; //Method clone:([Ljava/lang/Object;)[Ljava/lang/Object;
   17:	areturn
   18:	aload_0
   19:	invokevirtual	#123; //Method java/lang/Object.getClass:()Ljava/lang/Class;
   22:	invokevirtual	#124; //Method java/lang/Class.getComponentType:()Ljava/lang/Class;
   25:	aload_0
   26:	arraylength
   27:	aload_1
   28:	arraylength
   29:	iadd
   30:	invokestatic	#166; //Method java/lang/reflect/Array.newInstance:(Ljava/lang/Class;I)Ljava/lang/Object;
   33:	checkcast	#18; //class "[Ljava/lang/Object;"
   36:	astore_2
   37:	aload_0
   38:	iconst_0
   39:	aload_2
   40:	iconst_0
   41:	aload_0
   42:	arraylength
   43:	invokestatic	#102; //Method java/lang/System.arraycopy:(Ljava/lang/Object;ILjava/lang/Object;II)V
   46:	aload_1
   47:	iconst_0
   48:	aload_2
   49:	aload_0
   50:	arraylength
   51:	aload_1
   52:	arraylength
   53:	invokestatic	#102; //Method java/lang/System.arraycopy:(Ljava/lang/Object;ILjava/lang/Object;II)V
   56:	aload_2
   57:	areturn
  LineNumberTable: 
   line 2886: 0
   line 2887: 4
   line 2888: 9
   line 2889: 13
   line 2891: 18
   line 2892: 25
   line 2891: 30
   line 2893: 37
   line 2894: 46
   line 2895: 56

  LocalVariableTable: 
   Start  Length  Slot  Name   Signature
   0      58      0    array1       [Ljava/lang/Object;
   0      58      1    array2       [Ljava/lang/Object;
   37      21      2    joinedArray       [Ljava/lang/Object;


public static short[] addAll(short[], short[]);
  Code:
   Stack=5, Locals=3, Args_size=2
   0:	aload_0
   1:	ifnonnull	9
   4:	aload_1
   5:	invokestatic	#115; //Method clone:([S)[S
   8:	areturn
   9:	aload_1
   10:	ifnonnull	18
   13:	aload_0
   14:	invokestatic	#115; //Method clone:([S)[S
   17:	areturn
   18:	aload_0
   19:	arraylength
   20:	aload_1
   21:	arraylength
   22:	iadd
   23:	newarray short
   25:	astore_2
   26:	aload_0
   27:	iconst_0
   28:	aload_2
   29:	iconst_0
   30:	aload_0
   31:	arraylength
   32:	invokestatic	#102; //Method java/lang/System.arraycopy:(Ljava/lang/Object;ILjava/lang/Object;II)V
   35:	aload_1
   36:	iconst_0
   37:	aload_2
   38:	aload_0
   39:	arraylength
   40:	aload_1
   41:	arraylength
   42:	invokestatic	#102; //Method java/lang/System.arraycopy:(Ljava/lang/Object;ILjava/lang/Object;II)V
   45:	aload_2
   46:	areturn
  LineNumberTable: 
   line 3003: 0
   line 3004: 4
   line 3005: 9
   line 3006: 13
   line 3008: 18
   line 3009: 26
   line 3010: 35
   line 3011: 45

  LocalVariableTable: 
   Start  Length  Slot  Name   Signature
   0      47      0    array1       [S
   0      47      1    array2       [S
   26      21      2    joinedArray       [S


public static boolean[] addAll(boolean[], boolean[]);
  Code:
   Stack=5, Locals=3, Args_size=2
   0:	aload_0
   1:	ifnonnull	9
   4:	aload_1
   5:	invokestatic	#116; //Method clone:([Z)[Z
   8:	areturn
   9:	aload_1
   10:	ifnonnull	18
   13:	aload_0
   14:	invokestatic	#116; //Method clone:([Z)[Z
   17:	areturn
   18:	aload_0
   19:	arraylength
   20:	aload_1
   21:	arraylength
   22:	iadd
   23:	newarray boolean
   25:	astore_2
   26:	aload_0
   27:	iconst_0
   28:	aload_2
   29:	iconst_0
   30:	aload_0
   31:	arraylength
   32:	invokestatic	#102; //Method java/lang/System.arraycopy:(Ljava/lang/Object;ILjava/lang/Object;II)V
   35:	aload_1
   36:	iconst_0
   37:	aload_2
   38:	aload_0
   39:	arraylength
   40:	aload_1
   41:	arraylength
   42:	invokestatic	#102; //Method java/lang/System.arraycopy:(Ljava/lang/Object;ILjava/lang/Object;II)V
   45:	aload_2
   46:	areturn
  LineNumberTable: 
   line 2916: 0
   line 2917: 4
   line 2918: 9
   line 2919: 13
   line 2921: 18
   line 2922: 26
   line 2923: 35
   line 2924: 45

  LocalVariableTable: 
   Start  Length  Slot  Name   Signature
   0      47      0    array1       [Z
   0      47      1    array2       [Z
   26      21      2    joinedArray       [Z


static java.lang.Class class$(java.lang.String);
  Code:
   Stack=3, Locals=2, Args_size=1
   0:	aload_0
   1:	invokestatic	#122; //Method java/lang/Class.forName:(Ljava/lang/String;)Ljava/lang/Class;
   4:	areturn
   5:	astore_1
   6:	new	#32; //class java/lang/NoClassDefFoundError
   9:	dup
   10:	aload_1
   11:	invokevirtual	#128; //Method java/lang/Throwable.getMessage:()Ljava/lang/String;
   14:	invokespecial	#61; //Method java/lang/NoClassDefFoundError."<init>":(Ljava/lang/String;)V
   17:	athrow
  Exception table:
   from   to  target type
     0     5     5   Class java/lang/ClassNotFoundException

  LineNumberTable: 
   line 49: 0

  LocalVariableTable: 
   Start  Length  Slot  Name   Signature
   0      18      0    class$       Ljava/lang/String;
   6      12      1    forName       Ljava/lang/ClassNotFoundException;

  Synthetic: true

public static byte[] clone(byte[]);
  Code:
   Stack=1, Locals=1, Args_size=1
   0:	aload_0
   1:	ifnonnull	6
   4:	aconst_null
   5:	areturn
   6:	aload_0
   7:	invokevirtual	#107; //Method java/lang/Object.clone:()Ljava/lang/Object;
   10:	checkcast	#12; //class "[B"
   13:	areturn
  LineNumberTable: 
   line 349: 0
   line 350: 4
   line 352: 6

  LocalVariableTable: 
   Start  Length  Slot  Name   Signature
   0      14      0    array       [B


public static char[] clone(char[]);
  Code:
   Stack=1, Locals=1, Args_size=1
   0:	aload_0
   1:	ifnonnull	6
   4:	aconst_null
   5:	areturn
   6:	aload_0
   7:	invokevirtual	#107; //Method java/lang/Object.clone:()Ljava/lang/Object;
   10:	checkcast	#13; //class "[C"
   13:	areturn
  LineNumberTable: 
   line 333: 0
   line 334: 4
   line 336: 6

  LocalVariableTable: 
   Start  Length  Slot  Name   Signature
   0      14      0    array       [C


public static double[] clone(double[]);
  Code:
   Stack=1, Locals=1, Args_size=1
   0:	aload_0
   1:	ifnonnull	6
   4:	aconst_null
   5:	areturn
   6:	aload_0
   7:	invokevirtual	#107; //Method java/lang/Object.clone:()Ljava/lang/Object;
   10:	checkcast	#14; //class "[D"
   13:	areturn
  LineNumberTable: 
   line 365: 0
   line 366: 4
   line 368: 6

  LocalVariableTable: 
   Start  Length  Slot  Name   Signature
   0      14      0    array       [D


public static float[] clone(float[]);
  Code:
   Stack=1, Locals=1, Args_size=1
   0:	aload_0
   1:	ifnonnull	6
   4:	aconst_null
   5:	areturn
   6:	aload_0
   7:	invokevirtual	#107; //Method java/lang/Object.clone:()Ljava/lang/Object;
   10:	checkcast	#15; //class "[F"
   13:	areturn
  LineNumberTable: 
   line 381: 0
   line 382: 4
   line 384: 6

  LocalVariableTable: 
   Start  Length  Slot  Name   Signature
   0      14      0    array       [F


public static int[] clone(int[]);
  Code:
   Stack=1, Locals=1, Args_size=1
   0:	aload_0
   1:	ifnonnull	6
   4:	aconst_null
   5:	areturn
   6:	aload_0
   7:	invokevirtual	#107; //Method java/lang/Object.clone:()Ljava/lang/Object;
   10:	checkcast	#16; //class "[I"
   13:	areturn
  LineNumberTable: 
   line 301: 0
   line 302: 4
   line 304: 6

  LocalVariableTable: 
   Start  Length  Slot  Name   Signature
   0      14      0    array       [I


public static long[] clone(long[]);
  Code:
   Stack=1, Locals=1, Args_size=1
   0:	aload_0
   1:	ifnonnull	6
   4:	aconst_null
   5:	areturn
   6:	aload_0
   7:	invokevirtual	#107; //Method java/lang/Object.clone:()Ljava/lang/Object;
   10:	checkcast	#17; //class "[J"
   13:	areturn
  LineNumberTable: 
   line 285: 0
   line 286: 4
   line 288: 6

  LocalVariableTable: 
   Start  Length  Slot  Name   Signature
   0      14      0    array       [J


public static java.lang.Object[] clone(java.lang.Object[]);
  Code:
   Stack=1, Locals=1, Args_size=1
   0:	aload_0
   1:	ifnonnull	6
   4:	aconst_null
   5:	areturn
   6:	aload_0
   7:	invokevirtual	#107; //Method java/lang/Object.clone:()Ljava/lang/Object;
   10:	checkcast	#18; //class "[Ljava/lang/Object;"
   13:	areturn
  LineNumberTable: 
   line 269: 0
   line 270: 4
   line 272: 6

  LocalVariableTable: 
   Start  Length  Slot  Name   Signature
   0      14      0    array       [Ljava/lang/Object;


public static short[] clone(short[]);
  Code:
   Stack=1, Locals=1, Args_size=1
   0:	aload_0
   1:	ifnonnull	6
   4:	aconst_null
   5:	areturn
   6:	aload_0
   7:	invokevirtual	#107; //Method java/lang/Object.clone:()Ljava/lang/Object;
   10:	checkcast	#19; //class "[S"
   13:	areturn
  LineNumberTable: 
   line 317: 0
   line 318: 4
   line 320: 6

  LocalVariableTable: 
   Start  Length  Slot  Name   Signature
   0      14      0    array       [S


public static boolean[] clone(boolean[]);
  Code:
   Stack=1, Locals=1, Args_size=1
   0:	aload_0
   1:	ifnonnull	6
   4:	aconst_null
   5:	areturn
   6:	aload_0
   7:	invokevirtual	#107; //Method java/lang/Object.clone:()Ljava/lang/Object;
   10:	checkcast	#20; //class "[Z"
   13:	areturn
  LineNumberTable: 
   line 397: 0
   line 398: 4
   line 400: 6

  LocalVariableTable: 
   Start  Length  Slot  Name   Signature
   0      14      0    array       [Z


public static boolean contains(byte[], byte);
  Code:
   Stack=2, Locals=2, Args_size=2
   0:	aload_0
   1:	iload_1
   2:	invokestatic	#131; //Method indexOf:([BB)I
   5:	iconst_m1
   6:	if_icmpne	13
   9:	iconst_0
   10:	goto	14
   13:	iconst_1
   14:	ireturn
  LineNumberTable: 
   line 1825: 0

  LocalVariableTable: 
   Start  Length  Slot  Name   Signature
   0      15      0    array       [B
   0      15      1    valueToFind       B


public static boolean contains(char[], char);
  Code:
   Stack=2, Locals=2, Args_size=2
   0:	aload_0
   1:	iload_1
   2:	invokestatic	#133; //Method indexOf:([CC)I
   5:	iconst_m1
   6:	if_icmpne	13
   9:	iconst_0
   10:	goto	14
   13:	iconst_1
   14:	ireturn
  LineNumberTable: 
   line 1722: 0

  LocalVariableTable: 
   Start  Length  Slot  Name   Signature
   0      15      0    array       [C
   0      15      1    valueToFind       C


public static boolean contains(double[], double);
  Code:
   Stack=3, Locals=3, Args_size=2
   0:	aload_0
   1:	dload_1
   2:	invokestatic	#135; //Method indexOf:([DD)I
   5:	iconst_m1
   6:	if_icmpne	13
   9:	iconst_0
   10:	goto	14
   13:	iconst_1
   14:	ireturn
  LineNumberTable: 
   line 2032: 0

  LocalVariableTable: 
   Start  Length  Slot  Name   Signature
   0      15      0    array       [D
   0      15      1    valueToFind       D


public static boolean contains(double[], double, double);
  Code:
   Stack=6, Locals=5, Args_size=3
   0:	aload_0
   1:	dload_1
   2:	iconst_0
   3:	dload_3
   4:	invokestatic	#137; //Method indexOf:([DDID)I
   7:	iconst_m1
   8:	if_icmpne	15
   11:	iconst_0
   12:	goto	16
   15:	iconst_1
   16:	ireturn
  LineNumberTable: 
   line 2049: 0

  LocalVariableTable: 
   Start  Length  Slot  Name   Signature
   0      17      0    array       [D
   0      17      1    valueToFind       D
   0      17      3    tolerance       D


public static boolean contains(float[], float);
  Code:
   Stack=2, Locals=2, Args_size=2
   0:	aload_0
   1:	fload_1
   2:	invokestatic	#138; //Method indexOf:([FF)I
   5:	iconst_m1
   6:	if_icmpne	13
   9:	iconst_0
   10:	goto	14
   13:	iconst_1
   14:	ireturn
  LineNumberTable: 
   line 2152: 0

  LocalVariableTable: 
   Start  Length  Slot  Name   Signature
   0      15      0    array       [F
   0      15      1    valueToFind       F


public static boolean contains(int[], int);
  Code:
   Stack=2, Locals=2, Args_size=2
   0:	aload_0
   1:	iload_1
   2:	invokestatic	#140; //Method indexOf:([II)I
   5:	iconst_m1
   6:	if_icmpne	13
   9:	iconst_0
   10:	goto	14
   13:	iconst_1
   14:	ireturn
  LineNumberTable: 
   line 1511: 0

  LocalVariableTable: 
   Start  Length  Slot  Name   Signature
   0      15      0    array       [I
   0      15      1    valueToFind       I


public static boolean contains(long[], long);
  Code:
   Stack=3, Locals=3, Args_size=2
   0:	aload_0
   1:	lload_1
   2:	invokestatic	#142; //Method indexOf:([JJ)I
   5:	iconst_m1
   6:	if_icmpne	13
   9:	iconst_0
   10:	goto	14
   13:	iconst_1
   14:	ireturn
  LineNumberTable: 
   line 1408: 0

  LocalVariableTable: 
   Start  Length  Slot  Name   Signature
   0      15      0    array       [J
   0      15      1    valueToFind       J


public static boolean contains(java.lang.Object[], java.lang.Object);
  Code:
   Stack=2, Locals=2, Args_size=2
   0:	aload_0
   1:	aload_1
   2:	invokestatic	#144; //Method indexOf:([Ljava/lang/Object;Ljava/lang/Object;)I
   5:	iconst_m1
   6:	if_icmpne	13
   9:	iconst_0
   10:	goto	14
   13:	iconst_1
   14:	ireturn
  LineNumberTable: 
   line 1305: 0

  LocalVariableTable: 
   Start  Length  Slot  Name   Signature
   0      15      0    array       [Ljava/lang/Object;
   0      15      1    objectToFind       Ljava/lang/Object;


public static boolean contains(short[], short);
  Code:
   Stack=2, Locals=2, Args_size=2
   0:	aload_0
   1:	iload_1
   2:	invokestatic	#146; //Method indexOf:([SS)I
   5:	iconst_m1
   6:	if_icmpne	13
   9:	iconst_0
   10:	goto	14
   13:	iconst_1
   14:	ireturn
  LineNumberTable: 
   line 1614: 0

  LocalVariableTable: 
   Start  Length  Slot  Name   Signature
   0      15      0    array       [S
   0      15      1    valueToFind       S


public static boolean contains(boolean[], boolean);
  Code:
   Stack=2, Locals=2, Args_size=2
   0:	aload_0
   1:	iload_1
   2:	invokestatic	#148; //Method indexOf:([ZZ)I
   5:	iconst_m1
   6:	if_icmpne	13
   9:	iconst_0
   10:	goto	14
   13:	iconst_1
   14:	ireturn
  LineNumberTable: 
   line 2255: 0

  LocalVariableTable: 
   Start  Length  Slot  Name   Signature
   0      15      0    array       [Z
   0      15      1    valueToFind       Z


public static int getLength(java.lang.Object);
  Code:
   Stack=1, Locals=1, Args_size=1
   0:	aload_0
   1:	ifnonnull	6
   4:	iconst_0
   5:	ireturn
   6:	aload_0
   7:	invokestatic	#126; //Method java/lang/reflect/Array.getLength:(Ljava/lang/Object;)I
   10:	ireturn
  LineNumberTable: 
   line 952: 0
   line 953: 4
   line 955: 6

  LocalVariableTable: 
   Start  Length  Slot  Name   Signature
   0      11      0    array       Ljava/lang/Object;


public static int hashCode(java.lang.Object);
  Code:
   Stack=2, Locals=1, Args_size=1
   0:	new	#45; //class org/apache/commons/lang/builder/HashCodeBuilder
   3:	dup
   4:	invokespecial	#50; //Method org/apache/commons/lang/builder/HashCodeBuilder."<init>":()V
   7:	aload_0
   8:	invokevirtual	#98; //Method org/apache/commons/lang/builder/HashCodeBuilder.append:(Ljava/lang/Object;)Lorg/apache/commons/lang/builder/HashCodeBuilder;
   11:	invokevirtual	#180; //Method org/apache/commons/lang/builder/HashCodeBuilder.toHashCode:()I
   14:	ireturn
  LineNumberTable: 
   line 183: 0

  LocalVariableTable: 
   Start  Length  Slot  Name   Signature
   0      15      0    array       Ljava/lang/Object;


public static int indexOf(byte[], byte);
  Code:
   Stack=3, Locals=2, Args_size=2
   0:	aload_0
   1:	iload_1
   2:	iconst_0
   3:	invokestatic	#132; //Method indexOf:([BBI)I
   6:	ireturn
  LineNumberTable: 
   line 1738: 0

  LocalVariableTable: 
   Start  Length  Slot  Name   Signature
   0      7      0    array       [B
   0      7      1    valueToFind       B


public static int indexOf(byte[], byte, int);
  Code:
   Stack=3, Locals=4, Args_size=3
   0:	aload_0
   1:	ifnonnull	6
   4:	iconst_m1
   5:	ireturn
   6:	iload_2
   7:	ifge	12
   10:	iconst_0
   11:	istore_2
   12:	iload_2
   13:	istore_3
   14:	goto	29
   17:	iload_1
   18:	aload_0
   19:	iload_3
   20:	baload
   21:	if_icmpne	26
   24:	iload_3
   25:	ireturn
   26:	iinc	3, 1
   29:	iload_3
   30:	aload_0
   31:	arraylength
   32:	if_icmplt	17
   35:	iconst_m1
   36:	ireturn
  LineNumberTable: 
   line 1756: 0
   line 1757: 4
   line 1759: 6
   line 1760: 10
   line 1762: 12
   line 1763: 17
   line 1764: 24
   line 1762: 26
   line 1767: 35

  LocalVariableTable: 
   Start  Length  Slot  Name   Signature
   0      37      0    array       [B
   0      37      1    valueToFind       B
   0      37      2    startIndex       I
   14      23      3    i       I


public static int indexOf(char[], char);
  Code:
   Stack=3, Locals=2, Args_size=2
   0:	aload_0
   1:	iload_1
   2:	iconst_0
   3:	invokestatic	#134; //Method indexOf:([CCI)I
   6:	ireturn
  LineNumberTable: 
   line 1631: 0

  LocalVariableTable: 
   Start  Length  Slot  Name   Signature
   0      7      0    array       [C
   0      7      1    valueToFind       C


public static int indexOf(char[], char, int);
  Code:
   Stack=3, Locals=4, Args_size=3
   0:	aload_0
   1:	ifnonnull	6
   4:	iconst_m1
   5:	ireturn
   6:	iload_2
   7:	ifge	12
   10:	iconst_0
   11:	istore_2
   12:	iload_2
   13:	istore_3
   14:	goto	29
   17:	iload_1
   18:	aload_0
   19:	iload_3
   20:	caload
   21:	if_icmpne	26
   24:	iload_3
   25:	ireturn
   26:	iinc	3, 1
   29:	iload_3
   30:	aload_0
   31:	arraylength
   32:	if_icmplt	17
   35:	iconst_m1
   36:	ireturn
  LineNumberTable: 
   line 1650: 0
   line 1651: 4
   line 1653: 6
   line 1654: 10
   line 1656: 12
   line 1657: 17
   line 1658: 24
   line 1656: 26
   line 1661: 35

  LocalVariableTable: 
   Start  Length  Slot  Name   Signature
   0      37      0    array       [C
   0      37      1    valueToFind       C
   0      37      2    startIndex       I
   14      23      3    i       I


public static int indexOf(double[], double);
  Code:
   Stack=4, Locals=3, Args_size=2
   0:	aload_0
   1:	dload_1
   2:	iconst_0
   3:	invokestatic	#136; //Method indexOf:([DDI)I
   6:	ireturn
  LineNumberTable: 
   line 1841: 0

  LocalVariableTable: 
   Start  Length  Slot  Name   Signature
   0      7      0    array       [D
   0      7      1    valueToFind       D


public static int indexOf(double[], double, double);
  Code:
   Stack=6, Locals=5, Args_size=3
   0:	aload_0
   1:	dload_1
   2:	iconst_0
   3:	dload_3
   4:	invokestatic	#137; //Method indexOf:([DDID)I
   7:	ireturn
  LineNumberTable: 
   line 1858: 0

  LocalVariableTable: 
   Start  Length  Slot  Name   Signature
   0      8      0    array       [D
   0      8      1    valueToFind       D
   0      8      3    tolerance       D


public static int indexOf(double[], double, int);
  Code:
   Stack=4, Locals=5, Args_size=3
   0:	aload_0
   1:	invokestatic	#151; //Method isEmpty:([D)Z
   4:	ifeq	9
   7:	iconst_m1
   8:	ireturn
   9:	iload_3
   10:	ifge	15
   13:	iconst_0
   14:	istore_3
   15:	iload_3
   16:	istore	4
   18:	goto	36
   21:	dload_1
   22:	aload_0
   23:	iload	4
   25:	daload
   26:	dcmpl
   27:	ifne	33
   30:	iload	4
   32:	ireturn
   33:	iinc	4, 1
   36:	iload	4
   38:	aload_0
   39:	arraylength
   40:	if_icmplt	21
   43:	iconst_m1
   44:	ireturn
  LineNumberTable: 
   line 1876: 0
   line 1877: 7
   line 1879: 9
   line 1880: 13
   line 1882: 15
   line 1883: 21
   line 1884: 30
   line 1882: 33
   line 1887: 43

  LocalVariableTable: 
   Start  Length  Slot  Name   Signature
   0      45      0    array       [D
   0      45      1    valueToFind       D
   0      45      3    startIndex       I
   18      27      4    i       I


public static int indexOf(double[], double, int, double);
  Code:
   Stack=4, Locals=11, Args_size=4
   0:	aload_0
   1:	invokestatic	#151; //Method isEmpty:([D)Z
   4:	ifeq	9
   7:	iconst_m1
   8:	ireturn
   9:	iload_3
   10:	ifge	15
   13:	iconst_0
   14:	istore_3
   15:	dload_1
   16:	dload	4
   18:	dsub
   19:	dstore	6
   21:	dload_1
   22:	dload	4
   24:	dadd
   25:	dstore	8
   27:	iload_3
   28:	istore	10
   30:	goto	59
   33:	aload_0
   34:	iload	10
   36:	daload
   37:	dload	6
   39:	dcmpl
   40:	iflt	56
   43:	aload_0
   44:	iload	10
   46:	daload
   47:	dload	8
   49:	dcmpg
   50:	ifgt	56
   53:	iload	10
   55:	ireturn
   56:	iinc	10, 1
   59:	iload	10
   61:	aload_0
   62:	arraylength
   63:	if_icmplt	33
   66:	iconst_m1
   67:	ireturn
  LineNumberTable: 
   line 1908: 0
   line 1909: 7
   line 1911: 9
   line 1912: 13
   line 1914: 15
   line 1915: 21
   line 1916: 27
   line 1917: 33
   line 1918: 53
   line 1916: 56
   line 1921: 66

  LocalVariableTable: 
   Start  Length  Slot  Name   Signature
   0      68      0    array       [D
   0      68      1    valueToFind       D
   0      68      3    startIndex       I
   0      68      4    tolerance       D
   21      47      6    min       D
   27      41      8    max       D
   30      38      10    i       I


public static int indexOf(float[], float);
  Code:
   Stack=3, Locals=2, Args_size=2
   0:	aload_0
   1:	fload_1
   2:	iconst_0
   3:	invokestatic	#139; //Method indexOf:([FFI)I
   6:	ireturn
  LineNumberTable: 
   line 2065: 0

  LocalVariableTable: 
   Start  Length  Slot  Name   Signature
   0      7      0    array       [F
   0      7      1    valueToFind       F


public static int indexOf(float[], float, int);
  Code:
   Stack=3, Locals=4, Args_size=3
   0:	aload_0
   1:	invokestatic	#152; //Method isEmpty:([F)Z
   4:	ifeq	9
   7:	iconst_m1
   8:	ireturn
   9:	iload_2
   10:	ifge	15
   13:	iconst_0
   14:	istore_2
   15:	iload_2
   16:	istore_3
   17:	goto	33
   20:	fload_1
   21:	aload_0
   22:	iload_3
   23:	faload
   24:	fcmpl
   25:	ifne	30
   28:	iload_3
   29:	ireturn
   30:	iinc	3, 1
   33:	iload_3
   34:	aload_0
   35:	arraylength
   36:	if_icmplt	20
   39:	iconst_m1
   40:	ireturn
  LineNumberTable: 
   line 2083: 0
   line 2084: 7
   line 2086: 9
   line 2087: 13
   line 2089: 15
   line 2090: 20
   line 2091: 28
   line 2089: 30
   line 2094: 39

  LocalVariableTable: 
   Start  Length  Slot  Name   Signature
   0      41      0    array       [F
   0      41      1    valueToFind       F
   0      41      2    startIndex       I
   17      24      3    i       I


public static int indexOf(int[], int);
  Code:
   Stack=3, Locals=2, Args_size=2
   0:	aload_0
   1:	iload_1
   2:	iconst_0
   3:	invokestatic	#141; //Method indexOf:([III)I
   6:	ireturn
  LineNumberTable: 
   line 1424: 0

  LocalVariableTable: 
   Start  Length  Slot  Name   Signature
   0      7      0    array       [I
   0      7      1    valueToFind       I


public static int indexOf(int[], int, int);
  Code:
   Stack=3, Locals=4, Args_size=3
   0:	aload_0
   1:	ifnonnull	6
   4:	iconst_m1
   5:	ireturn
   6:	iload_2
   7:	ifge	12
   10:	iconst_0
   11:	istore_2
   12:	iload_2
   13:	istore_3
   14:	goto	29
   17:	iload_1
   18:	aload_0
   19:	iload_3
   20:	iaload
   21:	if_icmpne	26
   24:	iload_3
   25:	ireturn
   26:	iinc	3, 1
   29:	iload_3
   30:	aload_0
   31:	arraylength
   32:	if_icmplt	17
   35:	iconst_m1
   36:	ireturn
  LineNumberTable: 
   line 1442: 0
   line 1443: 4
   line 1445: 6
   line 1446: 10
   line 1448: 12
   line 1449: 17
   line 1450: 24
   line 1448: 26
   line 1453: 35

  LocalVariableTable: 
   Start  Length  Slot  Name   Signature
   0      37      0    array       [I
   0      37      1    valueToFind       I
   0      37      2    startIndex       I
   14      23      3    i       I


public static int indexOf(long[], long);
  Code:
   Stack=4, Locals=3, Args_size=2
   0:	aload_0
   1:	lload_1
   2:	iconst_0
   3:	invokestatic	#143; //Method indexOf:([JJI)I
   6:	ireturn
  LineNumberTable: 
   line 1321: 0

  LocalVariableTable: 
   Start  Length  Slot  Name   Signature
   0      7      0    array       [J
   0      7      1    valueToFind       J


public static int indexOf(long[], long, int);
  Code:
   Stack=4, Locals=5, Args_size=3
   0:	aload_0
   1:	ifnonnull	6
   4:	iconst_m1
   5:	ireturn
   6:	iload_3
   7:	ifge	12
   10:	iconst_0
   11:	istore_3
   12:	iload_3
   13:	istore	4
   15:	goto	33
   18:	lload_1
   19:	aload_0
   20:	iload	4
   22:	laload
   23:	lcmp
   24:	ifne	30
   27:	iload	4
   29:	ireturn
   30:	iinc	4, 1
   33:	iload	4
   35:	aload_0
   36:	arraylength
   37:	if_icmplt	18
   40:	iconst_m1
   41:	ireturn
  LineNumberTable: 
   line 1339: 0
   line 1340: 4
   line 1342: 6
   line 1343: 10
   line 1345: 12
   line 1346: 18
   line 1347: 27
   line 1345: 30
   line 1350: 40

  LocalVariableTable: 
   Start  Length  Slot  Name   Signature
   0      42      0    array       [J
   0      42      1    valueToFind       J
   0      42      3    startIndex       I
   15      27      4    i       I


public static int indexOf(java.lang.Object[], java.lang.Object);
  Code:
   Stack=3, Locals=2, Args_size=2
   0:	aload_0
   1:	aload_1
   2:	iconst_0
   3:	invokestatic	#145; //Method indexOf:([Ljava/lang/Object;Ljava/lang/Object;I)I
   6:	ireturn
  LineNumberTable: 
   line 1202: 0

  LocalVariableTable: 
   Start  Length  Slot  Name   Signature
   0      7      0    array       [Ljava/lang/Object;
   0      7      1    objectToFind       Ljava/lang/Object;


public static int indexOf(java.lang.Object[], java.lang.Object, int);
  Code:
   Stack=3, Locals=4, Args_size=3
   0:	aload_0
   1:	ifnonnull	6
   4:	iconst_m1
   5:	ireturn
   6:	iload_2
   7:	ifge	12
   10:	iconst_0
   11:	istore_2
   12:	aload_1
   13:	ifnonnull	41
   16:	iload_2
   17:	istore_3
   18:	goto	32
   21:	aload_0
   22:	iload_3
   23:	aaload
   24:	ifnonnull	29
   27:	iload_3
   28:	ireturn
   29:	iinc	3, 1
   32:	iload_3
   33:	aload_0
   34:	arraylength
   35:	if_icmplt	21
   38:	goto	67
   41:	iload_2
   42:	istore_3
   43:	goto	61
   46:	aload_1
   47:	aload_0
   48:	iload_3
   49:	aaload
   50:	invokevirtual	#119; //Method java/lang/Object.equals:(Ljava/lang/Object;)Z
   53:	ifeq	58
   56:	iload_3
   57:	ireturn
   58:	iinc	3, 1
   61:	iload_3
   62:	aload_0
   63:	arraylength
   64:	if_icmplt	46
   67:	iconst_m1
   68:	ireturn
  LineNumberTable: 
   line 1220: 0
   line 1221: 4
   line 1223: 6
   line 1224: 10
   line 1226: 12
   line 1227: 16
   line 1228: 21
   line 1229: 27
   line 1227: 29
   line 1226: 38
   line 1233: 41
   line 1234: 46
   line 1235: 56
   line 1233: 58
   line 1239: 67

  LocalVariableTable: 
   Start  Length  Slot  Name   Signature
   0      69      0    array       [Ljava/lang/Object;
   0      69      1    objectToFind       Ljava/lang/Object;
   0      69      2    startIndex       I
   18      23      3    i       I
   43      24      3    i       I


public static int indexOf(short[], short);
  Code:
   Stack=3, Locals=2, Args_size=2
   0:	aload_0
   1:	iload_1
   2:	iconst_0
   3:	invokestatic	#147; //Method indexOf:([SSI)I
   6:	ireturn
  LineNumberTable: 
   line 1527: 0

  LocalVariableTable: 
   Start  Length  Slot  Name   Signature
   0      7      0    array       [S
   0      7      1    valueToFind       S


public static int indexOf(short[], short, int);
  Code:
   Stack=3, Locals=4, Args_size=3
   0:	aload_0
   1:	ifnonnull	6
   4:	iconst_m1
   5:	ireturn
   6:	iload_2
   7:	ifge	12
   10:	iconst_0
   11:	istore_2
   12:	iload_2
   13:	istore_3
   14:	goto	29
   17:	iload_1
   18:	aload_0
   19:	iload_3
   20:	saload
   21:	if_icmpne	26
   24:	iload_3
   25:	ireturn
   26:	iinc	3, 1
   29:	iload_3
   30:	aload_0
   31:	arraylength
   32:	if_icmplt	17
   35:	iconst_m1
   36:	ireturn
  LineNumberTable: 
   line 1545: 0
   line 1546: 4
   line 1548: 6
   line 1549: 10
   line 1551: 12
   line 1552: 17
   line 1553: 24
   line 1551: 26
   line 1556: 35

  LocalVariableTable: 
   Start  Length  Slot  Name   Signature
   0      37      0    array       [S
   0      37      1    valueToFind       S
   0      37      2    startIndex       I
   14      23      3    i       I


public static int indexOf(boolean[], boolean);
  Code:
   Stack=3, Locals=2, Args_size=2
   0:	aload_0
   1:	iload_1
   2:	iconst_0
   3:	invokestatic	#149; //Method indexOf:([ZZI)I
   6:	ireturn
  LineNumberTable: 
   line 2168: 0

  LocalVariableTable: 
   Start  Length  Slot  Name   Signature
   0      7      0    array       [Z
   0      7      1    valueToFind       Z


public static int indexOf(boolean[], boolean, int);
  Code:
   Stack=3, Locals=4, Args_size=3
   0:	aload_0
   1:	invokestatic	#153; //Method isEmpty:([Z)Z
   4:	ifeq	9
   7:	iconst_m1
   8:	ireturn
   9:	iload_2
   10:	ifge	15
   13:	iconst_0
   14:	istore_2
   15:	iload_2
   16:	istore_3
   17:	goto	32
   20:	iload_1
   21:	aload_0
   22:	iload_3
   23:	baload
   24:	if_icmpne	29
   27:	iload_3
   28:	ireturn
   29:	iinc	3, 1
   32:	iload_3
   33:	aload_0
   34:	arraylength
   35:	if_icmplt	20
   38:	iconst_m1
   39:	ireturn
  LineNumberTable: 
   line 2186: 0
   line 2187: 7
   line 2189: 9
   line 2190: 13
   line 2192: 15
   line 2193: 20
   line 2194: 27
   line 2192: 29
   line 2197: 38

  LocalVariableTable: 
   Start  Length  Slot  Name   Signature
   0      40      0    array       [Z
   0      40      1    valueToFind       Z
   0      40      2    startIndex       I
   17      23      3    i       I


public static boolean isEmpty(byte[]);
  Code:
   Stack=1, Locals=1, Args_size=1
   0:	aload_0
   1:	ifnull	9
   4:	aload_0
   5:	arraylength
   6:	ifne	11
   9:	iconst_1
   10:	ireturn
   11:	iconst_0
   12:	ireturn
  LineNumberTable: 
   line 2816: 0
   line 2817: 9
   line 2819: 11

  LocalVariableTable: 
   Start  Length  Slot  Name   Signature
   0      13      0    array       [B


public static boolean isEmpty(char[]);
  Code:
   Stack=1, Locals=1, Args_size=1
   0:	aload_0
   1:	ifnull	9
   4:	aload_0
   5:	arraylength
   6:	ifne	11
   9:	iconst_1
   10:	ireturn
   11:	iconst_0
   12:	ireturn
  LineNumberTable: 
   line 2802: 0
   line 2803: 9
   line 2805: 11

  LocalVariableTable: 
   Start  Length  Slot  Name   Signature
   0      13      0    array       [C


public static boolean isEmpty(double[]);
  Code:
   Stack=1, Locals=1, Args_size=1
   0:	aload_0
   1:	ifnull	9
   4:	aload_0
   5:	arraylength
   6:	ifne	11
   9:	iconst_1
   10:	ireturn
   11:	iconst_0
   12:	ireturn
  LineNumberTable: 
   line 2830: 0
   line 2831: 9
   line 2833: 11

  LocalVariableTable: 
   Start  Length  Slot  Name   Signature
   0      13      0    array       [D


public static boolean isEmpty(float[]);
  Code:
   Stack=1, Locals=1, Args_size=1
   0:	aload_0
   1:	ifnull	9
   4:	aload_0
   5:	arraylength
   6:	ifne	11
   9:	iconst_1
   10:	ireturn
   11:	iconst_0
   12:	ireturn
  LineNumberTable: 
   line 2844: 0
   line 2845: 9
   line 2847: 11

  LocalVariableTable: 
   Start  Length  Slot  Name   Signature
   0      13      0    array       [F


public static boolean isEmpty(int[]);
  Code:
   Stack=1, Locals=1, Args_size=1
   0:	aload_0
   1:	ifnull	9
   4:	aload_0
   5:	arraylength
   6:	ifne	11
   9:	iconst_1
   10:	ireturn
   11:	iconst_0
   12:	ireturn
  LineNumberTable: 
   line 2774: 0
   line 2775: 9
   line 2777: 11

  LocalVariableTable: 
   Start  Length  Slot  Name   Signature
   0      13      0    array       [I


public static boolean isEmpty(long[]);
  Code:
   Stack=1, Locals=1, Args_size=1
   0:	aload_0
   1:	ifnull	9
   4:	aload_0
   5:	arraylength
   6:	ifne	11
   9:	iconst_1
   10:	ireturn
   11:	iconst_0
   12:	ireturn
  LineNumberTable: 
   line 2760: 0
   line 2761: 9
   line 2763: 11

  LocalVariableTable: 
   Start  Length  Slot  Name   Signature
   0      13      0    array       [J


public static boolean isEmpty(java.lang.Object[]);
  Code:
   Stack=1, Locals=1, Args_size=1
   0:	aload_0
   1:	ifnull	9
   4:	aload_0
   5:	arraylength
   6:	ifne	11
   9:	iconst_1
   10:	ireturn
   11:	iconst_0
   12:	ireturn
  LineNumberTable: 
   line 2746: 0
   line 2747: 9
   line 2749: 11

  LocalVariableTable: 
   Start  Length  Slot  Name   Signature
   0      13      0    array       [Ljava/lang/Object;


public static boolean isEmpty(short[]);
  Code:
   Stack=1, Locals=1, Args_size=1
   0:	aload_0
   1:	ifnull	9
   4:	aload_0
   5:	arraylength
   6:	ifne	11
   9:	iconst_1
   10:	ireturn
   11:	iconst_0
   12:	ireturn
  LineNumberTable: 
   line 2788: 0
   line 2789: 9
   line 2791: 11

  LocalVariableTable: 
   Start  Length  Slot  Name   Signature
   0      13      0    array       [S


public static boolean isEmpty(boolean[]);
  Code:
   Stack=1, Locals=1, Args_size=1
   0:	aload_0
   1:	ifnull	9
   4:	aload_0
   5:	arraylength
   6:	ifne	11
   9:	iconst_1
   10:	ireturn
   11:	iconst_0
   12:	ireturn
  LineNumberTable: 
   line 2858: 0
   line 2859: 9
   line 2861: 11

  LocalVariableTable: 
   Start  Length  Slot  Name   Signature
   0      13      0    array       [Z


public static boolean isEquals(java.lang.Object, java.lang.Object);
  Code:
   Stack=3, Locals=2, Args_size=2
   0:	new	#44; //class org/apache/commons/lang/builder/EqualsBuilder
   3:	dup
   4:	invokespecial	#49; //Method org/apache/commons/lang/builder/EqualsBuilder."<init>":()V
   7:	aload_0
   8:	aload_1
   9:	invokevirtual	#100; //Method org/apache/commons/lang/builder/EqualsBuilder.append:(Ljava/lang/Object;Ljava/lang/Object;)Lorg/apache/commons/lang/builder/EqualsBuilder;
   12:	invokevirtual	#154; //Method org/apache/commons/lang/builder/EqualsBuilder.isEquals:()Z
   15:	ireturn
  LineNumberTable: 
   line 197: 0

  LocalVariableTable: 
   Start  Length  Slot  Name   Signature
   0      16      0    array1       Ljava/lang/Object;
   0      16      1    array2       Ljava/lang/Object;


public static boolean isSameLength(byte[], byte[]);
  Code:
   Stack=2, Locals=2, Args_size=2
   0:	aload_0
   1:	ifnonnull	13
   4:	aload_1
   5:	ifnull	13
   8:	aload_1
   9:	arraylength
   10:	ifgt	41
   13:	aload_1
   14:	ifnonnull	26
   17:	aload_0
   18:	ifnull	26
   21:	aload_0
   22:	arraylength
   23:	ifgt	41
   26:	aload_0
   27:	ifnull	43
   30:	aload_1
   31:	ifnull	43
   34:	aload_0
   35:	arraylength
   36:	aload_1
   37:	arraylength
   38:	if_icmpeq	43
   41:	iconst_0
   42:	ireturn
   43:	iconst_1
   44:	ireturn
  LineNumberTable: 
   line 868: 0
   line 869: 13
   line 870: 26
   line 871: 41
   line 873: 43

  LocalVariableTable: 
   Start  Length  Slot  Name   Signature
   0      45      0    array1       [B
   0      45      1    array2       [B


public static boolean isSameLength(char[], char[]);
  Code:
   Stack=2, Locals=2, Args_size=2
   0:	aload_0
   1:	ifnonnull	13
   4:	aload_1
   5:	ifnull	13
   8:	aload_1
   9:	arraylength
   10:	ifgt	41
   13:	aload_1
   14:	ifnonnull	26
   17:	aload_0
   18:	ifnull	26
   21:	aload_0
   22:	arraylength
   23:	ifgt	41
   26:	aload_0
   27:	ifnull	43
   30:	aload_1
   31:	ifnull	43
   34:	aload_0
   35:	arraylength
   36:	aload_1
   37:	arraylength
   38:	if_icmpeq	43
   41:	iconst_0
   42:	ireturn
   43:	iconst_1
   44:	ireturn
  LineNumberTable: 
   line 850: 0
   line 851: 13
   line 852: 26
   line 853: 41
   line 855: 43

  LocalVariableTable: 
   Start  Length  Slot  Name   Signature
   0      45      0    array1       [C
   0      45      1    array2       [C


public static boolean isSameLength(double[], double[]);
  Code:
   Stack=2, Locals=2, Args_size=2
   0:	aload_0
   1:	ifnonnull	13
   4:	aload_1
   5:	ifnull	13
   8:	aload_1
   9:	arraylength
   10:	ifgt	41
   13:	aload_1
   14:	ifnonnull	26
   17:	aload_0
   18:	ifnull	26
   21:	aload_0
   22:	arraylength
   23:	ifgt	41
   26:	aload_0
   27:	ifnull	43
   30:	aload_1
   31:	ifnull	43
   34:	aload_0
   35:	arraylength
   36:	aload_1
   37:	arraylength
   38:	if_icmpeq	43
   41:	iconst_0
   42:	ireturn
   43:	iconst_1
   44:	ireturn
  LineNumberTable: 
   line 886: 0
   line 887: 13
   line 888: 26
   line 889: 41
   line 891: 43

  LocalVariableTable: 
   Start  Length  Slot  Name   Signature
   0      45      0    array1       [D
   0      45      1    array2       [D


public static boolean isSameLength(float[], float[]);
  Code:
   Stack=2, Locals=2, Args_size=2
   0:	aload_0
   1:	ifnonnull	13
   4:	aload_1
   5:	ifnull	13
   8:	aload_1
   9:	arraylength
   10:	ifgt	41
   13:	aload_1
   14:	ifnonnull	26
   17:	aload_0
   18:	ifnull	26
   21:	aload_0
   22:	arraylength
   23:	ifgt	41
   26:	aload_0
   27:	ifnull	43
   30:	aload_1
   31:	ifnull	43
   34:	aload_0
   35:	arraylength
   36:	aload_1
   37:	arraylength
   38:	if_icmpeq	43
   41:	iconst_0
   42:	ireturn
   43:	iconst_1
   44:	ireturn
  LineNumberTable: 
   line 904: 0
   line 905: 13
   line 906: 26
   line 907: 41
   line 909: 43

  LocalVariableTable: 
   Start  Length  Slot  Name   Signature
   0      45      0    array1       [F
   0      45      1    array2       [F


public static boolean isSameLength(int[], int[]);
  Code:
   Stack=2, Locals=2, Args_size=2
   0:	aload_0
   1:	ifnonnull	13
   4:	aload_1
   5:	ifnull	13
   8:	aload_1
   9:	arraylength
   10:	ifgt	41
   13:	aload_1
   14:	ifnonnull	26
   17:	aload_0
   18:	ifnull	26
   21:	aload_0
   22:	arraylength
   23:	ifgt	41
   26:	aload_0
   27:	ifnull	43
   30:	aload_1
   31:	ifnull	43
   34:	aload_0
   35:	arraylength
   36:	aload_1
   37:	arraylength
   38:	if_icmpeq	43
   41:	iconst_0
   42:	ireturn
   43:	iconst_1
   44:	ireturn
  LineNumberTable: 
   line 814: 0
   line 815: 13
   line 816: 26
   line 817: 41
   line 819: 43

  LocalVariableTable: 
   Start  Length  Slot  Name   Signature
   0      45      0    array1       [I
   0      45      1    array2       [I


public static boolean isSameLength(long[], long[]);
  Code:
   Stack=2, Locals=2, Args_size=2
   0:	aload_0
   1:	ifnonnull	13
   4:	aload_1
   5:	ifnull	13
   8:	aload_1
   9:	arraylength
   10:	ifgt	41
   13:	aload_1
   14:	ifnonnull	26
   17:	aload_0
   18:	ifnull	26
   21:	aload_0
   22:	arraylength
   23:	ifgt	41
   26:	aload_0
   27:	ifnull	43
   30:	aload_1
   31:	ifnull	43
   34:	aload_0
   35:	arraylength
   36:	aload_1
   37:	arraylength
   38:	if_icmpeq	43
   41:	iconst_0
   42:	ireturn
   43:	iconst_1
   44:	ireturn
  LineNumberTable: 
   line 796: 0
   line 797: 13
   line 798: 26
   line 799: 41
   line 801: 43

  LocalVariableTable: 
   Start  Length  Slot  Name   Signature
   0      45      0    array1       [J
   0      45      1    array2       [J


public static boolean isSameLength(java.lang.Object[], java.lang.Object[]);
  Code:
   Stack=2, Locals=2, Args_size=2
   0:	aload_0
   1:	ifnonnull	13
   4:	aload_1
   5:	ifnull	13
   8:	aload_1
   9:	arraylength
   10:	ifgt	41
   13:	aload_1
   14:	ifnonnull	26
   17:	aload_0
   18:	ifnull	26
   21:	aload_0
   22:	arraylength
   23:	ifgt	41
   26:	aload_0
   27:	ifnull	43
   30:	aload_1
   31:	ifnull	43
   34:	aload_0
   35:	arraylength
   36:	aload_1
   37:	arraylength
   38:	if_icmpeq	43
   41:	iconst_0
   42:	ireturn
   43:	iconst_1
   44:	ireturn
  LineNumberTable: 
   line 778: 0
   line 779: 13
   line 780: 26
   line 781: 41
   line 783: 43

  LocalVariableTable: 
   Start  Length  Slot  Name   Signature
   0      45      0    array1       [Ljava/lang/Object;
   0      45      1    array2       [Ljava/lang/Object;


public static boolean isSameLength(short[], short[]);
  Code:
   Stack=2, Locals=2, Args_size=2
   0:	aload_0
   1:	ifnonnull	13
   4:	aload_1
   5:	ifnull	13
   8:	aload_1
   9:	arraylength
   10:	ifgt	41
   13:	aload_1
   14:	ifnonnull	26
   17:	aload_0
   18:	ifnull	26
   21:	aload_0
   22:	arraylength
   23:	ifgt	41
   26:	aload_0
   27:	ifnull	43
   30:	aload_1
   31:	ifnull	43
   34:	aload_0
   35:	arraylength
   36:	aload_1
   37:	arraylength
   38:	if_icmpeq	43
   41:	iconst_0
   42:	ireturn
   43:	iconst_1
   44:	ireturn
  LineNumberTable: 
   line 832: 0
   line 833: 13
   line 834: 26
   line 835: 41
   line 837: 43

  LocalVariableTable: 
   Start  Length  Slot  Name   Signature
   0      45      0    array1       [S
   0      45      1    array2       [S


public static boolean isSameLength(boolean[], boolean[]);
  Code:
   Stack=2, Locals=2, Args_size=2
   0:	aload_0
   1:	ifnonnull	13
   4:	aload_1
   5:	ifnull	13
   8:	aload_1
   9:	arraylength
   10:	ifgt	41
   13:	aload_1
   14:	ifnonnull	26
   17:	aload_0
   18:	ifnull	26
   21:	aload_0
   22:	arraylength
   23:	ifgt	41
   26:	aload_0
   27:	ifnull	43
   30:	aload_1
   31:	ifnull	43
   34:	aload_0
   35:	arraylength
   36:	aload_1
   37:	arraylength
   38:	if_icmpeq	43
   41:	iconst_0
   42:	ireturn
   43:	iconst_1
   44:	ireturn
  LineNumberTable: 
   line 922: 0
   line 923: 13
   line 924: 26
   line 925: 41
   line 927: 43

  LocalVariableTable: 
   Start  Length  Slot  Name   Signature
   0      45      0    array1       [Z
   0      45      1    array2       [Z


public static boolean isSameType(java.lang.Object, java.lang.Object);
  Code:
   Stack=3, Locals=2, Args_size=2
   0:	aload_0
   1:	ifnull	8
   4:	aload_1
   5:	ifnonnull	18
   8:	new	#28; //class java/lang/IllegalArgumentException
   11:	dup
   12:	ldc	#9; //String The Array must not be null
   14:	invokespecial	#59; //Method java/lang/IllegalArgumentException."<init>":(Ljava/lang/String;)V
   17:	athrow
   18:	aload_0
   19:	invokevirtual	#123; //Method java/lang/Object.getClass:()Ljava/lang/Class;
   22:	invokevirtual	#129; //Method java/lang/Class.getName:()Ljava/lang/String;
   25:	aload_1
   26:	invokevirtual	#123; //Method java/lang/Object.getClass:()Ljava/lang/Class;
   29:	invokevirtual	#129; //Method java/lang/Class.getName:()Ljava/lang/String;
   32:	invokevirtual	#120; //Method java/lang/String.equals:(Ljava/lang/Object;)Z
   35:	ireturn
  LineNumberTable: 
   line 969: 0
   line 970: 8
   line 972: 18

  LocalVariableTable: 
   Start  Length  Slot  Name   Signature
   0      36      0    array1       Ljava/lang/Object;
   0      36      1    array2       Ljava/lang/Object;


public static int lastIndexOf(byte[], byte);
  Code:
   Stack=3, Locals=2, Args_size=2
   0:	aload_0
   1:	iload_1
   2:	ldc	#1; //int 2147483647
   4:	invokestatic	#155; //Method lastIndexOf:([BBI)I
   7:	ireturn
  LineNumberTable: 
   line 1781: 0

  LocalVariableTable: 
   Start  Length  Slot  Name   Signature
   0      8      0    array       [B
   0      8      1    valueToFind       B


public static int lastIndexOf(byte[], byte, int);
  Code:
   Stack=3, Locals=4, Args_size=3
   0:	aload_0
   1:	ifnonnull	6
   4:	iconst_m1
   5:	ireturn
   6:	iload_2
   7:	ifge	12
   10:	iconst_m1
   11:	ireturn
   12:	iload_2
   13:	aload_0
   14:	arraylength
   15:	if_icmplt	23
   18:	aload_0
   19:	arraylength
   20:	iconst_1
   21:	isub
   22:	istore_2
   23:	iload_2
   24:	istore_3
   25:	goto	40
   28:	iload_1
   29:	aload_0
   30:	iload_3
   31:	baload
   32:	if_icmpne	37
   35:	iload_3
   36:	ireturn
   37:	iinc	3, -1
   40:	iload_3
   41:	ifge	28
   44:	iconst_m1
   45:	ireturn
  LineNumberTable: 
   line 1799: 0
   line 1800: 4
   line 1802: 6
   line 1803: 10
   line 1804: 12
   line 1805: 18
   line 1807: 23
   line 1808: 28
   line 1809: 35
   line 1807: 37
   line 1812: 44

  LocalVariableTable: 
   Start  Length  Slot  Name   Signature
   0      46      0    array       [B
   0      46      1    valueToFind       B
   0      46      2    startIndex       I
   25      21      3    i       I


public static int lastIndexOf(char[], char);
  Code:
   Stack=3, Locals=2, Args_size=2
   0:	aload_0
   1:	iload_1
   2:	ldc	#1; //int 2147483647
   4:	invokestatic	#156; //Method lastIndexOf:([CCI)I
   7:	ireturn
  LineNumberTable: 
   line 1676: 0

  LocalVariableTable: 
   Start  Length  Slot  Name   Signature
   0      8      0    array       [C
   0      8      1    valueToFind       C


public static int lastIndexOf(char[], char, int);
  Code:
   Stack=3, Locals=4, Args_size=3
   0:	aload_0
   1:	ifnonnull	6
   4:	iconst_m1
   5:	ireturn
   6:	iload_2
   7:	ifge	12
   10:	iconst_m1
   11:	ireturn
   12:	iload_2
   13:	aload_0
   14:	arraylength
   15:	if_icmplt	23
   18:	aload_0
   19:	arraylength
   20:	iconst_1
   21:	isub
   22:	istore_2
   23:	iload_2
   24:	istore_3
   25:	goto	40
   28:	iload_1
   29:	aload_0
   30:	iload_3
   31:	caload
   32:	if_icmpne	37
   35:	iload_3
   36:	ireturn
   37:	iinc	3, -1
   40:	iload_3
   41:	ifge	28
   44:	iconst_m1
   45:	ireturn
  LineNumberTable: 
   line 1695: 0
   line 1696: 4
   line 1698: 6
   line 1699: 10
   line 1700: 12
   line 1701: 18
   line 1703: 23
   line 1704: 28
   line 1705: 35
   line 1703: 37
   line 1708: 44

  LocalVariableTable: 
   Start  Length  Slot  Name   Signature
   0      46      0    array       [C
   0      46      1    valueToFind       C
   0      46      2    startIndex       I
   25      21      3    i       I


public static int lastIndexOf(double[], double);
  Code:
   Stack=4, Locals=3, Args_size=2
   0:	aload_0
   1:	dload_1
   2:	ldc	#1; //int 2147483647
   4:	invokestatic	#157; //Method lastIndexOf:([DDI)I
   7:	ireturn
  LineNumberTable: 
   line 1935: 0

  LocalVariableTable: 
   Start  Length  Slot  Name   Signature
   0      8      0    array       [D
   0      8      1    valueToFind       D


public static int lastIndexOf(double[], double, double);
  Code:
   Stack=6, Locals=5, Args_size=3
   0:	aload_0
   1:	dload_1
   2:	ldc	#1; //int 2147483647
   4:	dload_3
   5:	invokestatic	#158; //Method lastIndexOf:([DDID)I
   8:	ireturn
  LineNumberTable: 
   line 1952: 0

  LocalVariableTable: 
   Start  Length  Slot  Name   Signature
   0      9      0    array       [D
   0      9      1    valueToFind       D
   0      9      3    tolerance       D


public static int lastIndexOf(double[], double, int);
  Code:
   Stack=4, Locals=5, Args_size=3
   0:	aload_0
   1:	invokestatic	#151; //Method isEmpty:([D)Z
   4:	ifeq	9
   7:	iconst_m1
   8:	ireturn
   9:	iload_3
   10:	ifge	15
   13:	iconst_m1
   14:	ireturn
   15:	iload_3
   16:	aload_0
   17:	arraylength
   18:	if_icmplt	26
   21:	aload_0
   22:	arraylength
   23:	iconst_1
   24:	isub
   25:	istore_3
   26:	iload_3
   27:	istore	4
   29:	goto	47
   32:	dload_1
   33:	aload_0
   34:	iload	4
   36:	daload
   37:	dcmpl
   38:	ifne	44
   41:	iload	4
   43:	ireturn
   44:	iinc	4, -1
   47:	iload	4
   49:	ifge	32
   52:	iconst_m1
   53:	ireturn
  LineNumberTable: 
   line 1970: 0
   line 1971: 7
   line 1973: 9
   line 1974: 13
   line 1975: 15
   line 1976: 21
   line 1978: 26
   line 1979: 32
   line 1980: 41
   line 1978: 44
   line 1983: 52

  LocalVariableTable: 
   Start  Length  Slot  Name   Signature
   0      54      0    array       [D
   0      54      1    valueToFind       D
   0      54      3    startIndex       I
   29      25      4    i       I


public static int lastIndexOf(double[], double, int, double);
  Code:
   Stack=4, Locals=11, Args_size=4
   0:	aload_0
   1:	invokestatic	#151; //Method isEmpty:([D)Z
   4:	ifeq	9
   7:	iconst_m1
   8:	ireturn
   9:	iload_3
   10:	ifge	15
   13:	iconst_m1
   14:	ireturn
   15:	iload_3
   16:	aload_0
   17:	arraylength
   18:	if_icmplt	26
   21:	aload_0
   22:	arraylength
   23:	iconst_1
   24:	isub
   25:	istore_3
   26:	dload_1
   27:	dload	4
   29:	dsub
   30:	dstore	6
   32:	dload_1
   33:	dload	4
   35:	dadd
   36:	dstore	8
   38:	iload_3
   39:	istore	10
   41:	goto	70
   44:	aload_0
   45:	iload	10
   47:	daload
   48:	dload	6
   50:	dcmpl
   51:	iflt	67
   54:	aload_0
   55:	iload	10
   57:	daload
   58:	dload	8
   60:	dcmpg
   61:	ifgt	67
   64:	iload	10
   66:	ireturn
   67:	iinc	10, -1
   70:	iload	10
   72:	ifge	44
   75:	iconst_m1
   76:	ireturn
  LineNumberTable: 
   line 2004: 0
   line 2005: 7
   line 2007: 9
   line 2008: 13
   line 2009: 15
   line 2010: 21
   line 2012: 26
   line 2013: 32
   line 2014: 38
   line 2015: 44
   line 2016: 64
   line 2014: 67
   line 2019: 75

  LocalVariableTable: 
   Start  Length  Slot  Name   Signature
   0      77      0    array       [D
   0      77      1    valueToFind       D
   0      77      3    startIndex       I
   0      77      4    tolerance       D
   32      45      6    min       D
   38      39      8    max       D
   41      36      10    i       I


public static int lastIndexOf(float[], float);
  Code:
   Stack=3, Locals=2, Args_size=2
   0:	aload_0
   1:	fload_1
   2:	ldc	#1; //int 2147483647
   4:	invokestatic	#159; //Method lastIndexOf:([FFI)I
   7:	ireturn
  LineNumberTable: 
   line 2108: 0

  LocalVariableTable: 
   Start  Length  Slot  Name   Signature
   0      8      0    array       [F
   0      8      1    valueToFind       F


public static int lastIndexOf(float[], float, int);
  Code:
   Stack=3, Locals=4, Args_size=3
   0:	aload_0
   1:	invokestatic	#152; //Method isEmpty:([F)Z
   4:	ifeq	9
   7:	iconst_m1
   8:	ireturn
   9:	iload_2
   10:	ifge	15
   13:	iconst_m1
   14:	ireturn
   15:	iload_2
   16:	aload_0
   17:	arraylength
   18:	if_icmplt	26
   21:	aload_0
   22:	arraylength
   23:	iconst_1
   24:	isub
   25:	istore_2
   26:	iload_2
   27:	istore_3
   28:	goto	44
   31:	fload_1
   32:	aload_0
   33:	iload_3
   34:	faload
   35:	fcmpl
   36:	ifne	41
   39:	iload_3
   40:	ireturn
   41:	iinc	3, -1
   44:	iload_3
   45:	ifge	31
   48:	iconst_m1
   49:	ireturn
  LineNumberTable: 
   line 2126: 0
   line 2127: 7
   line 2129: 9
   line 2130: 13
   line 2131: 15
   line 2132: 21
   line 2134: 26
   line 2135: 31
   line 2136: 39
   line 2134: 41
   line 2139: 48

  LocalVariableTable: 
   Start  Length  Slot  Name   Signature
   0      50      0    array       [F
   0      50      1    valueToFind       F
   0      50      2    startIndex       I
   28      22      3    i       I


public static int lastIndexOf(int[], int);
  Code:
   Stack=3, Locals=2, Args_size=2
   0:	aload_0
   1:	iload_1
   2:	ldc	#1; //int 2147483647
   4:	invokestatic	#160; //Method lastIndexOf:([III)I
   7:	ireturn
  LineNumberTable: 
   line 1467: 0

  LocalVariableTable: 
   Start  Length  Slot  Name   Signature
   0      8      0    array       [I
   0      8      1    valueToFind       I


public static int lastIndexOf(int[], int, int);
  Code:
   Stack=3, Locals=4, Args_size=3
   0:	aload_0
   1:	ifnonnull	6
   4:	iconst_m1
   5:	ireturn
   6:	iload_2
   7:	ifge	12
   10:	iconst_m1
   11:	ireturn
   12:	iload_2
   13:	aload_0
   14:	arraylength
   15:	if_icmplt	23
   18:	aload_0
   19:	arraylength
   20:	iconst_1
   21:	isub
   22:	istore_2
   23:	iload_2
   24:	istore_3
   25:	goto	40
   28:	iload_1
   29:	aload_0
   30:	iload_3
   31:	iaload
   32:	if_icmpne	37
   35:	iload_3
   36:	ireturn
   37:	iinc	3, -1
   40:	iload_3
   41:	ifge	28
   44:	iconst_m1
   45:	ireturn
  LineNumberTable: 
   line 1485: 0
   line 1486: 4
   line 1488: 6
   line 1489: 10
   line 1490: 12
   line 1491: 18
   line 1493: 23
   line 1494: 28
   line 1495: 35
   line 1493: 37
   line 1498: 44

  LocalVariableTable: 
   Start  Length  Slot  Name   Signature
   0      46      0    array       [I
   0      46      1    valueToFind       I
   0      46      2    startIndex       I
   25      21      3    i       I


public static int lastIndexOf(long[], long);
  Code:
   Stack=4, Locals=3, Args_size=2
   0:	aload_0
   1:	lload_1
   2:	ldc	#1; //int 2147483647
   4:	invokestatic	#161; //Method lastIndexOf:([JJI)I
   7:	ireturn
  LineNumberTable: 
   line 1364: 0

  LocalVariableTable: 
   Start  Length  Slot  Name   Signature
   0      8      0    array       [J
   0      8      1    valueToFind       J


public static int lastIndexOf(long[], long, int);
  Code:
   Stack=4, Locals=5, Args_size=3
   0:	aload_0
   1:	ifnonnull	6
   4:	iconst_m1
   5:	ireturn
   6:	iload_3
   7:	ifge	12
   10:	iconst_m1
   11:	ireturn
   12:	iload_3
   13:	aload_0
   14:	arraylength
   15:	if_icmplt	23
   18:	aload_0
   19:	arraylength
   20:	iconst_1
   21:	isub
   22:	istore_3
   23:	iload_3
   24:	istore	4
   26:	goto	44
   29:	lload_1
   30:	aload_0
   31:	iload	4
   33:	laload
   34:	lcmp
   35:	ifne	41
   38:	iload	4
   40:	ireturn
   41:	iinc	4, -1
   44:	iload	4
   46:	ifge	29
   49:	iconst_m1
   50:	ireturn
  LineNumberTable: 
   line 1382: 0
   line 1383: 4
   line 1385: 6
   line 1386: 10
   line 1387: 12
   line 1388: 18
   line 1390: 23
   line 1391: 29
   line 1392: 38
   line 1390: 41
   line 1395: 49

  LocalVariableTable: 
   Start  Length  Slot  Name   Signature
   0      51      0    array       [J
   0      51      1    valueToFind       J
   0      51      3    startIndex       I
   26      25      4    i       I


public static int lastIndexOf(java.lang.Object[], java.lang.Object);
  Code:
   Stack=3, Locals=2, Args_size=2
   0:	aload_0
   1:	aload_1
   2:	ldc	#1; //int 2147483647
   4:	invokestatic	#162; //Method lastIndexOf:([Ljava/lang/Object;Ljava/lang/Object;I)I
   7:	ireturn
  LineNumberTable: 
   line 1253: 0

  LocalVariableTable: 
   Start  Length  Slot  Name   Signature
   0      8      0    array       [Ljava/lang/Object;
   0      8      1    objectToFind       Ljava/lang/Object;


public static int lastIndexOf(java.lang.Object[], java.lang.Object, int);
  Code:
   Stack=3, Locals=4, Args_size=3
   0:	aload_0
   1:	ifnonnull	6
   4:	iconst_m1
   5:	ireturn
   6:	iload_2
   7:	ifge	12
   10:	iconst_m1
   11:	ireturn
   12:	iload_2
   13:	aload_0
   14:	arraylength
   15:	if_icmplt	23
   18:	aload_0
   19:	arraylength
   20:	iconst_1
   21:	isub
   22:	istore_2
   23:	aload_1
   24:	ifnonnull	50
   27:	iload_2
   28:	istore_3
   29:	goto	43
   32:	aload_0
   33:	iload_3
   34:	aaload
   35:	ifnonnull	40
   38:	iload_3
   39:	ireturn
   40:	iinc	3, -1
   43:	iload_3
   44:	ifge	32
   47:	goto	74
   50:	iload_2
   51:	istore_3
   52:	goto	70
   55:	aload_1
   56:	aload_0
   57:	iload_3
   58:	aaload
   59:	invokevirtual	#119; //Method java/lang/Object.equals:(Ljava/lang/Object;)Z
   62:	ifeq	67
   65:	iload_3
   66:	ireturn
   67:	iinc	3, -1
   70:	iload_3
   71:	ifge	55
   74:	iconst_m1
   75:	ireturn
  LineNumberTable: 
   line 1271: 0
   line 1272: 4
   line 1274: 6
   line 1275: 10
   line 1276: 12
   line 1277: 18
   line 1279: 23
   line 1280: 27
   line 1281: 32
   line 1282: 38
   line 1280: 40
   line 1279: 47
   line 1286: 50
   line 1287: 55
   line 1288: 65
   line 1286: 67
   line 1292: 74

  LocalVariableTable: 
   Start  Length  Slot  Name   Signature
   0      76      0    array       [Ljava/lang/Object;
   0      76      1    objectToFind       Ljava/lang/Object;
   0      76      2    startIndex       I
   29      21      3    i       I
   52      22      3    i       I


public static int lastIndexOf(short[], short);
  Code:
   Stack=3, Locals=2, Args_size=2
   0:	aload_0
   1:	iload_1
   2:	ldc	#1; //int 2147483647
   4:	invokestatic	#163; //Method lastIndexOf:([SSI)I
   7:	ireturn
  LineNumberTable: 
   line 1570: 0

  LocalVariableTable: 
   Start  Length  Slot  Name   Signature
   0      8      0    array       [S
   0      8      1    valueToFind       S


public static int lastIndexOf(short[], short, int);
  Code:
   Stack=3, Locals=4, Args_size=3
   0:	aload_0
   1:	ifnonnull	6
   4:	iconst_m1
   5:	ireturn
   6:	iload_2
   7:	ifge	12
   10:	iconst_m1
   11:	ireturn
   12:	iload_2
   13:	aload_0
   14:	arraylength
   15:	if_icmplt	23
   18:	aload_0
   19:	arraylength
   20:	iconst_1
   21:	isub
   22:	istore_2
   23:	iload_2
   24:	istore_3
   25:	goto	40
   28:	iload_1
   29:	aload_0
   30:	iload_3
   31:	saload
   32:	if_icmpne	37
   35:	iload_3
   36:	ireturn
   37:	iinc	3, -1
   40:	iload_3
   41:	ifge	28
   44:	iconst_m1
   45:	ireturn
  LineNumberTable: 
   line 1588: 0
   line 1589: 4
   line 1591: 6
   line 1592: 10
   line 1593: 12
   line 1594: 18
   line 1596: 23
   line 1597: 28
   line 1598: 35
   line 1596: 37
   line 1601: 44

  LocalVariableTable: 
   Start  Length  Slot  Name   Signature
   0      46      0    array       [S
   0      46      1    valueToFind       S
   0      46      2    startIndex       I
   25      21      3    i       I


public static int lastIndexOf(boolean[], boolean);
  Code:
   Stack=3, Locals=2, Args_size=2
   0:	aload_0
   1:	iload_1
   2:	ldc	#1; //int 2147483647
   4:	invokestatic	#164; //Method lastIndexOf:([ZZI)I
   7:	ireturn
  LineNumberTable: 
   line 2211: 0

  LocalVariableTable: 
   Start  Length  Slot  Name   Signature
   0      8      0    array       [Z
   0      8      1    valueToFind       Z


public static int lastIndexOf(boolean[], boolean, int);
  Code:
   Stack=3, Locals=4, Args_size=3
   0:	aload_0
   1:	invokestatic	#153; //Method isEmpty:([Z)Z
   4:	ifeq	9
   7:	iconst_m1
   8:	ireturn
   9:	iload_2
   10:	ifge	15
   13:	iconst_m1
   14:	ireturn
   15:	iload_2
   16:	aload_0
   17:	arraylength
   18:	if_icmplt	26
   21:	aload_0
   22:	arraylength
   23:	iconst_1
   24:	isub
   25:	istore_2
   26:	iload_2
   27:	istore_3
   28:	goto	43
   31:	iload_1
   32:	aload_0
   33:	iload_3
   34:	baload
   35:	if_icmpne	40
   38:	iload_3
   39:	ireturn
   40:	iinc	3, -1
   43:	iload_3
   44:	ifge	31
   47:	iconst_m1
   48:	ireturn
  LineNumberTable: 
   line 2229: 0
   line 2230: 7
   line 2232: 9
   line 2233: 13
   line 2234: 15
   line 2235: 21
   line 2237: 26
   line 2238: 31
   line 2239: 38
   line 2237: 40
   line 2242: 47

  LocalVariableTable: 
   Start  Length  Slot  Name   Signature
   0      49      0    array       [Z
   0      49      1    valueToFind       Z
   0      49      2    startIndex       I
   28      21      3    i       I


public static byte[] remove(byte[], int);
  Code:
   Stack=2, Locals=2, Args_size=2
   0:	aload_0
   1:	iload_1
   2:	invokestatic	#168; //Method remove:(Ljava/lang/Object;I)Ljava/lang/Object;
   5:	checkcast	#12; //class "[B"
   8:	areturn
  LineNumberTable: 
   line 3878: 0

  LocalVariableTable: 
   Start  Length  Slot  Name   Signature
   0      9      0    array       [B
   0      9      1    index       I


public static char[] remove(char[], int);
  Code:
   Stack=2, Locals=2, Args_size=2
   0:	aload_0
   1:	iload_1
   2:	invokestatic	#168; //Method remove:(Ljava/lang/Object;I)Ljava/lang/Object;
   5:	checkcast	#13; //class "[C"
   8:	areturn
  LineNumberTable: 
   line 3943: 0

  LocalVariableTable: 
   Start  Length  Slot  Name   Signature
   0      9      0    array       [C
   0      9      1    index       I


public static double[] remove(double[], int);
  Code:
   Stack=2, Locals=2, Args_size=2
   0:	aload_0
   1:	iload_1
   2:	invokestatic	#168; //Method remove:(Ljava/lang/Object;I)Ljava/lang/Object;
   5:	checkcast	#14; //class "[D"
   8:	areturn
  LineNumberTable: 
   line 4008: 0

  LocalVariableTable: 
   Start  Length  Slot  Name   Signature
   0      9      0    array       [D
   0      9      1    index       I


public static float[] remove(float[], int);
  Code:
   Stack=2, Locals=2, Args_size=2
   0:	aload_0
   1:	iload_1
   2:	invokestatic	#168; //Method remove:(Ljava/lang/Object;I)Ljava/lang/Object;
   5:	checkcast	#15; //class "[F"
   8:	areturn
  LineNumberTable: 
   line 4073: 0

  LocalVariableTable: 
   Start  Length  Slot  Name   Signature
   0      9      0    array       [F
   0      9      1    index       I


public static int[] remove(int[], int);
  Code:
   Stack=2, Locals=2, Args_size=2
   0:	aload_0
   1:	iload_1
   2:	invokestatic	#168; //Method remove:(Ljava/lang/Object;I)Ljava/lang/Object;
   5:	checkcast	#16; //class "[I"
   8:	areturn
  LineNumberTable: 
   line 4138: 0

  LocalVariableTable: 
   Start  Length  Slot  Name   Signature
   0      9      0    array       [I
   0      9      1    index       I


public static long[] remove(long[], int);
  Code:
   Stack=2, Locals=2, Args_size=2
   0:	aload_0
   1:	iload_1
   2:	invokestatic	#168; //Method remove:(Ljava/lang/Object;I)Ljava/lang/Object;
   5:	checkcast	#17; //class "[J"
   8:	areturn
  LineNumberTable: 
   line 4203: 0

  LocalVariableTable: 
   Start  Length  Slot  Name   Signature
   0      9      0    array       [J
   0      9      1    index       I


public static java.lang.Object[] remove(java.lang.Object[], int);
  Code:
   Stack=2, Locals=2, Args_size=2
   0:	aload_0
   1:	iload_1
   2:	invokestatic	#168; //Method remove:(Ljava/lang/Object;I)Ljava/lang/Object;
   5:	checkcast	#18; //class "[Ljava/lang/Object;"
   8:	areturn
  LineNumberTable: 
   line 3748: 0

  LocalVariableTable: 
   Start  Length  Slot  Name   Signature
   0      9      0    array       [Ljava/lang/Object;
   0      9      1    index       I


public static short[] remove(short[], int);
  Code:
   Stack=2, Locals=2, Args_size=2
   0:	aload_0
   1:	iload_1
   2:	invokestatic	#168; //Method remove:(Ljava/lang/Object;I)Ljava/lang/Object;
   5:	checkcast	#19; //class "[S"
   8:	areturn
  LineNumberTable: 
   line 4268: 0

  LocalVariableTable: 
   Start  Length  Slot  Name   Signature
   0      9      0    array       [S
   0      9      1    index       I


public static boolean[] remove(boolean[], int);
  Code:
   Stack=2, Locals=2, Args_size=2
   0:	aload_0
   1:	iload_1
   2:	invokestatic	#168; //Method remove:(Ljava/lang/Object;I)Ljava/lang/Object;
   5:	checkcast	#20; //class "[Z"
   8:	areturn
  LineNumberTable: 
   line 3813: 0

  LocalVariableTable: 
   Start  Length  Slot  Name   Signature
   0      9      0    array       [Z
   0      9      1    index       I


public static byte[] removeElement(byte[], byte);
  Code:
   Stack=2, Locals=3, Args_size=2
   0:	aload_0
   1:	iload_1
   2:	invokestatic	#131; //Method indexOf:([BB)I
   5:	istore_2
   6:	iload_2
   7:	iconst_m1
   8:	if_icmpne	16
   11:	aload_0
   12:	invokestatic	#108; //Method clone:([B)[B
   15:	areturn
   16:	aload_0
   17:	iload_2
   18:	invokestatic	#169; //Method remove:([BI)[B
   21:	areturn
  LineNumberTable: 
   line 3907: 0
   line 3908: 6
   line 3909: 11
   line 3911: 16

  LocalVariableTable: 
   Start  Length  Slot  Name   Signature
   0      22      0    array       [B
   0      22      1    element       B
   6      16      2    index       I


public static char[] removeElement(char[], char);
  Code:
   Stack=2, Locals=3, Args_size=2
   0:	aload_0
   1:	iload_1
   2:	invokestatic	#133; //Method indexOf:([CC)I
   5:	istore_2
   6:	iload_2
   7:	iconst_m1
   8:	if_icmpne	16
   11:	aload_0
   12:	invokestatic	#109; //Method clone:([C)[C
   15:	areturn
   16:	aload_0
   17:	iload_2
   18:	invokestatic	#170; //Method remove:([CI)[C
   21:	areturn
  LineNumberTable: 
   line 3972: 0
   line 3973: 6
   line 3974: 11
   line 3976: 16

  LocalVariableTable: 
   Start  Length  Slot  Name   Signature
   0      22      0    array       [C
   0      22      1    element       C
   6      16      2    index       I


public static double[] removeElement(double[], double);
  Code:
   Stack=3, Locals=4, Args_size=2
   0:	aload_0
   1:	dload_1
   2:	invokestatic	#135; //Method indexOf:([DD)I
   5:	istore_3
   6:	iload_3
   7:	iconst_m1
   8:	if_icmpne	16
   11:	aload_0
   12:	invokestatic	#110; //Method clone:([D)[D
   15:	areturn
   16:	aload_0
   17:	iload_3
   18:	invokestatic	#171; //Method remove:([DI)[D
   21:	areturn
  LineNumberTable: 
   line 4037: 0
   line 4038: 6
   line 4039: 11
   line 4041: 16

  LocalVariableTable: 
   Start  Length  Slot  Name   Signature
   0      22      0    array       [D
   0      22      1    element       D
   6      16      3    index       I


public static float[] removeElement(float[], float);
  Code:
   Stack=2, Locals=3, Args_size=2
   0:	aload_0
   1:	fload_1
   2:	invokestatic	#138; //Method indexOf:([FF)I
   5:	istore_2
   6:	iload_2
   7:	iconst_m1
   8:	if_icmpne	16
   11:	aload_0
   12:	invokestatic	#111; //Method clone:([F)[F
   15:	areturn
   16:	aload_0
   17:	iload_2
   18:	invokestatic	#172; //Method remove:([FI)[F
   21:	areturn
  LineNumberTable: 
   line 4102: 0
   line 4103: 6
   line 4104: 11
   line 4106: 16

  LocalVariableTable: 
   Start  Length  Slot  Name   Signature
   0      22      0    array       [F
   0      22      1    element       F
   6      16      2    index       I


public static int[] removeElement(int[], int);
  Code:
   Stack=2, Locals=3, Args_size=2
   0:	aload_0
   1:	iload_1
   2:	invokestatic	#140; //Method indexOf:([II)I
   5:	istore_2
   6:	iload_2
   7:	iconst_m1
   8:	if_icmpne	16
   11:	aload_0
   12:	invokestatic	#112; //Method clone:([I)[I
   15:	areturn
   16:	aload_0
   17:	iload_2
   18:	invokestatic	#173; //Method remove:([II)[I
   21:	areturn
  LineNumberTable: 
   line 4167: 0
   line 4168: 6
   line 4169: 11
   line 4171: 16

  LocalVariableTable: 
   Start  Length  Slot  Name   Signature
   0      22      0    array       [I
   0      22      1    element       I
   6      16      2    index       I


public static long[] removeElement(long[], long);
  Code:
   Stack=3, Locals=4, Args_size=2
   0:	aload_0
   1:	lload_1
   2:	invokestatic	#142; //Method indexOf:([JJ)I
   5:	istore_3
   6:	iload_3
   7:	iconst_m1
   8:	if_icmpne	16
   11:	aload_0
   12:	invokestatic	#113; //Method clone:([J)[J
   15:	areturn
   16:	aload_0
   17:	iload_3
   18:	invokestatic	#174; //Method remove:([JI)[J
   21:	areturn
  LineNumberTable: 
   line 4232: 0
   line 4233: 6
   line 4234: 11
   line 4236: 16

  LocalVariableTable: 
   Start  Length  Slot  Name   Signature
   0      22      0    array       [J
   0      22      1    element       J
   6      16      3    index       I


public static java.lang.Object[] removeElement(java.lang.Object[], java.lang.Object);
  Code:
   Stack=2, Locals=3, Args_size=2
   0:	aload_0
   1:	aload_1
   2:	invokestatic	#144; //Method indexOf:([Ljava/lang/Object;Ljava/lang/Object;)I
   5:	istore_2
   6:	iload_2
   7:	iconst_m1
   8:	if_icmpne	16
   11:	aload_0
   12:	invokestatic	#114; //Method clone:([Ljava/lang/Object;)[Ljava/lang/Object;
   15:	areturn
   16:	aload_0
   17:	iload_2
   18:	invokestatic	#175; //Method remove:([Ljava/lang/Object;I)[Ljava/lang/Object;
   21:	areturn
  LineNumberTable: 
   line 3777: 0
   line 3778: 6
   line 3779: 11
   line 3781: 16

  LocalVariableTable: 
   Start  Length  Slot  Name   Signature
   0      22      0    array       [Ljava/lang/Object;
   0      22      1    element       Ljava/lang/Object;
   6      16      2    index       I


public static short[] removeElement(short[], short);
  Code:
   Stack=2, Locals=3, Args_size=2
   0:	aload_0
   1:	iload_1
   2:	invokestatic	#146; //Method indexOf:([SS)I
   5:	istore_2
   6:	iload_2
   7:	iconst_m1
   8:	if_icmpne	16
   11:	aload_0
   12:	invokestatic	#115; //Method clone:([S)[S
   15:	areturn
   16:	aload_0
   17:	iload_2
   18:	invokestatic	#176; //Method remove:([SI)[S
   21:	areturn
  LineNumberTable: 
   line 4297: 0
   line 4298: 6
   line 4299: 11
   line 4301: 16

  LocalVariableTable: 
   Start  Length  Slot  Name   Signature
   0      22      0    array       [S
   0      22      1    element       S
   6      16      2    index       I


public static boolean[] removeElement(boolean[], boolean);
  Code:
   Stack=2, Locals=3, Args_size=2
   0:	aload_0
   1:	iload_1
   2:	invokestatic	#148; //Method indexOf:([ZZ)I
   5:	istore_2
   6:	iload_2
   7:	iconst_m1
   8:	if_icmpne	16
   11:	aload_0
   12:	invokestatic	#116; //Method clone:([Z)[Z
   15:	areturn
   16:	aload_0
   17:	iload_2
   18:	invokestatic	#177; //Method remove:([ZI)[Z
   21:	areturn
  LineNumberTable: 
   line 3842: 0
   line 3843: 6
   line 3844: 11
   line 3846: 16

  LocalVariableTable: 
   Start  Length  Slot  Name   Signature
   0      22      0    array       [Z
   0      22      1    element       Z
   6      16      2    index       I


public static void reverse(byte[]);
  Code:
   Stack=4, Locals=4, Args_size=1
   0:	aload_0
   1:	ifnonnull	5
   4:	return
   5:	iconst_0
   6:	istore_1
   7:	aload_0
   8:	arraylength
   9:	iconst_1
   10:	isub
   11:	istore_2
   12:	goto	35
   15:	aload_0
   16:	iload_2
   17:	baload
   18:	istore_3
   19:	aload_0
   20:	iload_2
   21:	aload_0
   22:	iload_1
   23:	baload
   24:	bastore
   25:	aload_0
   26:	iload_1
   27:	iload_3
   28:	bastore
   29:	iinc	2, -1
   32:	iinc	1, 1
   35:	iload_2
   36:	iload_1
   37:	if_icmpgt	15
   40:	return
  LineNumberTable: 
   line 1102: 0
   line 1103: 4
   line 1105: 5
   line 1106: 7
   line 1108: 12
   line 1109: 15
   line 1110: 19
   line 1111: 25
   line 1112: 29
   line 1113: 32
   line 1108: 35
   line 1101: 40

  LocalVariableTable: 
   Start  Length  Slot  Name   Signature
   0      41      0    array       [B
   7      34      1    i       I
   12      29      2    j       I
   19      16      3    tmp       B


public static void reverse(char[]);
  Code:
   Stack=4, Locals=4, Args_size=1
   0:	aload_0
   1:	ifnonnull	5
   4:	return
   5:	iconst_0
   6:	istore_1
   7:	aload_0
   8:	arraylength
   9:	iconst_1
   10:	isub
   11:	istore_2
   12:	goto	35
   15:	aload_0
   16:	iload_2
   17:	caload
   18:	istore_3
   19:	aload_0
   20:	iload_2
   21:	aload_0
   22:	iload_1
   23:	caload
   24:	castore
   25:	aload_0
   26:	iload_1
   27:	iload_3
   28:	castore
   29:	iinc	2, -1
   32:	iinc	1, 1
   35:	iload_2
   36:	iload_1
   37:	if_icmpgt	15
   40:	return
  LineNumberTable: 
   line 1079: 0
   line 1080: 4
   line 1082: 5
   line 1083: 7
   line 1085: 12
   line 1086: 15
   line 1087: 19
   line 1088: 25
   line 1089: 29
   line 1090: 32
   line 1085: 35
   line 1078: 40

  LocalVariableTable: 
   Start  Length  Slot  Name   Signature
   0      41      0    array       [C
   7      34      1    i       I
   12      29      2    j       I
   19      16      3    tmp       C


public static void reverse(double[]);
  Code:
   Stack=4, Locals=5, Args_size=1
   0:	aload_0
   1:	ifnonnull	5
   4:	return
   5:	iconst_0
   6:	istore_1
   7:	aload_0
   8:	arraylength
   9:	iconst_1
   10:	isub
   11:	istore_2
   12:	goto	35
   15:	aload_0
   16:	iload_2
   17:	daload
   18:	dstore_3
   19:	aload_0
   20:	iload_2
   21:	aload_0
   22:	iload_1
   23:	daload
   24:	dastore
   25:	aload_0
   26:	iload_1
   27:	dload_3
   28:	dastore
   29:	iinc	2, -1
   32:	iinc	1, 1
   35:	iload_2
   36:	iload_1
   37:	if_icmpgt	15
   40:	return
  LineNumberTable: 
   line 1125: 0
   line 1126: 4
   line 1128: 5
   line 1129: 7
   line 1131: 12
   line 1132: 15
   line 1133: 19
   line 1134: 25
   line 1135: 29
   line 1136: 32
   line 1131: 35
   line 1124: 40

  LocalVariableTable: 
   Start  Length  Slot  Name   Signature
   0      41      0    array       [D
   7      34      1    i       I
   12      29      2    j       I
   19      16      3    tmp       D


public static void reverse(float[]);
  Code:
   Stack=4, Locals=4, Args_size=1
   0:	aload_0
   1:	ifnonnull	5
   4:	return
   5:	iconst_0
   6:	istore_1
   7:	aload_0
   8:	arraylength
   9:	iconst_1
   10:	isub
   11:	istore_2
   12:	goto	35
   15:	aload_0
   16:	iload_2
   17:	faload
   18:	fstore_3
   19:	aload_0
   20:	iload_2
   21:	aload_0
   22:	iload_1
   23:	faload
   24:	fastore
   25:	aload_0
   26:	iload_1
   27:	fload_3
   28:	fastore
   29:	iinc	2, -1
   32:	iinc	1, 1
   35:	iload_2
   36:	iload_1
   37:	if_icmpgt	15
   40:	return
  LineNumberTable: 
   line 1148: 0
   line 1149: 4
   line 1151: 5
   line 1152: 7
   line 1154: 12
   line 1155: 15
   line 1156: 19
   line 1157: 25
   line 1158: 29
   line 1159: 32
   line 1154: 35
   line 1147: 40

  LocalVariableTable: 
   Start  Length  Slot  Name   Signature
   0      41      0    array       [F
   7      34      1    i       I
   12      29      2    j       I
   19      16      3    tmp       F


public static void reverse(int[]);
  Code:
   Stack=4, Locals=4, Args_size=1
   0:	aload_0
   1:	ifnonnull	5
   4:	return
   5:	iconst_0
   6:	istore_1
   7:	aload_0
   8:	arraylength
   9:	iconst_1
   10:	isub
   11:	istore_2
   12:	goto	35
   15:	aload_0
   16:	iload_2
   17:	iaload
   18:	istore_3
   19:	aload_0
   20:	iload_2
   21:	aload_0
   22:	iload_1
   23:	iaload
   24:	iastore
   25:	aload_0
   26:	iload_1
   27:	iload_3
   28:	iastore
   29:	iinc	2, -1
   32:	iinc	1, 1
   35:	iload_2
   36:	iload_1
   37:	if_icmpgt	15
   40:	return
  LineNumberTable: 
   line 1033: 0
   line 1034: 4
   line 1036: 5
   line 1037: 7
   line 1039: 12
   line 1040: 15
   line 1041: 19
   line 1042: 25
   line 1043: 29
   line 1044: 32
   line 1039: 35
   line 1032: 40

  LocalVariableTable: 
   Start  Length  Slot  Name   Signature
   0      41      0    array       [I
   7      34      1    i       I
   12      29      2    j       I
   19      16      3    tmp       I


public static void reverse(long[]);
  Code:
   Stack=4, Locals=5, Args_size=1
   0:	aload_0
   1:	ifnonnull	5
   4:	return
   5:	iconst_0
   6:	istore_1
   7:	aload_0
   8:	arraylength
   9:	iconst_1
   10:	isub
   11:	istore_2
   12:	goto	35
   15:	aload_0
   16:	iload_2
   17:	laload
   18:	lstore_3
   19:	aload_0
   20:	iload_2
   21:	aload_0
   22:	iload_1
   23:	laload
   24:	lastore
   25:	aload_0
   26:	iload_1
   27:	lload_3
   28:	lastore
   29:	iinc	2, -1
   32:	iinc	1, 1
   35:	iload_2
   36:	iload_1
   37:	if_icmpgt	15
   40:	return
  LineNumberTable: 
   line 1010: 0
   line 1011: 4
   line 1013: 5
   line 1014: 7
   line 1016: 12
   line 1017: 15
   line 1018: 19
   line 1019: 25
   line 1020: 29
   line 1021: 32
   line 1016: 35
   line 1009: 40

  LocalVariableTable: 
   Start  Length  Slot  Name   Signature
   0      41      0    array       [J
   7      34      1    i       I
   12      29      2    j       I
   19      16      3    tmp       J


public static void reverse(java.lang.Object[]);
  Code:
   Stack=4, Locals=4, Args_size=1
   0:	aload_0
   1:	ifnonnull	5
   4:	return
   5:	iconst_0
   6:	istore_1
   7:	aload_0
   8:	arraylength
   9:	iconst_1
   10:	isub
   11:	istore_2
   12:	goto	35
   15:	aload_0
   16:	iload_2
   17:	aaload
   18:	astore_3
   19:	aload_0
   20:	iload_2
   21:	aload_0
   22:	iload_1
   23:	aaload
   24:	aastore
   25:	aload_0
   26:	iload_1
   27:	aload_3
   28:	aastore
   29:	iinc	2, -1
   32:	iinc	1, 1
   35:	iload_2
   36:	iload_1
   37:	if_icmpgt	15
   40:	return
  LineNumberTable: 
   line 987: 0
   line 988: 4
   line 990: 5
   line 991: 7
   line 993: 12
   line 994: 15
   line 995: 19
   line 996: 25
   line 997: 29
   line 998: 32
   line 993: 35
   line 986: 40

  LocalVariableTable: 
   Start  Length  Slot  Name   Signature
   0      41      0    array       [Ljava/lang/Object;
   7      34      1    i       I
   12      29      2    j       I
   19      16      3    tmp       Ljava/lang/Object;


public static void reverse(short[]);
  Code:
   Stack=4, Locals=4, Args_size=1
   0:	aload_0
   1:	ifnonnull	5
   4:	return
   5:	iconst_0
   6:	istore_1
   7:	aload_0
   8:	arraylength
   9:	iconst_1
   10:	isub
   11:	istore_2
   12:	goto	35
   15:	aload_0
   16:	iload_2
   17:	saload
   18:	istore_3
   19:	aload_0
   20:	iload_2
   21:	aload_0
   22:	iload_1
   23:	saload
   24:	sastore
   25:	aload_0
   26:	iload_1
   27:	iload_3
   28:	sastore
   29:	iinc	2, -1
   32:	iinc	1, 1
   35:	iload_2
   36:	iload_1
   37:	if_icmpgt	15
   40:	return
  LineNumberTable: 
   line 1056: 0
   line 1057: 4
   line 1059: 5
   line 1060: 7
   line 1062: 12
   line 1063: 15
   line 1064: 19
   line 1065: 25
   line 1066: 29
   line 1067: 32
   line 1062: 35
   line 1055: 40

  LocalVariableTable: 
   Start  Length  Slot  Name   Signature
   0      41      0    array       [S
   7      34      1    i       I
   12      29      2    j       I
   19      16      3    tmp       S


public static void reverse(boolean[]);
  Code:
   Stack=4, Locals=4, Args_size=1
   0:	aload_0
   1:	ifnonnull	5
   4:	return
   5:	iconst_0
   6:	istore_1
   7:	aload_0
   8:	arraylength
   9:	iconst_1
   10:	isub
   11:	istore_2
   12:	goto	35
   15:	aload_0
   16:	iload_2
   17:	baload
   18:	istore_3
   19:	aload_0
   20:	iload_2
   21:	aload_0
   22:	iload_1
   23:	baload
   24:	bastore
   25:	aload_0
   26:	iload_1
   27:	iload_3
   28:	bastore
   29:	iinc	2, -1
   32:	iinc	1, 1
   35:	iload_2
   36:	iload_1
   37:	if_icmpgt	15
   40:	return
  LineNumberTable: 
   line 1171: 0
   line 1172: 4
   line 1174: 5
   line 1175: 7
   line 1177: 12
   line 1178: 15
   line 1179: 19
   line 1180: 25
   line 1181: 29
   line 1182: 32
   line 1177: 35
   line 1170: 40

  LocalVariableTable: 
   Start  Length  Slot  Name   Signature
   0      41      0    array       [Z
   7      34      1    i       I
   12      29      2    j       I
   19      16      3    tmp       Z


public static byte[] subarray(byte[], int, int);
  Code:
   Stack=5, Locals=5, Args_size=3
   0:	aload_0
   1:	ifnonnull	6
   4:	aconst_null
   5:	areturn
   6:	iload_1
   7:	ifge	12
   10:	iconst_0
   11:	istore_1
   12:	iload_2
   13:	aload_0
   14:	arraylength
   15:	if_icmple	21
   18:	aload_0
   19:	arraylength
   20:	istore_2
   21:	iload_2
   22:	iload_1
   23:	isub
   24:	istore_3
   25:	iload_3
   26:	ifgt	33
   29:	getstatic	#67; //Field EMPTY_BYTE_ARRAY:[B
   32:	areturn
   33:	iload_3
   34:	newarray byte
   36:	astore	4
   38:	aload_0
   39:	iload_1
   40:	aload	4
   42:	iconst_0
   43:	iload_3
   44:	invokestatic	#102; //Method java/lang/System.arraycopy:(Ljava/lang/Object;ILjava/lang/Object;II)V
   47:	aload	4
   49:	areturn
  LineNumberTable: 
   line 628: 0
   line 629: 4
   line 631: 6
   line 632: 10
   line 634: 12
   line 635: 18
   line 637: 21
   line 638: 25
   line 639: 29
   line 642: 33
   line 643: 38
   line 644: 47

  LocalVariableTable: 
   Start  Length  Slot  Name   Signature
   0      50      0    array       [B
   0      50      1    startIndexInclusive       I
   0      50      2    endIndexExclusive       I
   25      25      3    newSize       I
   38      12      4    subarray       [B


public static char[] subarray(char[], int, int);
  Code:
   Stack=5, Locals=5, Args_size=3
   0:	aload_0
   1:	ifnonnull	6
   4:	aconst_null
   5:	areturn
   6:	iload_1
   7:	ifge	12
   10:	iconst_0
   11:	istore_1
   12:	iload_2
   13:	aload_0
   14:	arraylength
   15:	if_icmple	21
   18:	aload_0
   19:	arraylength
   20:	istore_2
   21:	iload_2
   22:	iload_1
   23:	isub
   24:	istore_3
   25:	iload_3
   26:	ifgt	33
   29:	getstatic	#70; //Field EMPTY_CHAR_ARRAY:[C
   32:	areturn
   33:	iload_3
   34:	newarray char
   36:	astore	4
   38:	aload_0
   39:	iload_1
   40:	aload	4
   42:	iconst_0
   43:	iload_3
   44:	invokestatic	#102; //Method java/lang/System.arraycopy:(Ljava/lang/Object;ILjava/lang/Object;II)V
   47:	aload	4
   49:	areturn
  LineNumberTable: 
   line 589: 0
   line 590: 4
   line 592: 6
   line 593: 10
   line 595: 12
   line 596: 18
   line 598: 21
   line 599: 25
   line 600: 29
   line 603: 33
   line 604: 38
   line 605: 47

  LocalVariableTable: 
   Start  Length  Slot  Name   Signature
   0      50      0    array       [C
   0      50      1    startIndexInclusive       I
   0      50      2    endIndexExclusive       I
   25      25      3    newSize       I
   38      12      4    subarray       [C


public static double[] subarray(double[], int, int);
  Code:
   Stack=5, Locals=5, Args_size=3
   0:	aload_0
   1:	ifnonnull	6
   4:	aconst_null
   5:	areturn
   6:	iload_1
   7:	ifge	12
   10:	iconst_0
   11:	istore_1
   12:	iload_2
   13:	aload_0
   14:	arraylength
   15:	if_icmple	21
   18:	aload_0
   19:	arraylength
   20:	istore_2
   21:	iload_2
   22:	iload_1
   23:	isub
   24:	istore_3
   25:	iload_3
   26:	ifgt	33
   29:	getstatic	#72; //Field EMPTY_DOUBLE_ARRAY:[D
   32:	areturn
   33:	iload_3
   34:	newarray double
   36:	astore	4
   38:	aload_0
   39:	iload_1
   40:	aload	4
   42:	iconst_0
   43:	iload_3
   44:	invokestatic	#102; //Method java/lang/System.arraycopy:(Ljava/lang/Object;ILjava/lang/Object;II)V
   47:	aload	4
   49:	areturn
  LineNumberTable: 
   line 667: 0
   line 668: 4
   line 670: 6
   line 671: 10
   line 673: 12
   line 674: 18
   line 676: 21
   line 677: 25
   line 678: 29
   line 681: 33
   line 682: 38
   line 683: 47

  LocalVariableTable: 
   Start  Length  Slot  Name   Signature
   0      50      0    array       [D
   0      50      1    startIndexInclusive       I
   0      50      2    endIndexExclusive       I
   25      25      3    newSize       I
   38      12      4    subarray       [D


public static float[] subarray(float[], int, int);
  Code:
   Stack=5, Locals=5, Args_size=3
   0:	aload_0
   1:	ifnonnull	6
   4:	aconst_null
   5:	areturn
   6:	iload_1
   7:	ifge	12
   10:	iconst_0
   11:	istore_1
   12:	iload_2
   13:	aload_0
   14:	arraylength
   15:	if_icmple	21
   18:	aload_0
   19:	arraylength
   20:	istore_2
   21:	iload_2
   22:	iload_1
   23:	isub
   24:	istore_3
   25:	iload_3
   26:	ifgt	33
   29:	getstatic	#74; //Field EMPTY_FLOAT_ARRAY:[F
   32:	areturn
   33:	iload_3
   34:	newarray float
   36:	astore	4
   38:	aload_0
   39:	iload_1
   40:	aload	4
   42:	iconst_0
   43:	iload_3
   44:	invokestatic	#102; //Method java/lang/System.arraycopy:(Ljava/lang/Object;ILjava/lang/Object;II)V
   47:	aload	4
   49:	areturn
  LineNumberTable: 
   line 706: 0
   line 707: 4
   line 709: 6
   line 710: 10
   line 712: 12
   line 713: 18
   line 715: 21
   line 716: 25
   line 717: 29
   line 720: 33
   line 721: 38
   line 722: 47

  LocalVariableTable: 
   Start  Length  Slot  Name   Signature
   0      50      0    array       [F
   0      50      1    startIndexInclusive       I
   0      50      2    endIndexExclusive       I
   25      25      3    newSize       I
   38      12      4    subarray       [F


public static int[] subarray(int[], int, int);
  Code:
   Stack=5, Locals=5, Args_size=3
   0:	aload_0
   1:	ifnonnull	6
   4:	aconst_null
   5:	areturn
   6:	iload_1
   7:	ifge	12
   10:	iconst_0
   11:	istore_1
   12:	iload_2
   13:	aload_0
   14:	arraylength
   15:	if_icmple	21
   18:	aload_0
   19:	arraylength
   20:	istore_2
   21:	iload_2
   22:	iload_1
   23:	isub
   24:	istore_3
   25:	iload_3
   26:	ifgt	33
   29:	getstatic	#77; //Field EMPTY_INT_ARRAY:[I
   32:	areturn
   33:	iload_3
   34:	newarray int
   36:	astore	4
   38:	aload_0
   39:	iload_1
   40:	aload	4
   42:	iconst_0
   43:	iload_3
   44:	invokestatic	#102; //Method java/lang/System.arraycopy:(Ljava/lang/Object;ILjava/lang/Object;II)V
   47:	aload	4
   49:	areturn
  LineNumberTable: 
   line 511: 0
   line 512: 4
   line 514: 6
   line 515: 10
   line 517: 12
   line 518: 18
   line 520: 21
   line 521: 25
   line 522: 29
   line 525: 33
   line 526: 38
   line 527: 47

  LocalVariableTable: 
   Start  Length  Slot  Name   Signature
   0      50      0    array       [I
   0      50      1    startIndexInclusive       I
   0      50      2    endIndexExclusive       I
   25      25      3    newSize       I
   38      12      4    subarray       [I


public static long[] subarray(long[], int, int);
  Code:
   Stack=5, Locals=5, Args_size=3
   0:	aload_0
   1:	ifnonnull	6
   4:	aconst_null
   5:	areturn
   6:	iload_1
   7:	ifge	12
   10:	iconst_0
   11:	istore_1
   12:	iload_2
   13:	aload_0
   14:	arraylength
   15:	if_icmple	21
   18:	aload_0
   19:	arraylength
   20:	istore_2
   21:	iload_2
   22:	iload_1
   23:	isub
   24:	istore_3
   25:	iload_3
   26:	ifgt	33
   29:	getstatic	#78; //Field EMPTY_LONG_ARRAY:[J
   32:	areturn
   33:	iload_3
   34:	newarray long
   36:	astore	4
   38:	aload_0
   39:	iload_1
   40:	aload	4
   42:	iconst_0
   43:	iload_3
   44:	invokestatic	#102; //Method java/lang/System.arraycopy:(Ljava/lang/Object;ILjava/lang/Object;II)V
   47:	aload	4
   49:	areturn
  LineNumberTable: 
   line 472: 0
   line 473: 4
   line 475: 6
   line 476: 10
   line 478: 12
   line 479: 18
   line 481: 21
   line 482: 25
   line 483: 29
   line 486: 33
   line 487: 38
   line 488: 47

  LocalVariableTable: 
   Start  Length  Slot  Name   Signature
   0      50      0    array       [J
   0      50      1    startIndexInclusive       I
   0      50      2    endIndexExclusive       I
   25      25      3    newSize       I
   38      12      4    subarray       [J


public static java.lang.Object[] subarray(java.lang.Object[], int, int);
  Code:
   Stack=5, Locals=6, Args_size=3
   0:	aload_0
   1:	ifnonnull	6
   4:	aconst_null
   5:	areturn
   6:	iload_1
   7:	ifge	12
   10:	iconst_0
   11:	istore_1
   12:	iload_2
   13:	aload_0
   14:	arraylength
   15:	if_icmple	21
   18:	aload_0
   19:	arraylength
   20:	istore_2
   21:	iload_2
   22:	iload_1
   23:	isub
   24:	istore_3
   25:	aload_0
   26:	invokevirtual	#123; //Method java/lang/Object.getClass:()Ljava/lang/Class;
   29:	invokevirtual	#124; //Method java/lang/Class.getComponentType:()Ljava/lang/Class;
   32:	astore	4
   34:	iload_3
   35:	ifgt	48
   38:	aload	4
   40:	iconst_0
   41:	invokestatic	#166; //Method java/lang/reflect/Array.newInstance:(Ljava/lang/Class;I)Ljava/lang/Object;
   44:	checkcast	#18; //class "[Ljava/lang/Object;"
   47:	areturn
   48:	aload	4
   50:	iload_3
   51:	invokestatic	#166; //Method java/lang/reflect/Array.newInstance:(Ljava/lang/Class;I)Ljava/lang/Object;
   54:	checkcast	#18; //class "[Ljava/lang/Object;"
   57:	astore	5
   59:	aload_0
   60:	iload_1
   61:	aload	5
   63:	iconst_0
   64:	iload_3
   65:	invokestatic	#102; //Method java/lang/System.arraycopy:(Ljava/lang/Object;ILjava/lang/Object;II)V
   68:	aload	5
   70:	areturn
  LineNumberTable: 
   line 433: 0
   line 434: 4
   line 436: 6
   line 437: 10
   line 439: 12
   line 440: 18
   line 442: 21
   line 443: 25
   line 444: 34
   line 445: 38
   line 447: 48
   line 448: 59
   line 449: 68

  LocalVariableTable: 
   Start  Length  Slot  Name   Signature
   0      71      0    array       [Ljava/lang/Object;
   0      71      1    startIndexInclusive       I
   0      71      2    endIndexExclusive       I
   25      46      3    newSize       I
   34      37      4    type       Ljava/lang/Class;
   59      12      5    subarray       [Ljava/lang/Object;


public static short[] subarray(short[], int, int);
  Code:
   Stack=5, Locals=5, Args_size=3
   0:	aload_0
   1:	ifnonnull	6
   4:	aconst_null
   5:	areturn
   6:	iload_1
   7:	ifge	12
   10:	iconst_0
   11:	istore_1
   12:	iload_2
   13:	aload_0
   14:	arraylength
   15:	if_icmple	21
   18:	aload_0
   19:	arraylength
   20:	istore_2
   21:	iload_2
   22:	iload_1
   23:	isub
   24:	istore_3
   25:	iload_3
   26:	ifgt	33
   29:	getstatic	#81; //Field EMPTY_SHORT_ARRAY:[S
   32:	areturn
   33:	iload_3
   34:	newarray short
   36:	astore	4
   38:	aload_0
   39:	iload_1
   40:	aload	4
   42:	iconst_0
   43:	iload_3
   44:	invokestatic	#102; //Method java/lang/System.arraycopy:(Ljava/lang/Object;ILjava/lang/Object;II)V
   47:	aload	4
   49:	areturn
  LineNumberTable: 
   line 550: 0
   line 551: 4
   line 553: 6
   line 554: 10
   line 556: 12
   line 557: 18
   line 559: 21
   line 560: 25
   line 561: 29
   line 564: 33
   line 565: 38
   line 566: 47

  LocalVariableTable: 
   Start  Length  Slot  Name   Signature
   0      50      0    array       [S
   0      50      1    startIndexInclusive       I
   0      50      2    endIndexExclusive       I
   25      25      3    newSize       I
   38      12      4    subarray       [S


public static boolean[] subarray(boolean[], int, int);
  Code:
   Stack=5, Locals=5, Args_size=3
   0:	aload_0
   1:	ifnonnull	6
   4:	aconst_null
   5:	areturn
   6:	iload_1
   7:	ifge	12
   10:	iconst_0
   11:	istore_1
   12:	iload_2
   13:	aload_0
   14:	arraylength
   15:	if_icmple	21
   18:	aload_0
   19:	arraylength
   20:	istore_2
   21:	iload_2
   22:	iload_1
   23:	isub
   24:	istore_3
   25:	iload_3
   26:	ifgt	33
   29:	getstatic	#65; //Field EMPTY_BOOLEAN_ARRAY:[Z
   32:	areturn
   33:	iload_3
   34:	newarray boolean
   36:	astore	4
   38:	aload_0
   39:	iload_1
   40:	aload	4
   42:	iconst_0
   43:	iload_3
   44:	invokestatic	#102; //Method java/lang/System.arraycopy:(Ljava/lang/Object;ILjava/lang/Object;II)V
   47:	aload	4
   49:	areturn
  LineNumberTable: 
   line 745: 0
   line 746: 4
   line 748: 6
   line 749: 10
   line 751: 12
   line 752: 18
   line 754: 21
   line 755: 25
   line 756: 29
   line 759: 33
   line 760: 38
   line 761: 47

  LocalVariableTable: 
   Start  Length  Slot  Name   Signature
   0      50      0    array       [Z
   0      50      1    startIndexInclusive       I
   0      50      2    endIndexExclusive       I
   25      25      3    newSize       I
   38      12      4    subarray       [Z


public static java.util.Map toMap(java.lang.Object[]);
  Code:
   Stack=6, Locals=5, Args_size=1
   0:	aload_0
   1:	ifnonnull	6
   4:	aconst_null
   5:	areturn
   6:	new	#40; //class java/util/HashMap
   9:	dup
   10:	aload_0
   11:	arraylength
   12:	i2d
   13:	ldc2_w	#184; //double 1.5d
   16:	dmul
   17:	d2i
   18:	invokespecial	#56; //Method java/util/HashMap."<init>":(I)V
   21:	astore_1
   22:	iconst_0
   23:	istore_2
   24:	goto	185
   27:	aload_0
   28:	iload_2
   29:	aaload
   30:	astore_3
   31:	aload_3
   32:	instanceof	#42; //class java/util/Map$Entry
   35:	ifeq	68
   38:	aload_3
   39:	checkcast	#42; //class java/util/Map$Entry
   42:	astore	4
   44:	aload_1
   45:	aload	4
   47:	invokeinterface	#125,  1; //InterfaceMethod java/util/Map$Entry.getKey:()Ljava/lang/Object;
   52:	aload	4
   54:	invokeinterface	#130,  1; //InterfaceMethod java/util/Map$Entry.getValue:()Ljava/lang/Object;
   59:	invokeinterface	#167,  3; //InterfaceMethod java/util/Map.put:(Ljava/lang/Object;Ljava/lang/Object;)Ljava/lang/Object;
   64:	pop
   65:	goto	182
   68:	aload_3
   69:	instanceof	#18; //class "[Ljava/lang/Object;"
   72:	ifeq	144
   75:	aload_3
   76:	checkcast	#18; //class "[Ljava/lang/Object;"
   79:	astore	4
   81:	aload	4
   83:	arraylength
   84:	iconst_2
   85:	if_icmpge	126
   88:	new	#28; //class java/lang/IllegalArgumentException
   91:	dup
   92:	new	#36; //class java/lang/StringBuffer
   95:	dup
   96:	ldc	#7; //String Array element 
   98:	invokespecial	#62; //Method java/lang/StringBuffer."<init>":(Ljava/lang/String;)V
   101:	iload_2
   102:	invokevirtual	#96; //Method java/lang/StringBuffer.append:(I)Ljava/lang/StringBuffer;
   105:	ldc	#4; //String , '
   107:	invokevirtual	#101; //Method java/lang/StringBuffer.append:(Ljava/lang/String;)Ljava/lang/StringBuffer;
   110:	aload_3
   111:	invokevirtual	#97; //Method java/lang/StringBuffer.append:(Ljava/lang/Object;)Ljava/lang/StringBuffer;
   114:	ldc	#2; //String ', has a length less than 2
   116:	invokevirtual	#101; //Method java/lang/StringBuffer.append:(Ljava/lang/String;)Ljava/lang/StringBuffer;
   119:	invokevirtual	#181; //Method java/lang/StringBuffer.toString:()Ljava/lang/String;
   122:	invokespecial	#59; //Method java/lang/IllegalArgumentException."<init>":(Ljava/lang/String;)V
   125:	athrow
   126:	aload_1
   127:	aload	4
   129:	iconst_0
   130:	aaload
   131:	aload	4
   133:	iconst_1
   134:	aaload
   135:	invokeinterface	#167,  3; //InterfaceMethod java/util/Map.put:(Ljava/lang/Object;Ljava/lang/Object;)Ljava/lang/Object;
   140:	pop
   141:	goto	182
   144:	new	#28; //class java/lang/IllegalArgumentException
   147:	dup
   148:	new	#36; //class java/lang/StringBuffer
   151:	dup
   152:	ldc	#7; //String Array element 
   154:	invokespecial	#62; //Method java/lang/StringBuffer."<init>":(Ljava/lang/String;)V
   157:	iload_2
   158:	invokevirtual	#96; //Method java/lang/StringBuffer.append:(I)Ljava/lang/StringBuffer;
   161:	ldc	#4; //String , '
   163:	invokevirtual	#101; //Method java/lang/StringBuffer.append:(Ljava/lang/String;)Ljava/lang/StringBuffer;
   166:	aload_3
   167:	invokevirtual	#97; //Method java/lang/StringBuffer.append:(Ljava/lang/Object;)Ljava/lang/StringBuffer;
   170:	ldc	#3; //String ', is neither of type Map.Entry nor an Array
   172:	invokevirtual	#101; //Method java/lang/StringBuffer.append:(Ljava/lang/String;)Ljava/lang/StringBuffer;
   175:	invokevirtual	#181; //Method java/lang/StringBuffer.toString:()Ljava/lang/String;
   178:	invokespecial	#59; //Method java/lang/IllegalArgumentException."<init>":(Ljava/lang/String;)V
   181:	athrow
   182:	iinc	2, 1
   185:	iload_2
   186:	aload_0
   187:	arraylength
   188:	if_icmplt	27
   191:	aload_1
   192:	areturn
  LineNumberTable: 
   line 228: 0
   line 229: 4
   line 231: 6
   line 232: 22
   line 233: 27
   line 234: 31
   line 235: 38
   line 236: 44
   line 234: 65
   line 237: 68
   line 238: 75
   line 239: 81
   line 240: 88
   line 241: 110
   line 242: 114
   line 240: 122
   line 244: 126
   line 237: 141
   line 246: 144
   line 247: 166
   line 248: 170
   line 246: 178
   line 232: 182
   line 251: 191

  LocalVariableTable: 
   Start  Length  Slot  Name   Signature
   0      193      0    array       [Ljava/lang/Object;
   22      171      1    map       Ljava/util/Map;
   24      169      2    i       I
   31      154      3    object       Ljava/lang/Object;
   44      24      4    entry       Ljava/util/Map$Entry;
   81      63      4    entry       [Ljava/lang/Object;


public static java.lang.Byte[] toObject(byte[]);
  Code:
   Stack=6, Locals=3, Args_size=1
   0:	aload_0
   1:	ifnonnull	6
   4:	aconst_null
   5:	areturn
   6:	aload_0
   7:	arraylength
   8:	ifne	15
   11:	getstatic	#68; //Field EMPTY_BYTE_OBJECT_ARRAY:[Ljava/lang/Byte;
   14:	areturn
   15:	aload_0
   16:	arraylength
   17:	anewarray	#22; //class java/lang/Byte
   20:	astore_1
   21:	iconst_0
   22:	istore_2
   23:	goto	42
   26:	aload_1
   27:	iload_2
   28:	new	#22; //class java/lang/Byte
   31:	dup
   32:	aload_0
   33:	iload_2
   34:	baload
   35:	invokespecial	#51; //Method java/lang/Byte."<init>":(B)V
   38:	aastore
   39:	iinc	2, 1
   42:	iload_2
   43:	aload_0
   44:	arraylength
   45:	if_icmplt	26
   48:	aload_1
   49:	areturn
  LineNumberTable: 
   line 2521: 0
   line 2522: 4
   line 2523: 6
   line 2524: 11
   line 2526: 15
   line 2527: 21
   line 2528: 26
   line 2527: 39
   line 2530: 48

  LocalVariableTable: 
   Start  Length  Slot  Name   Signature
   0      50      0    array       [B
   21      29      1    result       [Ljava/lang/Byte;
   23      27      2    i       I


public static java.lang.Double[] toObject(double[]);
  Code:
   Stack=6, Locals=3, Args_size=1
   0:	aload_0
   1:	ifnonnull	6
   4:	aconst_null
   5:	areturn
   6:	aload_0
   7:	arraylength
   8:	ifne	15
   11:	getstatic	#73; //Field EMPTY_DOUBLE_OBJECT_ARRAY:[Ljava/lang/Double;
   14:	areturn
   15:	aload_0
   16:	arraylength
   17:	anewarray	#26; //class java/lang/Double
   20:	astore_1
   21:	iconst_0
   22:	istore_2
   23:	goto	42
   26:	aload_1
   27:	iload_2
   28:	new	#26; //class java/lang/Double
   31:	dup
   32:	aload_0
   33:	iload_2
   34:	daload
   35:	invokespecial	#53; //Method java/lang/Double."<init>":(D)V
   38:	aastore
   39:	iinc	2, 1
   42:	iload_2
   43:	aload_0
   44:	arraylength
   45:	if_icmplt	26
   48:	aload_1
   49:	areturn
  LineNumberTable: 
   line 2589: 0
   line 2590: 4
   line 2591: 6
   line 2592: 11
   line 2594: 15
   line 2595: 21
   line 2596: 26
   line 2595: 39
   line 2598: 48

  LocalVariableTable: 
   Start  Length  Slot  Name   Signature
   0      50      0    array       [D
   21      29      1    result       [Ljava/lang/Double;
   23      27      2    i       I


public static java.lang.Float[] toObject(float[]);
  Code:
   Stack=6, Locals=3, Args_size=1
   0:	aload_0
   1:	ifnonnull	6
   4:	aconst_null
   5:	areturn
   6:	aload_0
   7:	arraylength
   8:	ifne	15
   11:	getstatic	#75; //Field EMPTY_FLOAT_OBJECT_ARRAY:[Ljava/lang/Float;
   14:	areturn
   15:	aload_0
   16:	arraylength
   17:	anewarray	#27; //class java/lang/Float
   20:	astore_1
   21:	iconst_0
   22:	istore_2
   23:	goto	42
   26:	aload_1
   27:	iload_2
   28:	new	#27; //class java/lang/Float
   31:	dup
   32:	aload_0
   33:	iload_2
   34:	faload
   35:	invokespecial	#54; //Method java/lang/Float."<init>":(F)V
   38:	aastore
   39:	iinc	2, 1
   42:	iload_2
   43:	aload_0
   44:	arraylength
   45:	if_icmplt	26
   48:	aload_1
   49:	areturn
  LineNumberTable: 
   line 2657: 0
   line 2658: 4
   line 2659: 6
   line 2660: 11
   line 2662: 15
   line 2663: 21
   line 2664: 26
   line 2663: 39
   line 2666: 48

  LocalVariableTable: 
   Start  Length  Slot  Name   Signature
   0      50      0    array       [F
   21      29      1    result       [Ljava/lang/Float;
   23      27      2    i       I


public static java.lang.Integer[] toObject(int[]);
  Code:
   Stack=6, Locals=3, Args_size=1
   0:	aload_0
   1:	ifnonnull	6
   4:	aconst_null
   5:	areturn
   6:	aload_0
   7:	arraylength
   8:	ifne	15
   11:	getstatic	#76; //Field EMPTY_INTEGER_OBJECT_ARRAY:[Ljava/lang/Integer;
   14:	areturn
   15:	aload_0
   16:	arraylength
   17:	anewarray	#30; //class java/lang/Integer
   20:	astore_1
   21:	iconst_0
   22:	istore_2
   23:	goto	42
   26:	aload_1
   27:	iload_2
   28:	new	#30; //class java/lang/Integer
   31:	dup
   32:	aload_0
   33:	iload_2
   34:	iaload
   35:	invokespecial	#55; //Method java/lang/Integer."<init>":(I)V
   38:	aastore
   39:	iinc	2, 1
   42:	iload_2
   43:	aload_0
   44:	arraylength
   45:	if_icmplt	26
   48:	aload_1
   49:	areturn
  LineNumberTable: 
   line 2385: 0
   line 2386: 4
   line 2387: 6
   line 2388: 11
   line 2390: 15
   line 2391: 21
   line 2392: 26
   line 2391: 39
   line 2394: 48

  LocalVariableTable: 
   Start  Length  Slot  Name   Signature
   0      50      0    array       [I
   21      29      1    result       [Ljava/lang/Integer;
   23      27      2    i       I


public static java.lang.Long[] toObject(long[]);
  Code:
   Stack=6, Locals=3, Args_size=1
   0:	aload_0
   1:	ifnonnull	6
   4:	aconst_null
   5:	areturn
   6:	aload_0
   7:	arraylength
   8:	ifne	15
   11:	getstatic	#79; //Field EMPTY_LONG_OBJECT_ARRAY:[Ljava/lang/Long;
   14:	areturn
   15:	aload_0
   16:	arraylength
   17:	anewarray	#31; //class java/lang/Long
   20:	astore_1
   21:	iconst_0
   22:	istore_2
   23:	goto	42
   26:	aload_1
   27:	iload_2
   28:	new	#31; //class java/lang/Long
   31:	dup
   32:	aload_0
   33:	iload_2
   34:	laload
   35:	invokespecial	#57; //Method java/lang/Long."<init>":(J)V
   38:	aastore
   39:	iinc	2, 1
   42:	iload_2
   43:	aload_0
   44:	arraylength
   45:	if_icmplt	26
   48:	aload_1
   49:	areturn
  LineNumberTable: 
   line 2317: 0
   line 2318: 4
   line 2319: 6
   line 2320: 11
   line 2322: 15
   line 2323: 21
   line 2324: 26
   line 2323: 39
   line 2326: 48

  LocalVariableTable: 
   Start  Length  Slot  Name   Signature
   0      50      0    array       [J
   21      29      1    result       [Ljava/lang/Long;
   23      27      2    i       I


public static java.lang.Short[] toObject(short[]);
  Code:
   Stack=6, Locals=3, Args_size=1
   0:	aload_0
   1:	ifnonnull	6
   4:	aconst_null
   5:	areturn
   6:	aload_0
   7:	arraylength
   8:	ifne	15
   11:	getstatic	#82; //Field EMPTY_SHORT_OBJECT_ARRAY:[Ljava/lang/Short;
   14:	areturn
   15:	aload_0
   16:	arraylength
   17:	anewarray	#34; //class java/lang/Short
   20:	astore_1
   21:	iconst_0
   22:	istore_2
   23:	goto	42
   26:	aload_1
   27:	iload_2
   28:	new	#34; //class java/lang/Short
   31:	dup
   32:	aload_0
   33:	iload_2
   34:	saload
   35:	invokespecial	#63; //Method java/lang/Short."<init>":(S)V
   38:	aastore
   39:	iinc	2, 1
   42:	iload_2
   43:	aload_0
   44:	arraylength
   45:	if_icmplt	26
   48:	aload_1
   49:	areturn
  LineNumberTable: 
   line 2453: 0
   line 2454: 4
   line 2455: 6
   line 2456: 11
   line 2458: 15
   line 2459: 21
   line 2460: 26
   line 2459: 39
   line 2462: 48

  LocalVariableTable: 
   Start  Length  Slot  Name   Signature
   0      50      0    array       [S
   21      29      1    result       [Ljava/lang/Short;
   23      27      2    i       I


public static java.lang.Boolean[] toObject(boolean[]);
  Code:
   Stack=4, Locals=3, Args_size=1
   0:	aload_0
   1:	ifnonnull	6
   4:	aconst_null
   5:	areturn
   6:	aload_0
   7:	arraylength
   8:	ifne	15
   11:	getstatic	#66; //Field EMPTY_BOOLEAN_OBJECT_ARRAY:[Ljava/lang/Boolean;
   14:	areturn
   15:	aload_0
   16:	arraylength
   17:	anewarray	#21; //class java/lang/Boolean
   20:	astore_1
   21:	iconst_0
   22:	istore_2
   23:	goto	47
   26:	aload_1
   27:	iload_2
   28:	aload_0
   29:	iload_2
   30:	baload
   31:	ifeq	40
   34:	getstatic	#86; //Field java/lang/Boolean.TRUE:Ljava/lang/Boolean;
   37:	goto	43
   40:	getstatic	#84; //Field java/lang/Boolean.FALSE:Ljava/lang/Boolean;
   43:	aastore
   44:	iinc	2, 1
   47:	iload_2
   48:	aload_0
   49:	arraylength
   50:	if_icmplt	26
   53:	aload_1
   54:	areturn
  LineNumberTable: 
   line 2725: 0
   line 2726: 4
   line 2727: 6
   line 2728: 11
   line 2730: 15
   line 2731: 21
   line 2732: 26
   line 2731: 44
   line 2734: 53

  LocalVariableTable: 
   Start  Length  Slot  Name   Signature
   0      55      0    array       [Z
   21      34      1    result       [Ljava/lang/Boolean;
   23      32      2    i       I


public static boolean[] toPrimitive(java.lang.Boolean[]);
  Code:
   Stack=4, Locals=3, Args_size=1
   0:	aload_0
   1:	ifnonnull	6
   4:	aconst_null
   5:	areturn
   6:	aload_0
   7:	arraylength
   8:	ifne	15
   11:	getstatic	#65; //Field EMPTY_BOOLEAN_ARRAY:[Z
   14:	areturn
   15:	aload_0
   16:	arraylength
   17:	newarray boolean
   19:	astore_1
   20:	iconst_0
   21:	istore_2
   22:	goto	37
   25:	aload_1
   26:	iload_2
   27:	aload_0
   28:	iload_2
   29:	aaload
   30:	invokevirtual	#103; //Method java/lang/Boolean.booleanValue:()Z
   33:	bastore
   34:	iinc	2, 1
   37:	iload_2
   38:	aload_0
   39:	arraylength
   40:	if_icmplt	25
   43:	aload_1
   44:	areturn
  LineNumberTable: 
   line 2681: 0
   line 2682: 4
   line 2683: 6
   line 2684: 11
   line 2686: 15
   line 2687: 20
   line 2688: 25
   line 2687: 34
   line 2690: 43

  LocalVariableTable: 
   Start  Length  Slot  Name   Signature
   0      45      0    array       [Ljava/lang/Boolean;
   20      25      1    result       [Z
   22      23      2    i       I


public static boolean[] toPrimitive(java.lang.Boolean[], boolean);
  Code:
   Stack=3, Locals=5, Args_size=2
   0:	aload_0
   1:	ifnonnull	6
   4:	aconst_null
   5:	areturn
   6:	aload_0
   7:	arraylength
   8:	ifne	15
   11:	getstatic	#65; //Field EMPTY_BOOLEAN_ARRAY:[Z
   14:	areturn
   15:	aload_0
   16:	arraylength
   17:	newarray boolean
   19:	astore_2
   20:	iconst_0
   21:	istore_3
   22:	goto	50
   25:	aload_0
   26:	iload_3
   27:	aaload
   28:	astore	4
   30:	aload_2
   31:	iload_3
   32:	aload	4
   34:	ifnonnull	41
   37:	iload_1
   38:	goto	46
   41:	aload	4
   43:	invokevirtual	#103; //Method java/lang/Boolean.booleanValue:()Z
   46:	bastore
   47:	iinc	3, 1
   50:	iload_3
   51:	aload_0
   52:	arraylength
   53:	if_icmplt	25
   56:	aload_2
   57:	areturn
  LineNumberTable: 
   line 2703: 0
   line 2704: 4
   line 2705: 6
   line 2706: 11
   line 2708: 15
   line 2709: 20
   line 2710: 25
   line 2711: 30
   line 2709: 47
   line 2713: 56

  LocalVariableTable: 
   Start  Length  Slot  Name   Signature
   0      58      0    array       [Ljava/lang/Boolean;
   0      58      1    valueForNull       Z
   20      38      2    result       [Z
   22      36      3    i       I
   30      20      4    b       Ljava/lang/Boolean;


public static byte[] toPrimitive(java.lang.Byte[]);
  Code:
   Stack=4, Locals=3, Args_size=1
   0:	aload_0
   1:	ifnonnull	6
   4:	aconst_null
   5:	areturn
   6:	aload_0
   7:	arraylength
   8:	ifne	15
   11:	getstatic	#67; //Field EMPTY_BYTE_ARRAY:[B
   14:	areturn
   15:	aload_0
   16:	arraylength
   17:	newarray byte
   19:	astore_1
   20:	iconst_0
   21:	istore_2
   22:	goto	37
   25:	aload_1
   26:	iload_2
   27:	aload_0
   28:	iload_2
   29:	aaload
   30:	invokevirtual	#104; //Method java/lang/Byte.byteValue:()B
   33:	bastore
   34:	iinc	2, 1
   37:	iload_2
   38:	aload_0
   39:	arraylength
   40:	if_icmplt	25
   43:	aload_1
   44:	areturn
  LineNumberTable: 
   line 2477: 0
   line 2478: 4
   line 2479: 6
   line 2480: 11
   line 2482: 15
   line 2483: 20
   line 2484: 25
   line 2483: 34
   line 2486: 43

  LocalVariableTable: 
   Start  Length  Slot  Name   Signature
   0      45      0    array       [Ljava/lang/Byte;
   20      25      1    result       [B
   22      23      2    i       I


public static byte[] toPrimitive(java.lang.Byte[], byte);
  Code:
   Stack=3, Locals=5, Args_size=2
   0:	aload_0
   1:	ifnonnull	6
   4:	aconst_null
   5:	areturn
   6:	aload_0
   7:	arraylength
   8:	ifne	15
   11:	getstatic	#67; //Field EMPTY_BYTE_ARRAY:[B
   14:	areturn
   15:	aload_0
   16:	arraylength
   17:	newarray byte
   19:	astore_2
   20:	iconst_0
   21:	istore_3
   22:	goto	50
   25:	aload_0
   26:	iload_3
   27:	aaload
   28:	astore	4
   30:	aload_2
   31:	iload_3
   32:	aload	4
   34:	ifnonnull	41
   37:	iload_1
   38:	goto	46
   41:	aload	4
   43:	invokevirtual	#104; //Method java/lang/Byte.byteValue:()B
   46:	bastore
   47:	iinc	3, 1
   50:	iload_3
   51:	aload_0
   52:	arraylength
   53:	if_icmplt	25
   56:	aload_2
   57:	areturn
  LineNumberTable: 
   line 2499: 0
   line 2500: 4
   line 2501: 6
   line 2502: 11
   line 2504: 15
   line 2505: 20
   line 2506: 25
   line 2507: 30
   line 2505: 47
   line 2509: 56

  LocalVariableTable: 
   Start  Length  Slot  Name   Signature
   0      58      0    array       [Ljava/lang/Byte;
   0      58      1    valueForNull       B
   20      38      2    result       [B
   22      36      3    i       I
   30      20      4    b       Ljava/lang/Byte;


public static double[] toPrimitive(java.lang.Double[]);
  Code:
   Stack=4, Locals=3, Args_size=1
   0:	aload_0
   1:	ifnonnull	6
   4:	aconst_null
   5:	areturn
   6:	aload_0
   7:	arraylength
   8:	ifne	15
   11:	getstatic	#72; //Field EMPTY_DOUBLE_ARRAY:[D
   14:	areturn
   15:	aload_0
   16:	arraylength
   17:	newarray double
   19:	astore_1
   20:	iconst_0
   21:	istore_2
   22:	goto	37
   25:	aload_1
   26:	iload_2
   27:	aload_0
   28:	iload_2
   29:	aaload
   30:	invokevirtual	#118; //Method java/lang/Double.doubleValue:()D
   33:	dastore
   34:	iinc	2, 1
   37:	iload_2
   38:	aload_0
   39:	arraylength
   40:	if_icmplt	25
   43:	aload_1
   44:	areturn
  LineNumberTable: 
   line 2545: 0
   line 2546: 4
   line 2547: 6
   line 2548: 11
   line 2550: 15
   line 2551: 20
   line 2552: 25
   line 2551: 34
   line 2554: 43

  LocalVariableTable: 
   Start  Length  Slot  Name   Signature
   0      45      0    array       [Ljava/lang/Double;
   20      25      1    result       [D
   22      23      2    i       I


public static double[] toPrimitive(java.lang.Double[], double);
  Code:
   Stack=4, Locals=6, Args_size=2
   0:	aload_0
   1:	ifnonnull	6
   4:	aconst_null
   5:	areturn
   6:	aload_0
   7:	arraylength
   8:	ifne	15
   11:	getstatic	#72; //Field EMPTY_DOUBLE_ARRAY:[D
   14:	areturn
   15:	aload_0
   16:	arraylength
   17:	newarray double
   19:	astore_3
   20:	iconst_0
   21:	istore	4
   23:	goto	53
   26:	aload_0
   27:	iload	4
   29:	aaload
   30:	astore	5
   32:	aload_3
   33:	iload	4
   35:	aload	5
   37:	ifnonnull	44
   40:	dload_1
   41:	goto	49
   44:	aload	5
   46:	invokevirtual	#118; //Method java/lang/Double.doubleValue:()D
   49:	dastore
   50:	iinc	4, 1
   53:	iload	4
   55:	aload_0
   56:	arraylength
   57:	if_icmplt	26
   60:	aload_3
   61:	areturn
  LineNumberTable: 
   line 2567: 0
   line 2568: 4
   line 2569: 6
   line 2570: 11
   line 2572: 15
   line 2573: 20
   line 2574: 26
   line 2575: 32
   line 2573: 50
   line 2577: 60

  LocalVariableTable: 
   Start  Length  Slot  Name   Signature
   0      62      0    array       [Ljava/lang/Double;
   0      62      1    valueForNull       D
   20      42      3    result       [D
   23      39      4    i       I
   32      21      5    b       Ljava/lang/Double;


public static float[] toPrimitive(java.lang.Float[]);
  Code:
   Stack=4, Locals=3, Args_size=1
   0:	aload_0
   1:	ifnonnull	6
   4:	aconst_null
   5:	areturn
   6:	aload_0
   7:	arraylength
   8:	ifne	15
   11:	getstatic	#74; //Field EMPTY_FLOAT_ARRAY:[F
   14:	areturn
   15:	aload_0
   16:	arraylength
   17:	newarray float
   19:	astore_1
   20:	iconst_0
   21:	istore_2
   22:	goto	37
   25:	aload_1
   26:	iload_2
   27:	aload_0
   28:	iload_2
   29:	aaload
   30:	invokevirtual	#121; //Method java/lang/Float.floatValue:()F
   33:	fastore
   34:	iinc	2, 1
   37:	iload_2
   38:	aload_0
   39:	arraylength
   40:	if_icmplt	25
   43:	aload_1
   44:	areturn
  LineNumberTable: 
   line 2613: 0
   line 2614: 4
   line 2615: 6
   line 2616: 11
   line 2618: 15
   line 2619: 20
   line 2620: 25
   line 2619: 34
   line 2622: 43

  LocalVariableTable: 
   Start  Length  Slot  Name   Signature
   0      45      0    array       [Ljava/lang/Float;
   20      25      1    result       [F
   22      23      2    i       I


public static float[] toPrimitive(java.lang.Float[], float);
  Code:
   Stack=3, Locals=5, Args_size=2
   0:	aload_0
   1:	ifnonnull	6
   4:	aconst_null
   5:	areturn
   6:	aload_0
   7:	arraylength
   8:	ifne	15
   11:	getstatic	#74; //Field EMPTY_FLOAT_ARRAY:[F
   14:	areturn
   15:	aload_0
   16:	arraylength
   17:	newarray float
   19:	astore_2
   20:	iconst_0
   21:	istore_3
   22:	goto	50
   25:	aload_0
   26:	iload_3
   27:	aaload
   28:	astore	4
   30:	aload_2
   31:	iload_3
   32:	aload	4
   34:	ifnonnull	41
   37:	fload_1
   38:	goto	46
   41:	aload	4
   43:	invokevirtual	#121; //Method java/lang/Float.floatValue:()F
   46:	fastore
   47:	iinc	3, 1
   50:	iload_3
   51:	aload_0
   52:	arraylength
   53:	if_icmplt	25
   56:	aload_2
   57:	areturn
  LineNumberTable: 
   line 2635: 0
   line 2636: 4
   line 2637: 6
   line 2638: 11
   line 2640: 15
   line 2641: 20
   line 2642: 25
   line 2643: 30
   line 2641: 47
   line 2645: 56

  LocalVariableTable: 
   Start  Length  Slot  Name   Signature
   0      58      0    array       [Ljava/lang/Float;
   0      58      1    valueForNull       F
   20      38      2    result       [F
   22      36      3    i       I
   30      20      4    b       Ljava/lang/Float;


public static int[] toPrimitive(java.lang.Integer[]);
  Code:
   Stack=4, Locals=3, Args_size=1
   0:	aload_0
   1:	ifnonnull	6
   4:	aconst_null
   5:	areturn
   6:	aload_0
   7:	arraylength
   8:	ifne	15
   11:	getstatic	#77; //Field EMPTY_INT_ARRAY:[I
   14:	areturn
   15:	aload_0
   16:	arraylength
   17:	newarray int
   19:	astore_1
   20:	iconst_0
   21:	istore_2
   22:	goto	37
   25:	aload_1
   26:	iload_2
   27:	aload_0
   28:	iload_2
   29:	aaload
   30:	invokevirtual	#150; //Method java/lang/Integer.intValue:()I
   33:	iastore
   34:	iinc	2, 1
   37:	iload_2
   38:	aload_0
   39:	arraylength
   40:	if_icmplt	25
   43:	aload_1
   44:	areturn
  LineNumberTable: 
   line 2341: 0
   line 2342: 4
   line 2343: 6
   line 2344: 11
   line 2346: 15
   line 2347: 20
   line 2348: 25
   line 2347: 34
   line 2350: 43

  LocalVariableTable: 
   Start  Length  Slot  Name   Signature
   0      45      0    array       [Ljava/lang/Integer;
   20      25      1    result       [I
   22      23      2    i       I


public static int[] toPrimitive(java.lang.Integer[], int);
  Code:
   Stack=3, Locals=5, Args_size=2
   0:	aload_0
   1:	ifnonnull	6
   4:	aconst_null
   5:	areturn
   6:	aload_0
   7:	arraylength
   8:	ifne	15
   11:	getstatic	#77; //Field EMPTY_INT_ARRAY:[I
   14:	areturn
   15:	aload_0
   16:	arraylength
   17:	newarray int
   19:	astore_2
   20:	iconst_0
   21:	istore_3
   22:	goto	50
   25:	aload_0
   26:	iload_3
   27:	aaload
   28:	astore	4
   30:	aload_2
   31:	iload_3
   32:	aload	4
   34:	ifnonnull	41
   37:	iload_1
   38:	goto	46
   41:	aload	4
   43:	invokevirtual	#150; //Method java/lang/Integer.intValue:()I
   46:	iastore
   47:	iinc	3, 1
   50:	iload_3
   51:	aload_0
   52:	arraylength
   53:	if_icmplt	25
   56:	aload_2
   57:	areturn
  LineNumberTable: 
   line 2363: 0
   line 2364: 4
   line 2365: 6
   line 2366: 11
   line 2368: 15
   line 2369: 20
   line 2370: 25
   line 2371: 30
   line 2369: 47
   line 2373: 56

  LocalVariableTable: 
   Start  Length  Slot  Name   Signature
   0      58      0    array       [Ljava/lang/Integer;
   0      58      1    valueForNull       I
   20      38      2    result       [I
   22      36      3    i       I
   30      20      4    b       Ljava/lang/Integer;


public static long[] toPrimitive(java.lang.Long[]);
  Code:
   Stack=4, Locals=3, Args_size=1
   0:	aload_0
   1:	ifnonnull	6
   4:	aconst_null
   5:	areturn
   6:	aload_0
   7:	arraylength
   8:	ifne	15
   11:	getstatic	#78; //Field EMPTY_LONG_ARRAY:[J
   14:	areturn
   15:	aload_0
   16:	arraylength
   17:	newarray long
   19:	astore_1
   20:	iconst_0
   21:	istore_2
   22:	goto	37
   25:	aload_1
   26:	iload_2
   27:	aload_0
   28:	iload_2
   29:	aaload
   30:	invokevirtual	#165; //Method java/lang/Long.longValue:()J
   33:	lastore
   34:	iinc	2, 1
   37:	iload_2
   38:	aload_0
   39:	arraylength
   40:	if_icmplt	25
   43:	aload_1
   44:	areturn
  LineNumberTable: 
   line 2273: 0
   line 2274: 4
   line 2275: 6
   line 2276: 11
   line 2278: 15
   line 2279: 20
   line 2280: 25
   line 2279: 34
   line 2282: 43

  LocalVariableTable: 
   Start  Length  Slot  Name   Signature
   0      45      0    array       [Ljava/lang/Long;
   20      25      1    result       [J
   22      23      2    i       I


public static long[] toPrimitive(java.lang.Long[], long);
  Code:
   Stack=4, Locals=6, Args_size=2
   0:	aload_0
   1:	ifnonnull	6
   4:	aconst_null
   5:	areturn
   6:	aload_0
   7:	arraylength
   8:	ifne	15
   11:	getstatic	#78; //Field EMPTY_LONG_ARRAY:[J
   14:	areturn
   15:	aload_0
   16:	arraylength
   17:	newarray long
   19:	astore_3
   20:	iconst_0
   21:	istore	4
   23:	goto	53
   26:	aload_0
   27:	iload	4
   29:	aaload
   30:	astore	5
   32:	aload_3
   33:	iload	4
   35:	aload	5
   37:	ifnonnull	44
   40:	lload_1
   41:	goto	49
   44:	aload	5
   46:	invokevirtual	#165; //Method java/lang/Long.longValue:()J
   49:	lastore
   50:	iinc	4, 1
   53:	iload	4
   55:	aload_0
   56:	arraylength
   57:	if_icmplt	26
   60:	aload_3
   61:	areturn
  LineNumberTable: 
   line 2295: 0
   line 2296: 4
   line 2297: 6
   line 2298: 11
   line 2300: 15
   line 2301: 20
   line 2302: 26
   line 2303: 32
   line 2301: 50
   line 2305: 60

  LocalVariableTable: 
   Start  Length  Slot  Name   Signature
   0      62      0    array       [Ljava/lang/Long;
   0      62      1    valueForNull       J
   20      42      3    result       [J
   23      39      4    i       I
   32      21      5    b       Ljava/lang/Long;


public static short[] toPrimitive(java.lang.Short[]);
  Code:
   Stack=4, Locals=3, Args_size=1
   0:	aload_0
   1:	ifnonnull	6
   4:	aconst_null
   5:	areturn
   6:	aload_0
   7:	arraylength
   8:	ifne	15
   11:	getstatic	#81; //Field EMPTY_SHORT_ARRAY:[S
   14:	areturn
   15:	aload_0
   16:	arraylength
   17:	newarray short
   19:	astore_1
   20:	iconst_0
   21:	istore_2
   22:	goto	37
   25:	aload_1
   26:	iload_2
   27:	aload_0
   28:	iload_2
   29:	aaload
   30:	invokevirtual	#179; //Method java/lang/Short.shortValue:()S
   33:	sastore
   34:	iinc	2, 1
   37:	iload_2
   38:	aload_0
   39:	arraylength
   40:	if_icmplt	25
   43:	aload_1
   44:	areturn
  LineNumberTable: 
   line 2409: 0
   line 2410: 4
   line 2411: 6
   line 2412: 11
   line 2414: 15
   line 2415: 20
   line 2416: 25
   line 2415: 34
   line 2418: 43

  LocalVariableTable: 
   Start  Length  Slot  Name   Signature
   0      45      0    array       [Ljava/lang/Short;
   20      25      1    result       [S
   22      23      2    i       I


public static short[] toPrimitive(java.lang.Short[], short);
  Code:
   Stack=3, Locals=5, Args_size=2
   0:	aload_0
   1:	ifnonnull	6
   4:	aconst_null
   5:	areturn
   6:	aload_0
   7:	arraylength
   8:	ifne	15
   11:	getstatic	#81; //Field EMPTY_SHORT_ARRAY:[S
   14:	areturn
   15:	aload_0
   16:	arraylength
   17:	newarray short
   19:	astore_2
   20:	iconst_0
   21:	istore_3
   22:	goto	50
   25:	aload_0
   26:	iload_3
   27:	aaload
   28:	astore	4
   30:	aload_2
   31:	iload_3
   32:	aload	4
   34:	ifnonnull	41
   37:	iload_1
   38:	goto	46
   41:	aload	4
   43:	invokevirtual	#179; //Method java/lang/Short.shortValue:()S
   46:	sastore
   47:	iinc	3, 1
   50:	iload_3
   51:	aload_0
   52:	arraylength
   53:	if_icmplt	25
   56:	aload_2
   57:	areturn
  LineNumberTable: 
   line 2431: 0
   line 2432: 4
   line 2433: 6
   line 2434: 11
   line 2436: 15
   line 2437: 20
   line 2438: 25
   line 2439: 30
   line 2437: 47
   line 2441: 56

  LocalVariableTable: 
   Start  Length  Slot  Name   Signature
   0      58      0    array       [Ljava/lang/Short;
   0      58      1    valueForNull       S
   20      38      2    result       [S
   22      36      3    i       I
   30      20      4    b       Ljava/lang/Short;


public static java.lang.String toString(java.lang.Object);
  Code:
   Stack=2, Locals=1, Args_size=1
   0:	aload_0
   1:	ldc	#11; //String {}
   3:	invokestatic	#183; //Method toString:(Ljava/lang/Object;Ljava/lang/String;)Ljava/lang/String;
   6:	areturn
  LineNumberTable: 
   line 152: 0

  LocalVariableTable: 
   Start  Length  Slot  Name   Signature
   0      7      0    array       Ljava/lang/Object;


public static java.lang.String toString(java.lang.Object, java.lang.String);
  Code:
   Stack=4, Locals=2, Args_size=2
   0:	aload_0
   1:	ifnonnull	6
   4:	aload_1
   5:	areturn
   6:	new	#46; //class org/apache/commons/lang/builder/ToStringBuilder
   9:	dup
   10:	aload_0
   11:	getstatic	#85; //Field org/apache/commons/lang/builder/ToStringStyle.SIMPLE_STYLE:Lorg/apache/commons/lang/builder/ToStringStyle;
   14:	invokespecial	#58; //Method org/apache/commons/lang/builder/ToStringBuilder."<init>":(Ljava/lang/Object;Lorg/apache/commons/lang/builder/ToStringStyle;)V
   17:	aload_0
   18:	invokevirtual	#99; //Method org/apache/commons/lang/builder/ToStringBuilder.append:(Ljava/lang/Object;)Lorg/apache/commons/lang/builder/ToStringBuilder;
   21:	invokevirtual	#182; //Method org/apache/commons/lang/builder/ToStringBuilder.toString:()Ljava/lang/String;
   24:	areturn
  LineNumberTable: 
   line 168: 0
   line 169: 4
   line 171: 6

  LocalVariableTable: 
   Start  Length  Slot  Name   Signature
   0      25      0    array       Ljava/lang/Object;
   0      25      1    stringIfNull       Ljava/lang/String;


}

