Compiled from "DurationFormatUtils.java"
public class org.apache.commons.lang.time.DurationFormatUtils extends java.lang.Object
  SourceFile: "DurationFormatUtils.java"
  InnerClass: 
   #198= #37 of #36; //Token=class org/apache/commons/lang/time/DurationFormatUtils$Token of class org/apache/commons/lang/time/DurationFormatUtils
  minor version: 3
  major version: 45
  Constant pool:
const #1 = String	#126;	//  
const #2 = String	#127;	//   
const #3 = String	#128;	//   0 days
const #4 = String	#129;	//   0 hours
const #5 = String	#130;	//   0 minutes
const #6 = String	#131;	//   0 seconds
const #7 = String	#132;	//  'P'yyyy'Y'M'M'd'DT'H'H'm'M's.S'S'
const #8 = String	#165;	//  1 day
const #9 = String	#166;	//  1 days
const #10 = String	#167;	//  1 hour
const #11 = String	#168;	//  1 hours
const #12 = String	#169;	//  1 minute
const #13 = String	#170;	//  1 minutes
const #14 = String	#171;	//  1 second
const #15 = String	#172;	//  1 seconds
const #16 = String	#179;	//  H
const #17 = String	#180;	//  H:mm:ss.SSS
const #18 = String	#195;	//  M
const #19 = String	#196;	//  S
const #20 = String	#209;	//  d
const #21 = String	#210;	//  d' days 'H' hours 'm' minutes 's' seconds'
const #22 = String	#248;	//  m
const #23 = String	#262;	//  s
const #24 = String	#282;	//  y
const #25 = class	#201;	//  "[Lorg/apache/commons/lang/time/DurationFormatUtils$Token;"
const #26 = class	#235;	//  java/lang/Integer
const #27 = class	#236;	//  java/lang/Object
const #28 = class	#237;	//  java/lang/String
const #29 = class	#238;	//  java/lang/StringBuffer
const #30 = class	#239;	//  java/util/ArrayList
const #31 = class	#240;	//  java/util/Calendar
const #32 = class	#241;	//  java/util/Date
const #33 = class	#242;	//  java/util/TimeZone
const #34 = class	#254;	//  org/apache/commons/lang/StringUtils
const #35 = class	#255;	//  org/apache/commons/lang/time/DateUtils
const #36 = class	#256;	//  org/apache/commons/lang/time/DurationFormatUtils
const #37 = class	#257;	//  org/apache/commons/lang/time/DurationFormatUtils$Token
const #38 = Method	#27.#88;	//  java/lang/Object."<init>":()V
const #39 = Method	#29.#88;	//  java/lang/StringBuffer."<init>":()V
const #40 = Method	#30.#89;	//  java/util/ArrayList."<init>":(I)V
const #41 = Method	#32.#90;	//  java/util/Date."<init>":(J)V
const #42 = Method	#37.#91;	//  org/apache/commons/lang/time/DurationFormatUtils$Token."<init>":(Ljava/lang/Object;)V
const #43 = Method	#29.#92;	//  java/lang/StringBuffer."<init>":(Ljava/lang/String;)V
const #44 = Field	#36.#93;	//  org/apache/commons/lang/time/DurationFormatUtils.H:Ljava/lang/Object;
const #45 = Field	#36.#94;	//  org/apache/commons/lang/time/DurationFormatUtils.M:Ljava/lang/Object;
const #46 = Field	#36.#95;	//  org/apache/commons/lang/time/DurationFormatUtils.S:Ljava/lang/Object;
const #47 = Method	#31.#96;	//  java/util/Calendar.add:(II)V
const #48 = Method	#30.#97;	//  java/util/ArrayList.add:(Ljava/lang/Object;)Z
const #49 = Method	#29.#98;	//  java/lang/StringBuffer.append:(C)Ljava/lang/StringBuffer;
const #50 = Method	#29.#99;	//  java/lang/StringBuffer.append:(Ljava/lang/String;)Ljava/lang/StringBuffer;
const #51 = Method	#37.#100;	//  org/apache/commons/lang/time/DurationFormatUtils$Token.containsTokenWithValue:([Lorg/apache/commons/lang/time/DurationFormatUtils$Token;Ljava/lang/Object;)Z
const #52 = Field	#36.#101;	//  org/apache/commons/lang/time/DurationFormatUtils.d:Ljava/lang/Object;
const #53 = Method	#36.#102;	//  org/apache/commons/lang/time/DurationFormatUtils.format:([Lorg/apache/commons/lang/time/DurationFormatUtils$Token;IIIIIIIZ)Ljava/lang/String;
const #54 = Method	#36.#103;	//  org/apache/commons/lang/time/DurationFormatUtils.formatDuration:(JLjava/lang/String;)Ljava/lang/String;
const #55 = Method	#36.#104;	//  org/apache/commons/lang/time/DurationFormatUtils.formatDuration:(JLjava/lang/String;Z)Ljava/lang/String;
const #56 = Method	#36.#105;	//  org/apache/commons/lang/time/DurationFormatUtils.formatPeriod:(JJLjava/lang/String;ZLjava/util/TimeZone;)Ljava/lang/String;
const #57 = Method	#31.#106;	//  java/util/Calendar.get:(I)I
const #58 = Method	#37.#107;	//  org/apache/commons/lang/time/DurationFormatUtils$Token.getCount:()I
const #59 = Method	#33.#108;	//  java/util/TimeZone.getDefault:()Ljava/util/TimeZone;
const #60 = Method	#31.#109;	//  java/util/Calendar.getInstance:(Ljava/util/TimeZone;)Ljava/util/Calendar;
const #61 = Method	#37.#110;	//  org/apache/commons/lang/time/DurationFormatUtils$Token.getValue:()Ljava/lang/Object;
const #62 = Method	#37.#111;	//  org/apache/commons/lang/time/DurationFormatUtils$Token.increment:()V
const #63 = Method	#34.#112;	//  org/apache/commons/lang/StringUtils.leftPad:(Ljava/lang/String;IC)Ljava/lang/String;
const #64 = Method	#28.#113;	//  java/lang/String.length:()I
const #65 = Method	#36.#114;	//  org/apache/commons/lang/time/DurationFormatUtils.lexx:(Ljava/lang/String;)[Lorg/apache/commons/lang/time/DurationFormatUtils$Token;
const #66 = Field	#36.#115;	//  org/apache/commons/lang/time/DurationFormatUtils.m:Ljava/lang/Object;
const #67 = Method	#36.#116;	//  org/apache/commons/lang/time/DurationFormatUtils.reduceAndCorrect:(Ljava/util/Calendar;Ljava/util/Calendar;II)I
const #68 = Method	#34.#117;	//  org/apache/commons/lang/StringUtils.replaceOnce:(Ljava/lang/String;Ljava/lang/String;Ljava/lang/String;)Ljava/lang/String;
const #69 = Field	#36.#118;	//  org/apache/commons/lang/time/DurationFormatUtils.s:Ljava/lang/Object;
const #70 = Method	#31.#119;	//  java/util/Calendar.setTime:(Ljava/util/Date;)V
const #71 = Method	#28.#120;	//  java/lang/String.substring:(I)Ljava/lang/String;
const #72 = Method	#30.#121;	//  java/util/ArrayList.toArray:([Ljava/lang/Object;)[Ljava/lang/Object;
const #73 = Method	#28.#122;	//  java/lang/String.toCharArray:()[C
const #74 = Method	#27.#123;	//  java/lang/Object.toString:()Ljava/lang/String;
const #75 = Method	#29.#123;	//  java/lang/StringBuffer.toString:()Ljava/lang/String;
const #76 = Method	#26.#124;	//  java/lang/Integer.toString:(I)Ljava/lang/String;
const #77 = Field	#36.#125;	//  org/apache/commons/lang/time/DurationFormatUtils.y:Ljava/lang/Object;
const #78 = long	1000l;
const #80 = long	60000l;
const #82 = long	3600000l;
const #84 = long	86400000l;
const #86 = long	2419200000l;
const #88 = NameAndType	#174:#137;//  "<init>":()V
const #89 = NameAndType	#174:#142;//  "<init>":(I)V
const #90 = NameAndType	#174:#145;//  "<init>":(J)V
const #91 = NameAndType	#174:#152;//  "<init>":(Ljava/lang/Object;)V
const #92 = NameAndType	#174:#155;//  "<init>":(Ljava/lang/String;)V
const #93 = NameAndType	#179:#186;//  H:Ljava/lang/Object;
const #94 = NameAndType	#195:#186;//  M:Ljava/lang/Object;
const #95 = NameAndType	#196:#186;//  S:Ljava/lang/Object;
const #96 = NameAndType	#202:#143;//  add:(II)V
const #97 = NameAndType	#202:#153;//  add:(Ljava/lang/Object;)Z
const #98 = NameAndType	#203:#139;//  append:(C)Ljava/lang/StringBuffer;
const #99 = NameAndType	#203:#154;//  append:(Ljava/lang/String;)Ljava/lang/StringBuffer;
const #100 = NameAndType	#207:#164;//  containsTokenWithValue:([Lorg/apache/commons/lang/time/DurationFormatUtils$Token;Ljava/lang/Object;)Z
const #101 = NameAndType	#209:#186;//  d:Ljava/lang/Object;
const #102 = NameAndType	#219:#163;//  format:([Lorg/apache/commons/lang/time/DurationFormatUtils$Token;IIIIIIIZ)Ljava/lang/String;
const #103 = NameAndType	#220:#149;//  formatDuration:(JLjava/lang/String;)Ljava/lang/String;
const #104 = NameAndType	#220:#150;//  formatDuration:(JLjava/lang/String;Z)Ljava/lang/String;
const #105 = NameAndType	#224:#148;//  formatPeriod:(JJLjava/lang/String;ZLjava/util/TimeZone;)Ljava/lang/String;
const #106 = NameAndType	#226:#140;//  get:(I)I
const #107 = NameAndType	#227:#133;//  getCount:()I
const #108 = NameAndType	#228:#136;//  getDefault:()Ljava/util/TimeZone;
const #109 = NameAndType	#229:#161;//  getInstance:(Ljava/util/TimeZone;)Ljava/util/Calendar;
const #110 = NameAndType	#230:#134;//  getValue:()Ljava/lang/Object;
const #111 = NameAndType	#234:#137;//  increment:()V
const #112 = NameAndType	#244:#157;//  leftPad:(Ljava/lang/String;IC)Ljava/lang/String;
const #113 = NameAndType	#245:#133;//  length:()I
const #114 = NameAndType	#246:#156;//  lexx:(Ljava/lang/String;)[Lorg/apache/commons/lang/time/DurationFormatUtils$Token;
const #115 = NameAndType	#248:#186;//  m:Ljava/lang/Object;
const #116 = NameAndType	#260:#159;//  reduceAndCorrect:(Ljava/util/Calendar;Ljava/util/Calendar;II)I
const #117 = NameAndType	#261:#158;//  replaceOnce:(Ljava/lang/String;Ljava/lang/String;Ljava/lang/String;)Ljava/lang/String;
const #118 = NameAndType	#262:#186;//  s:Ljava/lang/Object;
const #119 = NameAndType	#264:#160;//  setTime:(Ljava/util/Date;)V
const #120 = NameAndType	#269:#141;//  substring:(I)Ljava/lang/String;
const #121 = NameAndType	#276:#162;//  toArray:([Ljava/lang/Object;)[Ljava/lang/Object;
const #122 = NameAndType	#277:#138;//  toCharArray:()[C
const #123 = NameAndType	#278:#135;//  toString:()Ljava/lang/String;
const #124 = NameAndType	#278:#141;//  toString:(I)Ljava/lang/String;
const #125 = NameAndType	#282:#186;//  y:Ljava/lang/Object;
const #126 = Asciz	;
const #127 = Asciz	 ;
const #128 = Asciz	 0 days;
const #129 = Asciz	 0 hours;
const #130 = Asciz	 0 minutes;
const #131 = Asciz	 0 seconds;
const #132 = Asciz	'P'yyyy'Y'M'M'd'DT'H'H'm'M's.S'S';
const #133 = Asciz	()I;
const #134 = Asciz	()Ljava/lang/Object;;
const #135 = Asciz	()Ljava/lang/String;;
const #136 = Asciz	()Ljava/util/TimeZone;;
const #137 = Asciz	()V;
const #138 = Asciz	()[C;
const #139 = Asciz	(C)Ljava/lang/StringBuffer;;
const #140 = Asciz	(I)I;
const #141 = Asciz	(I)Ljava/lang/String;;
const #142 = Asciz	(I)V;
const #143 = Asciz	(II)V;
const #144 = Asciz	(J)Ljava/lang/String;;
const #145 = Asciz	(J)V;
const #146 = Asciz	(JJ)Ljava/lang/String;;
const #147 = Asciz	(JJLjava/lang/String;)Ljava/lang/String;;
const #148 = Asciz	(JJLjava/lang/String;ZLjava/util/TimeZone;)Ljava/lang/String;;
const #149 = Asciz	(JLjava/lang/String;)Ljava/lang/String;;
const #150 = Asciz	(JLjava/lang/String;Z)Ljava/lang/String;;
const #151 = Asciz	(JZZ)Ljava/lang/String;;
const #152 = Asciz	(Ljava/lang/Object;)V;
const #153 = Asciz	(Ljava/lang/Object;)Z;
const #154 = Asciz	(Ljava/lang/String;)Ljava/lang/StringBuffer;;
const #155 = Asciz	(Ljava/lang/String;)V;
const #156 = Asciz	(Ljava/lang/String;)[Lorg/apache/commons/lang/time/DurationFormatUtils$Token;;
const #157 = Asciz	(Ljava/lang/String;IC)Ljava/lang/String;;
const #158 = Asciz	(Ljava/lang/String;Ljava/lang/String;Ljava/lang/String;)Ljava/lang/String;;
const #159 = Asciz	(Ljava/util/Calendar;Ljava/util/Calendar;II)I;
const #160 = Asciz	(Ljava/util/Date;)V;
const #161 = Asciz	(Ljava/util/TimeZone;)Ljava/util/Calendar;;
const #162 = Asciz	([Ljava/lang/Object;)[Ljava/lang/Object;;
const #163 = Asciz	([Lorg/apache/commons/lang/time/DurationFormatUtils$Token;IIIIIIIZ)Ljava/lang/String;;
const #164 = Asciz	([Lorg/apache/commons/lang/time/DurationFormatUtils$Token;Ljava/lang/Object;)Z;
const #165 = Asciz	1 day;
const #166 = Asciz	1 days;
const #167 = Asciz	1 hour;
const #168 = Asciz	1 hours;
const #169 = Asciz	1 minute;
const #170 = Asciz	1 minutes;
const #171 = Asciz	1 second;
const #172 = Asciz	1 seconds;
const #173 = Asciz	<clinit>;
const #174 = Asciz	<init>;
const #175 = Asciz	C;
const #176 = Asciz	Code;
const #177 = Asciz	ConstantValue;
const #178 = Asciz	DurationFormatUtils.java;
const #179 = Asciz	H;
const #180 = Asciz	H:mm:ss.SSS;
const #181 = Asciz	I;
const #182 = Asciz	ISO_EXTENDED_FORMAT_PATTERN;
const #183 = Asciz	InnerClasses;
const #184 = Asciz	J;
const #185 = Asciz	LineNumberTable;
const #186 = Asciz	Ljava/lang/Object;;
const #187 = Asciz	Ljava/lang/String;;
const #188 = Asciz	Ljava/lang/StringBuffer;;
const #189 = Asciz	Ljava/util/ArrayList;;
const #190 = Asciz	Ljava/util/Calendar;;
const #191 = Asciz	Ljava/util/TimeZone;;
const #192 = Asciz	LocalVariableTable;
const #193 = Asciz	Lorg/apache/commons/lang/time/DurationFormatUtils$Token;;
const #194 = Asciz	Lorg/apache/commons/lang/time/DurationFormatUtils;;
const #195 = Asciz	M;
const #196 = Asciz	S;
const #197 = Asciz	SourceFile;
const #198 = Asciz	Token;
const #199 = Asciz	Z;
const #200 = Asciz	[C;
const #201 = Asciz	[Lorg/apache/commons/lang/time/DurationFormatUtils$Token;;
const #202 = Asciz	add;
const #203 = Asciz	append;
const #204 = Asciz	array;
const #205 = Asciz	buffer;
const #206 = Asciz	ch;
const #207 = Asciz	containsTokenWithValue;
const #208 = Asciz	count;
const #209 = Asciz	d;
const #210 = Asciz	d' days 'H' hours 'm' minutes 's' seconds';
const #211 = Asciz	days;
const #212 = Asciz	difference;
const #213 = Asciz	duration;
const #214 = Asciz	durationMillis;
const #215 = Asciz	end;
const #216 = Asciz	endMillis;
const #217 = Asciz	endValue;
const #218 = Asciz	field;
const #219 = Asciz	format;
const #220 = Asciz	formatDuration;
const #221 = Asciz	formatDurationHMS;
const #222 = Asciz	formatDurationISO;
const #223 = Asciz	formatDurationWords;
const #224 = Asciz	formatPeriod;
const #225 = Asciz	formatPeriodISO;
const #226 = Asciz	get;
const #227 = Asciz	getCount;
const #228 = Asciz	getDefault;
const #229 = Asciz	getInstance;
const #230 = Asciz	getValue;
const #231 = Asciz	hours;
const #232 = Asciz	i;
const #233 = Asciz	inLiteral;
const #234 = Asciz	increment;
const #235 = Asciz	java/lang/Integer;
const #236 = Asciz	java/lang/Object;
const #237 = Asciz	java/lang/String;
const #238 = Asciz	java/lang/StringBuffer;
const #239 = Asciz	java/util/ArrayList;
const #240 = Asciz	java/util/Calendar;
const #241 = Asciz	java/util/Date;
const #242 = Asciz	java/util/TimeZone;
const #243 = Asciz	lastOutputSeconds;
const #244 = Asciz	leftPad;
const #245 = Asciz	length;
const #246 = Asciz	lexx;
const #247 = Asciz	list;
const #248 = Asciz	m;
const #249 = Asciz	millis;
const #250 = Asciz	milliseconds;
const #251 = Asciz	minutes;
const #252 = Asciz	months;
const #253 = Asciz	newdiff;
const #254 = Asciz	org/apache/commons/lang/StringUtils;
const #255 = Asciz	org/apache/commons/lang/time/DateUtils;
const #256 = Asciz	org/apache/commons/lang/time/DurationFormatUtils;
const #257 = Asciz	org/apache/commons/lang/time/DurationFormatUtils$Token;
const #258 = Asciz	padWithZeros;
const #259 = Asciz	previous;
const #260 = Asciz	reduceAndCorrect;
const #261 = Asciz	replaceOnce;
const #262 = Asciz	s;
const #263 = Asciz	seconds;
const #264 = Asciz	setTime;
const #265 = Asciz	start;
const #266 = Asciz	startMillis;
const #267 = Asciz	startValue;
const #268 = Asciz	str;
const #269 = Asciz	substring;
const #270 = Asciz	suppressLeadingZeroElements;
const #271 = Asciz	suppressTrailingZeroElements;
const #272 = Asciz	sz;
const #273 = Asciz	this;
const #274 = Asciz	timezone;
const #275 = Asciz	tmp;
const #276 = Asciz	toArray;
const #277 = Asciz	toCharArray;
const #278 = Asciz	toString;
const #279 = Asciz	token;
const #280 = Asciz	tokens;
const #281 = Asciz	value;
const #282 = Asciz	y;
const #283 = Asciz	years;

{
public static final java.lang.String ISO_EXTENDED_FORMAT_PATTERN;
  Constant value: String 'P'yyyy'Y'M'M'd'DT'H'H'm'M's.S'S'
static final java.lang.Object y;

static final java.lang.Object M;

static final java.lang.Object d;

static final java.lang.Object H;

static final java.lang.Object m;

static final java.lang.Object s;

static final java.lang.Object S;

static {};
  Code:
   Stack=1, Locals=0, Args_size=0
   0:	ldc	#24; //String y
   2:	putstatic	#77; //Field y:Ljava/lang/Object;
   5:	ldc	#18; //String M
   7:	putstatic	#45; //Field M:Ljava/lang/Object;
   10:	ldc	#20; //String d
   12:	putstatic	#52; //Field d:Ljava/lang/Object;
   15:	ldc	#16; //String H
   17:	putstatic	#44; //Field H:Ljava/lang/Object;
   20:	ldc	#22; //String m
   22:	putstatic	#66; //Field m:Ljava/lang/Object;
   25:	ldc	#23; //String s
   27:	putstatic	#69; //Field s:Ljava/lang/Object;
   30:	ldc	#19; //String S
   32:	putstatic	#46; //Field S:Ljava/lang/Object;
   35:	return
  LineNumberTable: 
   line 450: 0
   line 451: 5
   line 452: 10
   line 453: 15
   line 454: 20
   line 455: 25
   line 456: 30
   line 47: 35



public org.apache.commons.lang.time.DurationFormatUtils();
  Code:
   Stack=1, Locals=1, Args_size=1
   0:	aload_0
   1:	invokespecial	#38; //Method java/lang/Object."<init>":()V
   4:	return
  LineNumberTable: 
   line 56: 0
   line 55: 4

  LocalVariableTable: 
   Start  Length  Slot  Name   Signature
   0      5      0    this       Lorg/apache/commons/lang/time/DurationFormatUtils;


static java.lang.String format(org.apache.commons.lang.time.DurationFormatUtils$Token[], int, int, int, int, int, int, int, boolean);
  Code:
   Stack=4, Locals=17, Args_size=9
   0:	new	#29; //class java/lang/StringBuffer
   3:	dup
   4:	invokespecial	#39; //Method java/lang/StringBuffer."<init>":()V
   7:	astore	9
   9:	iconst_0
   10:	istore	10
   12:	aload_0
   13:	arraylength
   14:	istore	11
   16:	iconst_0
   17:	istore	12
   19:	goto	419
   22:	aload_0
   23:	iload	12
   25:	aaload
   26:	astore	13
   28:	aload	13
   30:	invokevirtual	#61; //Method org/apache/commons/lang/time/DurationFormatUtils$Token.getValue:()Ljava/lang/Object;
   33:	astore	14
   35:	aload	13
   37:	invokevirtual	#58; //Method org/apache/commons/lang/time/DurationFormatUtils$Token.getCount:()I
   40:	istore	15
   42:	aload	14
   44:	instanceof	#29; //class java/lang/StringBuffer
   47:	ifeq	64
   50:	aload	9
   52:	aload	14
   54:	invokevirtual	#74; //Method java/lang/Object.toString:()Ljava/lang/String;
   57:	invokevirtual	#50; //Method java/lang/StringBuffer.append:(Ljava/lang/String;)Ljava/lang/StringBuffer;
   60:	pop
   61:	goto	416
   64:	aload	14
   66:	ldc	#24; //String y
   68:	if_acmpne	106
   71:	aload	9
   73:	iload	8
   75:	ifeq	92
   78:	iload_1
   79:	invokestatic	#76; //Method java/lang/Integer.toString:(I)Ljava/lang/String;
   82:	iload	15
   84:	bipush	48
   86:	invokestatic	#63; //Method org/apache/commons/lang/StringUtils.leftPad:(Ljava/lang/String;IC)Ljava/lang/String;
   89:	goto	96
   92:	iload_1
   93:	invokestatic	#76; //Method java/lang/Integer.toString:(I)Ljava/lang/String;
   96:	invokevirtual	#50; //Method java/lang/StringBuffer.append:(Ljava/lang/String;)Ljava/lang/StringBuffer;
   99:	pop
   100:	iconst_0
   101:	istore	10
   103:	goto	416
   106:	aload	14
   108:	ldc	#18; //String M
   110:	if_acmpne	148
   113:	aload	9
   115:	iload	8
   117:	ifeq	134
   120:	iload_2
   121:	invokestatic	#76; //Method java/lang/Integer.toString:(I)Ljava/lang/String;
   124:	iload	15
   126:	bipush	48
   128:	invokestatic	#63; //Method org/apache/commons/lang/StringUtils.leftPad:(Ljava/lang/String;IC)Ljava/lang/String;
   131:	goto	138
   134:	iload_2
   135:	invokestatic	#76; //Method java/lang/Integer.toString:(I)Ljava/lang/String;
   138:	invokevirtual	#50; //Method java/lang/StringBuffer.append:(Ljava/lang/String;)Ljava/lang/StringBuffer;
   141:	pop
   142:	iconst_0
   143:	istore	10
   145:	goto	416
   148:	aload	14
   150:	ldc	#20; //String d
   152:	if_acmpne	190
   155:	aload	9
   157:	iload	8
   159:	ifeq	176
   162:	iload_3
   163:	invokestatic	#76; //Method java/lang/Integer.toString:(I)Ljava/lang/String;
   166:	iload	15
   168:	bipush	48
   170:	invokestatic	#63; //Method org/apache/commons/lang/StringUtils.leftPad:(Ljava/lang/String;IC)Ljava/lang/String;
   173:	goto	180
   176:	iload_3
   177:	invokestatic	#76; //Method java/lang/Integer.toString:(I)Ljava/lang/String;
   180:	invokevirtual	#50; //Method java/lang/StringBuffer.append:(Ljava/lang/String;)Ljava/lang/StringBuffer;
   183:	pop
   184:	iconst_0
   185:	istore	10
   187:	goto	416
   190:	aload	14
   192:	ldc	#16; //String H
   194:	if_acmpne	234
   197:	aload	9
   199:	iload	8
   201:	ifeq	219
   204:	iload	4
   206:	invokestatic	#76; //Method java/lang/Integer.toString:(I)Ljava/lang/String;
   209:	iload	15
   211:	bipush	48
   213:	invokestatic	#63; //Method org/apache/commons/lang/StringUtils.leftPad:(Ljava/lang/String;IC)Ljava/lang/String;
   216:	goto	224
   219:	iload	4
   221:	invokestatic	#76; //Method java/lang/Integer.toString:(I)Ljava/lang/String;
   224:	invokevirtual	#50; //Method java/lang/StringBuffer.append:(Ljava/lang/String;)Ljava/lang/StringBuffer;
   227:	pop
   228:	iconst_0
   229:	istore	10
   231:	goto	416
   234:	aload	14
   236:	ldc	#22; //String m
   238:	if_acmpne	278
   241:	aload	9
   243:	iload	8
   245:	ifeq	263
   248:	iload	5
   250:	invokestatic	#76; //Method java/lang/Integer.toString:(I)Ljava/lang/String;
   253:	iload	15
   255:	bipush	48
   257:	invokestatic	#63; //Method org/apache/commons/lang/StringUtils.leftPad:(Ljava/lang/String;IC)Ljava/lang/String;
   260:	goto	268
   263:	iload	5
   265:	invokestatic	#76; //Method java/lang/Integer.toString:(I)Ljava/lang/String;
   268:	invokevirtual	#50; //Method java/lang/StringBuffer.append:(Ljava/lang/String;)Ljava/lang/StringBuffer;
   271:	pop
   272:	iconst_0
   273:	istore	10
   275:	goto	416
   278:	aload	14
   280:	ldc	#23; //String s
   282:	if_acmpne	322
   285:	aload	9
   287:	iload	8
   289:	ifeq	307
   292:	iload	6
   294:	invokestatic	#76; //Method java/lang/Integer.toString:(I)Ljava/lang/String;
   297:	iload	15
   299:	bipush	48
   301:	invokestatic	#63; //Method org/apache/commons/lang/StringUtils.leftPad:(Ljava/lang/String;IC)Ljava/lang/String;
   304:	goto	312
   307:	iload	6
   309:	invokestatic	#76; //Method java/lang/Integer.toString:(I)Ljava/lang/String;
   312:	invokevirtual	#50; //Method java/lang/StringBuffer.append:(Ljava/lang/String;)Ljava/lang/StringBuffer;
   315:	pop
   316:	iconst_1
   317:	istore	10
   319:	goto	416
   322:	aload	14
   324:	ldc	#19; //String S
   326:	if_acmpne	416
   329:	iload	10
   331:	ifeq	382
   334:	iinc_w 7, 1000
   340:	iload	8
   342:	ifeq	360
   345:	iload	7
   347:	invokestatic	#76; //Method java/lang/Integer.toString:(I)Ljava/lang/String;
   350:	iload	15
   352:	bipush	48
   354:	invokestatic	#63; //Method org/apache/commons/lang/StringUtils.leftPad:(Ljava/lang/String;IC)Ljava/lang/String;
   357:	goto	365
   360:	iload	7
   362:	invokestatic	#76; //Method java/lang/Integer.toString:(I)Ljava/lang/String;
   365:	astore	16
   367:	aload	9
   369:	aload	16
   371:	iconst_1
   372:	invokevirtual	#71; //Method java/lang/String.substring:(I)Ljava/lang/String;
   375:	invokevirtual	#50; //Method java/lang/StringBuffer.append:(Ljava/lang/String;)Ljava/lang/StringBuffer;
   378:	pop
   379:	goto	413
   382:	aload	9
   384:	iload	8
   386:	ifeq	404
   389:	iload	7
   391:	invokestatic	#76; //Method java/lang/Integer.toString:(I)Ljava/lang/String;
   394:	iload	15
   396:	bipush	48
   398:	invokestatic	#63; //Method org/apache/commons/lang/StringUtils.leftPad:(Ljava/lang/String;IC)Ljava/lang/String;
   401:	goto	409
   404:	iload	7
   406:	invokestatic	#76; //Method java/lang/Integer.toString:(I)Ljava/lang/String;
   409:	invokevirtual	#50; //Method java/lang/StringBuffer.append:(Ljava/lang/String;)Ljava/lang/StringBuffer;
   412:	pop
   413:	iconst_0
   414:	istore	10
   416:	iinc	12, 1
   419:	iload	12
   421:	iload	11
   423:	if_icmplt	22
   426:	aload	9
   428:	invokevirtual	#75; //Method java/lang/StringBuffer.toString:()Ljava/lang/String;
   431:	areturn
  LineNumberTable: 
   line 374: 0
   line 375: 9
   line 376: 12
   line 377: 16
   line 378: 22
   line 379: 28
   line 380: 35
   line 381: 42
   line 382: 50
   line 381: 61
   line 384: 64
   line 450: 66
   line 384: 68
   line 385: 71
   line 386: 92
   line 385: 96
   line 387: 100
   line 384: 103
   line 388: 106
   line 451: 108
   line 388: 110
   line 389: 113
   line 390: 134
   line 389: 138
   line 391: 142
   line 388: 145
   line 392: 148
   line 452: 150
   line 392: 152
   line 393: 155
   line 394: 176
   line 393: 180
   line 395: 184
   line 392: 187
   line 396: 190
   line 453: 192
   line 396: 194
   line 397: 197
   line 398: 219
   line 397: 224
   line 399: 228
   line 396: 231
   line 400: 234
   line 454: 236
   line 400: 238
   line 401: 241
   line 402: 263
   line 401: 268
   line 403: 272
   line 400: 275
   line 404: 278
   line 455: 280
   line 404: 282
   line 405: 285
   line 406: 307
   line 405: 312
   line 407: 316
   line 404: 319
   line 408: 322
   line 456: 324
   line 408: 326
   line 409: 329
   line 410: 334
   line 411: 340
   line 412: 345
   line 413: 360
   line 411: 365
   line 414: 367
   line 409: 379
   line 416: 382
   line 417: 389
   line 418: 404
   line 416: 409
   line 420: 413
   line 377: 416
   line 424: 426

  LocalVariableTable: 
   Start  Length  Slot  Name   Signature
   0      432      0    tokens       [Lorg/apache/commons/lang/time/DurationFormatUtils$Token;
   0      432      1    years       I
   0      432      2    months       I
   0      432      3    days       I
   0      432      4    hours       I
   0      432      5    minutes       I
   0      432      6    seconds       I
   0      432      7    milliseconds       I
   0      432      8    padWithZeros       Z
   9      423      9    buffer       Ljava/lang/StringBuffer;
   12      420      10    lastOutputSeconds       Z
   16      416      11    sz       I
   19      413      12    i       I
   28      391      13    token       Lorg/apache/commons/lang/time/DurationFormatUtils$Token;
   35      384      14    value       Ljava/lang/Object;
   42      377      15    count       I
   367      15      16    str       Ljava/lang/String;


public static java.lang.String formatDuration(long, java.lang.String);
  Code:
   Stack=4, Locals=3, Args_size=2
   0:	lload_0
   1:	aload_2
   2:	iconst_1
   3:	invokestatic	#55; //Method formatDuration:(JLjava/lang/String;Z)Ljava/lang/String;
   6:	areturn
  LineNumberTable: 
   line 109: 0

  LocalVariableTable: 
   Start  Length  Slot  Name   Signature
   0      7      0    durationMillis       J
   0      7      2    format       Ljava/lang/String;


public static java.lang.String formatDuration(long, java.lang.String, boolean);
  Code:
   Stack=9, Locals=10, Args_size=3
   0:	aload_2
   1:	invokestatic	#65; //Method lexx:(Ljava/lang/String;)[Lorg/apache/commons/lang/time/DurationFormatUtils$Token;
   4:	astore	4
   6:	iconst_0
   7:	istore	5
   9:	iconst_0
   10:	istore	6
   12:	iconst_0
   13:	istore	7
   15:	iconst_0
   16:	istore	8
   18:	iconst_0
   19:	istore	9
   21:	aload	4
   23:	ldc	#20; //String d
   25:	invokestatic	#51; //Method org/apache/commons/lang/time/DurationFormatUtils$Token.containsTokenWithValue:([Lorg/apache/commons/lang/time/DurationFormatUtils$Token;Ljava/lang/Object;)Z
   28:	ifeq	49
   31:	lload_0
   32:	ldc2_w	#84; //long 86400000l
   35:	ldiv
   36:	l2i
   37:	istore	5
   39:	lload_0
   40:	iload	5
   42:	i2l
   43:	ldc2_w	#84; //long 86400000l
   46:	lmul
   47:	lsub
   48:	lstore_0
   49:	aload	4
   51:	ldc	#16; //String H
   53:	invokestatic	#51; //Method org/apache/commons/lang/time/DurationFormatUtils$Token.containsTokenWithValue:([Lorg/apache/commons/lang/time/DurationFormatUtils$Token;Ljava/lang/Object;)Z
   56:	ifeq	77
   59:	lload_0
   60:	ldc2_w	#82; //long 3600000l
   63:	ldiv
   64:	l2i
   65:	istore	6
   67:	lload_0
   68:	iload	6
   70:	i2l
   71:	ldc2_w	#82; //long 3600000l
   74:	lmul
   75:	lsub
   76:	lstore_0
   77:	aload	4
   79:	ldc	#22; //String m
   81:	invokestatic	#51; //Method org/apache/commons/lang/time/DurationFormatUtils$Token.containsTokenWithValue:([Lorg/apache/commons/lang/time/DurationFormatUtils$Token;Ljava/lang/Object;)Z
   84:	ifeq	105
   87:	lload_0
   88:	ldc2_w	#80; //long 60000l
   91:	ldiv
   92:	l2i
   93:	istore	7
   95:	lload_0
   96:	iload	7
   98:	i2l
   99:	ldc2_w	#80; //long 60000l
   102:	lmul
   103:	lsub
   104:	lstore_0
   105:	aload	4
   107:	ldc	#23; //String s
   109:	invokestatic	#51; //Method org/apache/commons/lang/time/DurationFormatUtils$Token.containsTokenWithValue:([Lorg/apache/commons/lang/time/DurationFormatUtils$Token;Ljava/lang/Object;)Z
   112:	ifeq	133
   115:	lload_0
   116:	ldc2_w	#78; //long 1000l
   119:	ldiv
   120:	l2i
   121:	istore	8
   123:	lload_0
   124:	iload	8
   126:	i2l
   127:	ldc2_w	#78; //long 1000l
   130:	lmul
   131:	lsub
   132:	lstore_0
   133:	aload	4
   135:	ldc	#19; //String S
   137:	invokestatic	#51; //Method org/apache/commons/lang/time/DurationFormatUtils$Token.containsTokenWithValue:([Lorg/apache/commons/lang/time/DurationFormatUtils$Token;Ljava/lang/Object;)Z
   140:	ifeq	147
   143:	lload_0
   144:	l2i
   145:	istore	9
   147:	aload	4
   149:	iconst_0
   150:	iconst_0
   151:	iload	5
   153:	iload	6
   155:	iload	7
   157:	iload	8
   159:	iload	9
   161:	iload_3
   162:	invokestatic	#53; //Method format:([Lorg/apache/commons/lang/time/DurationFormatUtils$Token;IIIIIIIZ)Ljava/lang/String;
   165:	areturn
  LineNumberTable: 
   line 127: 0
   line 129: 6
   line 130: 9
   line 131: 12
   line 132: 15
   line 133: 18
   line 135: 21
   line 452: 23
   line 135: 25
   line 136: 31
   line 137: 39
   line 139: 49
   line 453: 51
   line 139: 53
   line 140: 59
   line 141: 67
   line 143: 77
   line 454: 79
   line 143: 81
   line 144: 87
   line 145: 95
   line 147: 105
   line 455: 107
   line 147: 109
   line 148: 115
   line 149: 123
   line 151: 133
   line 456: 135
   line 151: 137
   line 152: 143
   line 155: 147

  LocalVariableTable: 
   Start  Length  Slot  Name   Signature
   0      166      0    durationMillis       J
   0      166      2    format       Ljava/lang/String;
   0      166      3    padWithZeros       Z
   9      157      5    days       I
   6      160      4    tokens       [Lorg/apache/commons/lang/time/DurationFormatUtils$Token;
   12      154      6    hours       I
   15      151      7    minutes       I
   18      148      8    seconds       I
   21      145      9    milliseconds       I


public static java.lang.String formatDurationHMS(long);
  Code:
   Stack=3, Locals=2, Args_size=1
   0:	lload_0
   1:	ldc	#17; //String H:mm:ss.SSS
   3:	invokestatic	#54; //Method formatDuration:(JLjava/lang/String;)Ljava/lang/String;
   6:	areturn
  LineNumberTable: 
   line 79: 0

  LocalVariableTable: 
   Start  Length  Slot  Name   Signature
   0      7      0    durationMillis       J


public static java.lang.String formatDurationISO(long);
  Code:
   Stack=4, Locals=2, Args_size=1
   0:	lload_0
   1:	ldc	#7; //String 'P'yyyy'Y'M'M'd'DT'H'H'm'M's.S'S'
   3:	iconst_0
   4:	invokestatic	#55; //Method formatDuration:(JLjava/lang/String;Z)Ljava/lang/String;
   7:	areturn
  LineNumberTable: 
   line 94: 0

  LocalVariableTable: 
   Start  Length  Slot  Name   Signature
   0      8      0    durationMillis       J


public static java.lang.String formatDurationWords(long, boolean, boolean);
  Code:
   Stack=3, Locals=6, Args_size=3
   0:	lload_0
   1:	ldc	#21; //String d' days 'H' hours 'm' minutes 's' seconds'
   3:	invokestatic	#54; //Method formatDuration:(JLjava/lang/String;)Ljava/lang/String;
   6:	astore	4
   8:	iload_2
   9:	ifeq	142
   12:	new	#29; //class java/lang/StringBuffer
   15:	dup
   16:	ldc	#2; //String  
   18:	invokespecial	#43; //Method java/lang/StringBuffer."<init>":(Ljava/lang/String;)V
   21:	aload	4
   23:	invokevirtual	#50; //Method java/lang/StringBuffer.append:(Ljava/lang/String;)Ljava/lang/StringBuffer;
   26:	invokevirtual	#75; //Method java/lang/StringBuffer.toString:()Ljava/lang/String;
   29:	astore	4
   31:	aload	4
   33:	ldc	#3; //String  0 days
   35:	ldc	#1; //String 
   37:	invokestatic	#68; //Method org/apache/commons/lang/StringUtils.replaceOnce:(Ljava/lang/String;Ljava/lang/String;Ljava/lang/String;)Ljava/lang/String;
   40:	astore	5
   42:	aload	5
   44:	invokevirtual	#64; //Method java/lang/String.length:()I
   47:	aload	4
   49:	invokevirtual	#64; //Method java/lang/String.length:()I
   52:	if_icmpeq	126
   55:	aload	5
   57:	astore	4
   59:	aload	4
   61:	ldc	#4; //String  0 hours
   63:	ldc	#1; //String 
   65:	invokestatic	#68; //Method org/apache/commons/lang/StringUtils.replaceOnce:(Ljava/lang/String;Ljava/lang/String;Ljava/lang/String;)Ljava/lang/String;
   68:	astore	5
   70:	aload	5
   72:	invokevirtual	#64; //Method java/lang/String.length:()I
   75:	aload	4
   77:	invokevirtual	#64; //Method java/lang/String.length:()I
   80:	if_icmpeq	126
   83:	aload	5
   85:	astore	4
   87:	aload	4
   89:	ldc	#5; //String  0 minutes
   91:	ldc	#1; //String 
   93:	invokestatic	#68; //Method org/apache/commons/lang/StringUtils.replaceOnce:(Ljava/lang/String;Ljava/lang/String;Ljava/lang/String;)Ljava/lang/String;
   96:	astore	5
   98:	aload	5
   100:	astore	4
   102:	aload	5
   104:	invokevirtual	#64; //Method java/lang/String.length:()I
   107:	aload	4
   109:	invokevirtual	#64; //Method java/lang/String.length:()I
   112:	if_icmpeq	126
   115:	aload	5
   117:	ldc	#6; //String  0 seconds
   119:	ldc	#1; //String 
   121:	invokestatic	#68; //Method org/apache/commons/lang/StringUtils.replaceOnce:(Ljava/lang/String;Ljava/lang/String;Ljava/lang/String;)Ljava/lang/String;
   124:	astore	4
   126:	aload	4
   128:	invokevirtual	#64; //Method java/lang/String.length:()I
   131:	ifeq	142
   134:	aload	4
   136:	iconst_1
   137:	invokevirtual	#71; //Method java/lang/String.substring:(I)Ljava/lang/String;
   140:	astore	4
   142:	iload_3
   143:	ifeq	237
   146:	aload	4
   148:	ldc	#6; //String  0 seconds
   150:	ldc	#1; //String 
   152:	invokestatic	#68; //Method org/apache/commons/lang/StringUtils.replaceOnce:(Ljava/lang/String;Ljava/lang/String;Ljava/lang/String;)Ljava/lang/String;
   155:	astore	5
   157:	aload	5
   159:	invokevirtual	#64; //Method java/lang/String.length:()I
   162:	aload	4
   164:	invokevirtual	#64; //Method java/lang/String.length:()I
   167:	if_icmpeq	237
   170:	aload	5
   172:	astore	4
   174:	aload	4
   176:	ldc	#5; //String  0 minutes
   178:	ldc	#1; //String 
   180:	invokestatic	#68; //Method org/apache/commons/lang/StringUtils.replaceOnce:(Ljava/lang/String;Ljava/lang/String;Ljava/lang/String;)Ljava/lang/String;
   183:	astore	5
   185:	aload	5
   187:	invokevirtual	#64; //Method java/lang/String.length:()I
   190:	aload	4
   192:	invokevirtual	#64; //Method java/lang/String.length:()I
   195:	if_icmpeq	237
   198:	aload	5
   200:	astore	4
   202:	aload	4
   204:	ldc	#4; //String  0 hours
   206:	ldc	#1; //String 
   208:	invokestatic	#68; //Method org/apache/commons/lang/StringUtils.replaceOnce:(Ljava/lang/String;Ljava/lang/String;Ljava/lang/String;)Ljava/lang/String;
   211:	astore	5
   213:	aload	5
   215:	invokevirtual	#64; //Method java/lang/String.length:()I
   218:	aload	4
   220:	invokevirtual	#64; //Method java/lang/String.length:()I
   223:	if_icmpeq	237
   226:	aload	5
   228:	ldc	#3; //String  0 days
   230:	ldc	#1; //String 
   232:	invokestatic	#68; //Method org/apache/commons/lang/StringUtils.replaceOnce:(Ljava/lang/String;Ljava/lang/String;Ljava/lang/String;)Ljava/lang/String;
   235:	astore	4
   237:	aload	4
   239:	ldc	#15; //String 1 seconds
   241:	ldc	#14; //String 1 second
   243:	invokestatic	#68; //Method org/apache/commons/lang/StringUtils.replaceOnce:(Ljava/lang/String;Ljava/lang/String;Ljava/lang/String;)Ljava/lang/String;
   246:	astore	4
   248:	aload	4
   250:	ldc	#13; //String 1 minutes
   252:	ldc	#12; //String 1 minute
   254:	invokestatic	#68; //Method org/apache/commons/lang/StringUtils.replaceOnce:(Ljava/lang/String;Ljava/lang/String;Ljava/lang/String;)Ljava/lang/String;
   257:	astore	4
   259:	aload	4
   261:	ldc	#11; //String 1 hours
   263:	ldc	#10; //String 1 hour
   265:	invokestatic	#68; //Method org/apache/commons/lang/StringUtils.replaceOnce:(Ljava/lang/String;Ljava/lang/String;Ljava/lang/String;)Ljava/lang/String;
   268:	astore	4
   270:	aload	4
   272:	ldc	#9; //String 1 days
   274:	ldc	#8; //String 1 day
   276:	invokestatic	#68; //Method org/apache/commons/lang/StringUtils.replaceOnce:(Ljava/lang/String;Ljava/lang/String;Ljava/lang/String;)Ljava/lang/String;
   279:	astore	4
   281:	aload	4
   283:	areturn
  LineNumberTable: 
   line 177: 0
   line 178: 8
   line 180: 12
   line 181: 31
   line 182: 42
   line 183: 55
   line 184: 59
   line 185: 70
   line 186: 83
   line 187: 87
   line 188: 98
   line 189: 102
   line 190: 115
   line 194: 126
   line 196: 134
   line 199: 142
   line 200: 146
   line 201: 157
   line 202: 170
   line 203: 174
   line 204: 185
   line 205: 198
   line 206: 202
   line 207: 213
   line 208: 226
   line 214: 237
   line 215: 248
   line 216: 259
   line 217: 270
   line 218: 281

  LocalVariableTable: 
   Start  Length  Slot  Name   Signature
   0      284      0    durationMillis       J
   0      284      2    suppressLeadingZeroElements       Z
   0      284      3    suppressTrailingZeroElements       Z
   8      276      4    duration       Ljava/lang/String;
   42      100      5    tmp       Ljava/lang/String;
   157      80      5    tmp       Ljava/lang/String;


public static java.lang.String formatPeriod(long, long, java.lang.String);
  Code:
   Stack=7, Locals=5, Args_size=3
   0:	lload_0
   1:	lload_2
   2:	aload	4
   4:	iconst_1
   5:	invokestatic	#59; //Method java/util/TimeZone.getDefault:()Ljava/util/TimeZone;
   8:	invokestatic	#56; //Method formatPeriod:(JJLjava/lang/String;ZLjava/util/TimeZone;)Ljava/lang/String;
   11:	areturn
  LineNumberTable: 
   line 245: 0

  LocalVariableTable: 
   Start  Length  Slot  Name   Signature
   0      12      0    startMillis       J
   0      12      2    endMillis       J
   0      12      4    format       Ljava/lang/String;


public static java.lang.String formatPeriod(long, long, java.lang.String, boolean, java.util.TimeZone);
  Code:
   Stack=9, Locals=19, Args_size=5
   0:	lload_2
   1:	lload_0
   2:	lsub
   3:	lstore	7
   5:	lload	7
   7:	ldc2_w	#86; //long 2419200000l
   10:	lcmp
   11:	ifge	24
   14:	lload	7
   16:	aload	4
   18:	iload	5
   20:	invokestatic	#55; //Method formatDuration:(JLjava/lang/String;Z)Ljava/lang/String;
   23:	areturn
   24:	aload	4
   26:	invokestatic	#65; //Method lexx:(Ljava/lang/String;)[Lorg/apache/commons/lang/time/DurationFormatUtils$Token;
   29:	astore	9
   31:	aload	6
   33:	invokestatic	#60; //Method java/util/Calendar.getInstance:(Ljava/util/TimeZone;)Ljava/util/Calendar;
   36:	astore	10
   38:	aload	10
   40:	new	#32; //class java/util/Date
   43:	dup
   44:	lload_0
   45:	invokespecial	#41; //Method java/util/Date."<init>":(J)V
   48:	invokevirtual	#70; //Method java/util/Calendar.setTime:(Ljava/util/Date;)V
   51:	aload	6
   53:	invokestatic	#60; //Method java/util/Calendar.getInstance:(Ljava/util/TimeZone;)Ljava/util/Calendar;
   56:	astore	11
   58:	aload	11
   60:	new	#32; //class java/util/Date
   63:	dup
   64:	lload_2
   65:	invokespecial	#41; //Method java/util/Date."<init>":(J)V
   68:	invokevirtual	#70; //Method java/util/Calendar.setTime:(Ljava/util/Date;)V
   71:	aload	11
   73:	iconst_1
   74:	invokevirtual	#57; //Method java/util/Calendar.get:(I)I
   77:	aload	10
   79:	iconst_1
   80:	invokevirtual	#57; //Method java/util/Calendar.get:(I)I
   83:	isub
   84:	istore	12
   86:	aload	11
   88:	iconst_2
   89:	invokevirtual	#57; //Method java/util/Calendar.get:(I)I
   92:	aload	10
   94:	iconst_2
   95:	invokevirtual	#57; //Method java/util/Calendar.get:(I)I
   98:	isub
   99:	istore	13
   101:	goto	110
   104:	iinc	13, 12
   107:	iinc	12, -1
   110:	iload	13
   112:	iflt	104
   115:	aload	11
   117:	iconst_5
   118:	invokevirtual	#57; //Method java/util/Calendar.get:(I)I
   121:	aload	10
   123:	iconst_5
   124:	invokevirtual	#57; //Method java/util/Calendar.get:(I)I
   127:	isub
   128:	istore	14
   130:	goto	139
   133:	iinc	14, 31
   136:	iinc	13, -1
   139:	iload	14
   141:	iflt	133
   144:	aload	11
   146:	bipush	11
   148:	invokevirtual	#57; //Method java/util/Calendar.get:(I)I
   151:	aload	10
   153:	bipush	11
   155:	invokevirtual	#57; //Method java/util/Calendar.get:(I)I
   158:	isub
   159:	istore	15
   161:	goto	170
   164:	iinc	15, 24
   167:	iinc	14, -1
   170:	iload	15
   172:	iflt	164
   175:	aload	11
   177:	bipush	12
   179:	invokevirtual	#57; //Method java/util/Calendar.get:(I)I
   182:	aload	10
   184:	bipush	12
   186:	invokevirtual	#57; //Method java/util/Calendar.get:(I)I
   189:	isub
   190:	istore	16
   192:	goto	201
   195:	iinc	16, 60
   198:	iinc	15, -1
   201:	iload	16
   203:	iflt	195
   206:	aload	11
   208:	bipush	13
   210:	invokevirtual	#57; //Method java/util/Calendar.get:(I)I
   213:	aload	10
   215:	bipush	13
   217:	invokevirtual	#57; //Method java/util/Calendar.get:(I)I
   220:	isub
   221:	istore	17
   223:	goto	232
   226:	iinc	17, 60
   229:	iinc	16, -1
   232:	iload	17
   234:	iflt	226
   237:	aload	11
   239:	bipush	14
   241:	invokevirtual	#57; //Method java/util/Calendar.get:(I)I
   244:	aload	10
   246:	bipush	14
   248:	invokevirtual	#57; //Method java/util/Calendar.get:(I)I
   251:	isub
   252:	istore	18
   254:	goto	266
   257:	iinc_w 18, 1000
   263:	iinc	17, -1
   266:	iload	18
   268:	iflt	257
   271:	iload	18
   273:	aload	10
   275:	aload	11
   277:	bipush	14
   279:	iload	18
   281:	invokestatic	#67; //Method reduceAndCorrect:(Ljava/util/Calendar;Ljava/util/Calendar;II)I
   284:	isub
   285:	istore	18
   287:	iload	17
   289:	aload	10
   291:	aload	11
   293:	bipush	13
   295:	iload	17
   297:	invokestatic	#67; //Method reduceAndCorrect:(Ljava/util/Calendar;Ljava/util/Calendar;II)I
   300:	isub
   301:	istore	17
   303:	iload	16
   305:	aload	10
   307:	aload	11
   309:	bipush	12
   311:	iload	16
   313:	invokestatic	#67; //Method reduceAndCorrect:(Ljava/util/Calendar;Ljava/util/Calendar;II)I
   316:	isub
   317:	istore	16
   319:	iload	15
   321:	aload	10
   323:	aload	11
   325:	bipush	11
   327:	iload	15
   329:	invokestatic	#67; //Method reduceAndCorrect:(Ljava/util/Calendar;Ljava/util/Calendar;II)I
   332:	isub
   333:	istore	15
   335:	iload	14
   337:	aload	10
   339:	aload	11
   341:	iconst_5
   342:	iload	14
   344:	invokestatic	#67; //Method reduceAndCorrect:(Ljava/util/Calendar;Ljava/util/Calendar;II)I
   347:	isub
   348:	istore	14
   350:	iload	13
   352:	aload	10
   354:	aload	11
   356:	iconst_2
   357:	iload	13
   359:	invokestatic	#67; //Method reduceAndCorrect:(Ljava/util/Calendar;Ljava/util/Calendar;II)I
   362:	isub
   363:	istore	13
   365:	iload	12
   367:	aload	10
   369:	aload	11
   371:	iconst_1
   372:	iload	12
   374:	invokestatic	#67; //Method reduceAndCorrect:(Ljava/util/Calendar;Ljava/util/Calendar;II)I
   377:	isub
   378:	istore	12
   380:	aload	9
   382:	ldc	#24; //String y
   384:	invokestatic	#51; //Method org/apache/commons/lang/time/DurationFormatUtils$Token.containsTokenWithValue:([Lorg/apache/commons/lang/time/DurationFormatUtils$Token;Ljava/lang/Object;)Z
   387:	ifne	430
   390:	aload	9
   392:	ldc	#18; //String M
   394:	invokestatic	#51; //Method org/apache/commons/lang/time/DurationFormatUtils$Token.containsTokenWithValue:([Lorg/apache/commons/lang/time/DurationFormatUtils$Token;Ljava/lang/Object;)Z
   397:	ifeq	416
   400:	iload	13
   402:	bipush	12
   404:	iload	12
   406:	imul
   407:	iadd
   408:	istore	13
   410:	iconst_0
   411:	istore	12
   413:	goto	430
   416:	iload	14
   418:	sipush	365
   421:	iload	12
   423:	imul
   424:	iadd
   425:	istore	14
   427:	iconst_0
   428:	istore	12
   430:	aload	9
   432:	ldc	#18; //String M
   434:	invokestatic	#51; //Method org/apache/commons/lang/time/DurationFormatUtils$Token.containsTokenWithValue:([Lorg/apache/commons/lang/time/DurationFormatUtils$Token;Ljava/lang/Object;)Z
   437:	ifne	463
   440:	iload	14
   442:	aload	11
   444:	bipush	6
   446:	invokevirtual	#57; //Method java/util/Calendar.get:(I)I
   449:	aload	10
   451:	bipush	6
   453:	invokevirtual	#57; //Method java/util/Calendar.get:(I)I
   456:	isub
   457:	iadd
   458:	istore	14
   460:	iconst_0
   461:	istore	13
   463:	aload	9
   465:	ldc	#20; //String d
   467:	invokestatic	#51; //Method org/apache/commons/lang/time/DurationFormatUtils$Token.containsTokenWithValue:([Lorg/apache/commons/lang/time/DurationFormatUtils$Token;Ljava/lang/Object;)Z
   470:	ifne	486
   473:	iload	15
   475:	bipush	24
   477:	iload	14
   479:	imul
   480:	iadd
   481:	istore	15
   483:	iconst_0
   484:	istore	14
   486:	aload	9
   488:	ldc	#16; //String H
   490:	invokestatic	#51; //Method org/apache/commons/lang/time/DurationFormatUtils$Token.containsTokenWithValue:([Lorg/apache/commons/lang/time/DurationFormatUtils$Token;Ljava/lang/Object;)Z
   493:	ifne	509
   496:	iload	16
   498:	bipush	60
   500:	iload	15
   502:	imul
   503:	iadd
   504:	istore	16
   506:	iconst_0
   507:	istore	15
   509:	aload	9
   511:	ldc	#22; //String m
   513:	invokestatic	#51; //Method org/apache/commons/lang/time/DurationFormatUtils$Token.containsTokenWithValue:([Lorg/apache/commons/lang/time/DurationFormatUtils$Token;Ljava/lang/Object;)Z
   516:	ifne	532
   519:	iload	17
   521:	bipush	60
   523:	iload	16
   525:	imul
   526:	iadd
   527:	istore	17
   529:	iconst_0
   530:	istore	16
   532:	aload	9
   534:	ldc	#23; //String s
   536:	invokestatic	#51; //Method org/apache/commons/lang/time/DurationFormatUtils$Token.containsTokenWithValue:([Lorg/apache/commons/lang/time/DurationFormatUtils$Token;Ljava/lang/Object;)Z
   539:	ifne	556
   542:	iload	18
   544:	sipush	1000
   547:	iload	17
   549:	imul
   550:	iadd
   551:	istore	18
   553:	iconst_0
   554:	istore	17
   556:	aload	9
   558:	iload	12
   560:	iload	13
   562:	iload	14
   564:	iload	15
   566:	iload	16
   568:	iload	17
   570:	iload	18
   572:	iload	5
   574:	invokestatic	#53; //Method format:([Lorg/apache/commons/lang/time/DurationFormatUtils$Token;IIIIIIIZ)Ljava/lang/String;
   577:	areturn
  LineNumberTable: 
   line 263: 0
   line 264: 5
   line 265: 14
   line 268: 24
   line 272: 31
   line 273: 38
   line 274: 51
   line 275: 58
   line 278: 71
   line 279: 86
   line 281: 101
   line 282: 104
   line 283: 107
   line 281: 110
   line 285: 115
   line 286: 130
   line 287: 133
   line 288: 136
   line 286: 139
   line 290: 144
   line 291: 161
   line 292: 164
   line 293: 167
   line 291: 170
   line 295: 175
   line 296: 192
   line 297: 195
   line 298: 198
   line 296: 201
   line 300: 206
   line 301: 223
   line 302: 226
   line 303: 229
   line 301: 232
   line 305: 237
   line 306: 254
   line 307: 257
   line 308: 263
   line 306: 266
   line 312: 271
   line 313: 287
   line 314: 303
   line 315: 319
   line 316: 335
   line 317: 350
   line 318: 365
   line 323: 380
   line 450: 382
   line 323: 384
   line 324: 390
   line 451: 392
   line 324: 394
   line 325: 400
   line 326: 410
   line 324: 413
   line 329: 416
   line 330: 427
   line 333: 430
   line 451: 432
   line 333: 434
   line 334: 440
   line 335: 460
   line 337: 463
   line 452: 465
   line 337: 467
   line 338: 473
   line 339: 483
   line 341: 486
   line 453: 488
   line 341: 490
   line 342: 496
   line 343: 506
   line 345: 509
   line 454: 511
   line 345: 513
   line 346: 519
   line 347: 529
   line 349: 532
   line 455: 534
   line 349: 536
   line 350: 542
   line 351: 553
   line 354: 556

  LocalVariableTable: 
   Start  Length  Slot  Name   Signature
   0      578      0    startMillis       J
   0      578      2    endMillis       J
   0      578      4    format       Ljava/lang/String;
   0      578      5    padWithZeros       Z
   0      578      6    timezone       Ljava/util/TimeZone;
   5      573      7    millis       J
   31      547      9    tokens       [Lorg/apache/commons/lang/time/DurationFormatUtils$Token;
   38      540      10    start       Ljava/util/Calendar;
   58      520      11    end       Ljava/util/Calendar;
   86      492      12    years       I
   101      477      13    months       I
   130      448      14    days       I
   161      417      15    hours       I
   192      386      16    minutes       I
   223      355      17    seconds       I
   254      324      18    milliseconds       I


public static java.lang.String formatPeriodISO(long, long);
  Code:
   Stack=7, Locals=4, Args_size=2
   0:	lload_0
   1:	lload_2
   2:	ldc	#7; //String 'P'yyyy'Y'M'M'd'DT'H'H'm'M's.S'S'
   4:	iconst_0
   5:	invokestatic	#59; //Method java/util/TimeZone.getDefault:()Ljava/util/TimeZone;
   8:	invokestatic	#56; //Method formatPeriod:(JJLjava/lang/String;ZLjava/util/TimeZone;)Ljava/lang/String;
   11:	areturn
  LineNumberTable: 
   line 232: 0

  LocalVariableTable: 
   Start  Length  Slot  Name   Signature
   0      12      0    startMillis       J
   0      12      2    endMillis       J


static org.apache.commons.lang.time.DurationFormatUtils$Token[] lexx(java.lang.String);
  Code:
   Stack=4, Locals=11, Args_size=1
   0:	aload_0
   1:	invokevirtual	#73; //Method java/lang/String.toCharArray:()[C
   4:	astore_1
   5:	new	#30; //class java/util/ArrayList
   8:	dup
   9:	aload_1
   10:	arraylength
   11:	invokespecial	#40; //Method java/util/ArrayList."<init>":(I)V
   14:	astore_2
   15:	iconst_0
   16:	istore_3
   17:	aconst_null
   18:	astore	4
   20:	aconst_null
   21:	astore	5
   23:	aload_1
   24:	arraylength
   25:	istore	6
   27:	iconst_0
   28:	istore	7
   30:	goto	321
   33:	aload_1
   34:	iload	7
   36:	caload
   37:	istore	8
   39:	iload_3
   40:	ifeq	61
   43:	iload	8
   45:	bipush	39
   47:	if_icmpeq	61
   50:	aload	4
   52:	iload	8
   54:	invokevirtual	#49; //Method java/lang/StringBuffer.append:(C)Ljava/lang/StringBuffer;
   57:	pop
   58:	goto	318
   61:	aconst_null
   62:	astore	9
   64:	iload	8
   66:	lookupswitch{ //8
		39: 140;
		72: 201;
		77: 187;
		83: 222;
		100: 194;
		109: 208;
		115: 215;
		121: 180;
		default: 229 }
   140:	iload_3
   141:	ifeq	152
   144:	aconst_null
   145:	astore	4
   147:	iconst_0
   148:	istore_3
   149:	goto	265
   152:	new	#29; //class java/lang/StringBuffer
   155:	dup
   156:	invokespecial	#39; //Method java/lang/StringBuffer."<init>":()V
   159:	astore	4
   161:	aload_2
   162:	new	#37; //class org/apache/commons/lang/time/DurationFormatUtils$Token
   165:	dup
   166:	aload	4
   168:	invokespecial	#42; //Method org/apache/commons/lang/time/DurationFormatUtils$Token."<init>":(Ljava/lang/Object;)V
   171:	invokevirtual	#48; //Method java/util/ArrayList.add:(Ljava/lang/Object;)Z
   174:	pop
   175:	iconst_1
   176:	istore_3
   177:	goto	265
   180:	ldc	#24; //String y
   182:	astore	9
   184:	goto	265
   187:	ldc	#18; //String M
   189:	astore	9
   191:	goto	265
   194:	ldc	#20; //String d
   196:	astore	9
   198:	goto	265
   201:	ldc	#16; //String H
   203:	astore	9
   205:	goto	265
   208:	ldc	#22; //String m
   210:	astore	9
   212:	goto	265
   215:	ldc	#23; //String s
   217:	astore	9
   219:	goto	265
   222:	ldc	#19; //String S
   224:	astore	9
   226:	goto	265
   229:	aload	4
   231:	ifnonnull	257
   234:	new	#29; //class java/lang/StringBuffer
   237:	dup
   238:	invokespecial	#39; //Method java/lang/StringBuffer."<init>":()V
   241:	astore	4
   243:	aload_2
   244:	new	#37; //class org/apache/commons/lang/time/DurationFormatUtils$Token
   247:	dup
   248:	aload	4
   250:	invokespecial	#42; //Method org/apache/commons/lang/time/DurationFormatUtils$Token."<init>":(Ljava/lang/Object;)V
   253:	invokevirtual	#48; //Method java/util/ArrayList.add:(Ljava/lang/Object;)Z
   256:	pop
   257:	aload	4
   259:	iload	8
   261:	invokevirtual	#49; //Method java/lang/StringBuffer.append:(C)Ljava/lang/StringBuffer;
   264:	pop
   265:	aload	9
   267:	ifnull	318
   270:	aload	5
   272:	ifnull	293
   275:	aload	5
   277:	invokevirtual	#61; //Method org/apache/commons/lang/time/DurationFormatUtils$Token.getValue:()Ljava/lang/Object;
   280:	aload	9
   282:	if_acmpne	293
   285:	aload	5
   287:	invokevirtual	#62; //Method org/apache/commons/lang/time/DurationFormatUtils$Token.increment:()V
   290:	goto	315
   293:	new	#37; //class org/apache/commons/lang/time/DurationFormatUtils$Token
   296:	dup
   297:	aload	9
   299:	invokespecial	#42; //Method org/apache/commons/lang/time/DurationFormatUtils$Token."<init>":(Ljava/lang/Object;)V
   302:	astore	10
   304:	aload_2
   305:	aload	10
   307:	invokevirtual	#48; //Method java/util/ArrayList.add:(Ljava/lang/Object;)Z
   310:	pop
   311:	aload	10
   313:	astore	5
   315:	aconst_null
   316:	astore	4
   318:	iinc	7, 1
   321:	iload	7
   323:	iload	6
   325:	if_icmplt	33
   328:	aload_2
   329:	iconst_0
   330:	anewarray	#37; //class org/apache/commons/lang/time/DurationFormatUtils$Token
   333:	invokevirtual	#72; //Method java/util/ArrayList.toArray:([Ljava/lang/Object;)[Ljava/lang/Object;
   336:	checkcast	#25; //class "[Lorg/apache/commons/lang/time/DurationFormatUtils$Token;"
   339:	areturn
  LineNumberTable: 
   line 465: 0
   line 466: 5
   line 468: 15
   line 469: 17
   line 470: 20
   line 471: 23
   line 472: 27
   line 473: 33
   line 474: 39
   line 475: 50
   line 476: 58
   line 478: 61
   line 479: 64
   line 482: 140
   line 483: 144
   line 484: 147
   line 482: 149
   line 486: 152
   line 487: 161
   line 488: 175
   line 490: 177
   line 450: 180
   line 491: 182
   line 451: 187
   line 492: 189
   line 452: 194
   line 493: 196
   line 453: 201
   line 494: 203
   line 454: 208
   line 495: 210
   line 455: 215
   line 496: 217
   line 456: 222
   line 497: 224
   line 499: 229
   line 500: 234
   line 501: 243
   line 503: 257
   line 506: 265
   line 507: 270
   line 508: 285
   line 507: 290
   line 510: 293
   line 511: 304
   line 512: 311
   line 514: 315
   line 472: 318
   line 517: 328

  LocalVariableTable: 
   Start  Length  Slot  Name   Signature
   0      340      0    format       Ljava/lang/String;
   5      335      1    array       [C
   15      325      2    list       Ljava/util/ArrayList;
   17      323      3    inLiteral       Z
   20      320      4    buffer       Ljava/lang/StringBuffer;
   23      317      5    previous       Lorg/apache/commons/lang/time/DurationFormatUtils$Token;
   27      313      6    sz       I
   30      310      7    i       I
   39      282      8    ch       C
   64      254      9    value       Ljava/lang/Object;
   304      11      10    token       Lorg/apache/commons/lang/time/DurationFormatUtils$Token;


static int reduceAndCorrect(java.util.Calendar, java.util.Calendar, int, int);
  Code:
   Stack=4, Locals=7, Args_size=4
   0:	aload_1
   1:	iload_2
   2:	iconst_m1
   3:	iload_3
   4:	imul
   5:	invokevirtual	#47; //Method java/util/Calendar.add:(II)V
   8:	aload_1
   9:	iload_2
   10:	invokevirtual	#57; //Method java/util/Calendar.get:(I)I
   13:	istore	4
   15:	aload_0
   16:	iload_2
   17:	invokevirtual	#57; //Method java/util/Calendar.get:(I)I
   20:	istore	5
   22:	iload	4
   24:	iload	5
   26:	if_icmpge	46
   29:	iload	5
   31:	iload	4
   33:	isub
   34:	istore	6
   36:	aload_1
   37:	iload_2
   38:	iload	6
   40:	invokevirtual	#47; //Method java/util/Calendar.add:(II)V
   43:	iload	6
   45:	ireturn
   46:	iconst_0
   47:	ireturn
  LineNumberTable: 
   line 438: 0
   line 439: 8
   line 440: 15
   line 441: 22
   line 442: 29
   line 443: 36
   line 444: 43
   line 446: 46

  LocalVariableTable: 
   Start  Length  Slot  Name   Signature
   0      48      0    start       Ljava/util/Calendar;
   0      48      1    end       Ljava/util/Calendar;
   0      48      2    field       I
   0      48      3    difference       I
   15      33      4    endValue       I
   22      26      5    startValue       I
   36      10      6    newdiff       I


}

